Workbook

Sheet Table
E5: Single Phase
E6: Three Phase
B11: Unit ID | C11: EHO Number | D11: Dimensions | E11: Power Req. | F11: Unit ID | G11: EHO Number | H11: Dimensions | I11: Power Req.
D12: L x W | H12: L x W
B13: Burger/Chipper Units | F13: Confectionery
B14: O'Briens Chipper 1 | C14: 76575 | D14: 6M x 3M | E14: 125A + 32A | F14: Off Beat Donuts 2 | H14: 5M x 3M | I14: 32A + 16A
B15: O'Briens Chipper 2 | C15: 76967 | D15: 4M x 3M | E15: 63A | F15: Off Beat Donuts | G15: 76964 | H15: 5M x 3M | I15: 32A x2
B16: Smash Burger 1 | C16: 76972 | D16: 5M x 3M | E16: 125A | F16: Chocolate Fountain | G16: 76971 | H16: 4M x 3M | I16: 32A x2
B17: Smash Burger 2 | D17: 5M x 3M | E17: 125A | F17: Pick'n'Mix | H17: 5M x 3M | I17: 32A
B18: Loaded Burger | C18: 88122 | D18: 5.5M x 3M | E18: 125A | F18: The Village Kiosk 1 | G18: 76970 | H18: 4M x 3M | I18: 32A
B19: Misc. Food Units | F19: The Village Kiosk 2 | G19: 81824 | H19: 4M x 3M | I19: 16A
B20: Flex Use Airstream | D20: 5M x 3M | E20: 63A | F20: Sprinkles Churros | H20: 5M x 3M | I20: 32A
B21: Angelo's Pizza | C21: 76968 | D21: 4M x 3M | E21: 32A | F21: Sprinkles Desserts | G21: 98859 | H21: 4M x 3M | I21: 63A + 32A
B22: Angelo's Pizza & Pasta | C22: 88124 | D22: 9M x 3M | E22: 63A | F22: Ice Cream Vans
B23: Fried Chicken Truck | C23: 30923 | D23: 6M x 3M | E23: 63A | F23: 231-D | G23: 118984 | H23: 5M x 3M | I23: 32A + 13A
B24: Thindi | C24: 16535 | D24: 5M x 3M | E24: 63A | F24: 201-D | G24: 118985 | H24: 5M x 3M | I24: 32A + 13A
B25: Toasted | C25: 76963 | D25: 4M x 3M | E25: 63A | F25: 152-D | G25: 81822 | H25: 5M x 3M | I25: 32A + 13A
B26: Bun Club Hot Dogs | C26: 76966 | D26: 5M x 3M | E26: 63A | F26: 142-D | G26: 75724 | H26: 5M x 3M | I26: 32A + 13A
B27: Zambrero | C27: 113714 | D27: 6M x 3M | E27: 63A | F27: 09-D | G27: 76925 | H27: 5M x 3M | I27: 32A + 13A
B28: Pitt Bros BBQ | C28: 81939 | D28: 5M x 3M | E28: 63A | F28: 07-D | G28: 76926 | H28: 4M x 3M | I28: 32A + 13A
B29: Lucky Bao Buns | C29: 100979 | D29: 6M x 3M | E29: 32A | F29: 07-RN | G29: 76924 | H29: 5M x 3M | I29: 32A + 13A
B30: Camile Thai 2.0 | C30: 100979 | D30: 6M x 3M | E30: 125A | F30: 05-D | G30: 76922 | H30: 5M x 3M | I30: 13A
B31: Camile Thai | C31: 91759 | D31: 6M x 3M | E31: 125A | F31: 05-WH | G31: 81936 | H31: 5M x 3M | I31: 13A
B32: Coffee/Beverages | F32: 04-D | G32: 76927 | H32: 4M x 3M | I32: 13A
B33: Caffe Duomo 1 | C33: 88120 | D33: 5M x 3M | E33: 32A | F33: 03-D | G33: 76957 | H33: 4M x 3M | I33: 13A
B34: Caffe Duomo 2 | C34: 76961 | D34: 3M x 3M | E34: 32A x2 | F34: 02-WW | G34: 76956 | H34: 5M x 3M | I34: 13A
B35: Caffe Duomo 3 | D35: 3M x 3M | E35: 32A x2 | F35: 02-C | G35: 76959 | H35: 5M x 3M | I35: 13A
B36: Caffe Duomo Van | D36: 5M x 3M | E36: 32A | F36: 01-D | G36: 76960 | H36: 5M x 3M | I36: 13A
B37: Caffe Duomo/Torelli | C37: 76962 | D37: 4M x 3M | E37: 32A x2 | F37: BMC | G37: 76973 | H37: 6M x 3M | I37: 32A + 13A
B38: Freshly Ground Coffee 1 | D38: 3M x 3M | E38: 32A x2 | F38: LD | G38: 78576 | H38: 4M x 3M | I38: 32A + 13A
B39: Freshly Ground Coffee 2 | D39: 4M x 3M | E39: 32A x2 | F39: Pink Bedford | G39: 81823 | H39: 4M x 3M | I39: 32A + 13A
B40: Smoothies & Shakes 1 | C40: 76965 | D40: 5M x 3M | E40: 32A | F40: Yellow Transit | G40: 81935 | H40: 4M x 3M | I40: 32A + 13A
B41: Nobo/Citroen | D41: 4M x 3M | E41: 32A | F41: 88-WX | H41: 6M x 3M | I41: 16A + 13A
F42: Carts & Trikes
F43: Camile Cart | H43: 2M x 3M | I43: 16A
F44: Zambrero Cart | H44: 2M x 3M | I44: 16A
F45: Vespa Cart #1 | H45: 2M x 3M | I45: 13A
F46: Vespa Cart #2 | H46: 2M x 3M | I46: 13A
F47: Sweet Cart | H47: 2M x 3M | I47: 13A

Sheet Live Ops Checklist
B1: 🚚 | C1: 🅿️ | D1: 🧼 | E1: ⚡️ | F1: 📠 | G1: 🧾 | H1: 🌡 | I1: 🧯
A2: Friday
A3: Ideal Homes (Fri-Sunday) | B3: FALSE | C3: FALSE | D3: FALSE | E3: FALSE | F3: FALSE | G3: FALSE | H3: FALSE | I3: FALSE
A4: Camile | B4: FALSE | C4: FALSE | D4: FALSE | E4: TRUE | F4: FALSE | G4: FALSE | H4: FALSE | I4: FALSE
A5: Off Beat | B5: TRUE | C5: TRUE | D5: FALSE | E5: TRUE | F5: TRUE | G5: FALSE | H5: FALSE | I5: FALSE
A6: Toasted | B6: TRUE | C6: FALSE | D6: FALSE | E6: TRUE | F6: FALSE | G6: FALSE | H6: FALSE | I6: FALSE
A7: Coffee | B7: TRUE | C7: TRUE | D7: FALSE | E7: TRUE | F7: TRUE | G7: FALSE | H7: FALSE | I7: FALSE
A9: Saturday | B9: FALSE | C9: FALSE | D9: FALSE | E9: FALSE | F9: FALSE | G9: FALSE | H9: FALSE | I9: FALSE
A10: Merrion Square (Sat-Sun) | B10: FALSE | C10: FALSE | D10: FALSE | E10: FALSE | F10: FALSE | G10: FALSE | H10: FALSE | I10: FALSE
A11: Coffee | B11: FALSE | C11: FALSE | D11: FALSE | E11: FALSE | F11: FALSE | G11: FALSE | H11: FALSE | I11: FALSE
A12: Ice Cream | B12: FALSE | C12: FALSE | D12: FALSE | E12: FALSE | F12: FALSE | G12: FALSE | H12: FALSE | I12: FALSE
A13: Ice Cream | B13: FALSE | C13: FALSE | D13: FALSE | E13: FALSE | F13: FALSE | G13: FALSE | H13: FALSE | I13: FALSE
A14: Fairyhouse (Sat Only) | B14: FALSE | C14: FALSE | D14: FALSE | E14: FALSE | F14: FALSE | G14: FALSE | H14: FALSE | I14: FALSE
A15: Coffee | B15: TRUE | C15: FALSE | D15: FALSE | E15: FALSE | F15: FALSE | G15: FALSE | H15: FALSE | I15: FALSE
... A38: 142-D Van | B38: FALSE | C38: FALSE | D38: FALSE | E38: FALSE | F38: FALSE | G38: FALSE | H38: FALSE | I38: FALSE

Sheet Sheet25

Sheet Punchestown Festival 26
B1: Punchestown Festival 2024
K2: Last Year | L2: FC | M2: Cash | N2: Card | O2: Total | P2: Last Year | Q2: FC | R2: Cash | S2: Card | T2: Total | U2: Last Year | V2: FC | W2: Cash | X2: Card | Y2: Total | Z2: Last Year | AA2: FC | AB2: Cash | AC2: Card | AD2: Total | AE2: Last Year | AF2: FC | AG2: Cash | AH2: Card | AI2: Total
A3: Units | B3: Location | C3: 🚚 | D3: 🅿️ | E3: 🧼 | F3: ⚡️ | G3: 📠 | H3: 🧾 | I3: 🌡 | J3: 🧯 | K3: Tuesday | P3: Wednesday | U3: Thursday | Z3: Friday | AE3: Saturday
A4: Caffe Duomo Trailer | B4: Parade Ring | C4: FALSE | D4: FALSE | E4: FALSE | F4: FALSE | G4: FALSE | H4: FALSE | I4: FALSE | J4: FALSE | O4: =SUM(M4, N4) -> 0 | T4: =SUM(R4, S4) -> 0 | Y4: =SUM(W4:X4) -> 0 | AD4: =SUM(AB4:AC4) -> 0 | AI4: =SUM(AG4:AH4) -> 0
A5: Caffe Duomo Trailer | B5: Parade Ring | C5: FALSE | D5: FALSE | E5: FALSE | F5: FALSE | G5: FALSE | H5: FALSE | I5: FALSE | J5: FALSE | O5: =SUM(M5, N5) -> 0 | T5: =SUM(R5, S5) -> 0 | Y5: =SUM(W5:X5) -> 0 | AD5: =SUM(AB5:AC5) -> 0 | AI5: =SUM(AG5:AH5) -> 0
A6: Off Beat | B6: Parade Ring | C6: FALSE | D6: FALSE | E6: FALSE | F6: FALSE | G6: FALSE | H6: FALSE | I6: FALSE | J6: FALSE | O6: =SUM(M6, N6) -> 0 | T6: =SUM(R6, S6) -> 0 | Y6: =SUM(W6:X6) -> 0 | AD6: =SUM(AB6:AC6) -> 0 | AI6: =SUM(AG6:AH6) -> 0
A7: Kiosk Trailer | B7: Parade Ring | C7: FALSE | D7: FALSE | E7: FALSE | F7: FALSE | G7: FALSE | H7: FALSE | I7: FALSE | J7: FALSE | O7: =SUM(M7, N7) -> 0 | T7: =SUM(R7, S7) -> 0 | Y7: =SUM(W7:X7) -> 0 | AD7: =SUM(AB7:AC7) -> 0 | AI7: =SUM(AG7:AH7) -> 0
A8: Toasted | B8: Ladbrokes | C8: FALSE | D8: FALSE | E8: FALSE | F8: FALSE | G8: FALSE | H8: FALSE | I8: FALSE | J8: FALSE | O8: =SUM(M8:N8) -> 0 | T8: =SUM(R8:S8) -> 0 | Y8: =SUM(W8:X8) -> 0 | AD8: =SUM(AB8:AC8) -> 0 | AI8: =SUM(AG8:AH8) -> 0
A9: Camile | B9: Ladbrokes | C9: FALSE | D9: FALSE | E9: FALSE | F9: FALSE | G9: FALSE | H9: FALSE | I9: FALSE | J9: FALSE | O9: =SUM(M9:N9) -> 0 | T9: =SUM(R9:S9) -> 0 | Y9: =SUM(W9:X9) -> 0 | AD9: =SUM(AB9:AC9) -> 0 | AI9: =SUM(AG9:AH9) -> 0
A10: Pitt Bros | B10: Sky Bar | C10: FALSE | D10: FALSE | E10: FALSE | F10: FALSE | G10: FALSE | H10: FALSE | I10: FALSE | J10: FALSE | O10: =SUM(M10:N10) -> 0 | T10: =SUM(R10:S10) -> 0 | Y10: =SUM(W10:X10) -> 0 | AD10: =SUM(AB10:AC10) -> 0 | AI10: =SUM(AG10:AH10) -> 0
A11: Loaded | B11: Sky Bar | C11: FALSE | D11: FALSE | E11: FALSE | F11: FALSE | G11: FALSE | H11: FALSE | I11: FALSE | J11: FALSE | O11: =SUM(M11:N11) -> 0 | T11: =SUM(R11:S11) -> 0 | Y11: =SUM(W11:X11) -> 0 | AD11: =SUM(AB11:AC11) -> 0 | AI11: =SUM(AG11:AH11) -> 0
A12: Smash | B12: Sky Bar | C12: FALSE | D12: FALSE | E12: FALSE | F12: FALSE | G12: FALSE | H12: FALSE | I12: FALSE | J12: FALSE | O12: =SUM(M12:N12) -> 0 | T12: =SUM(R12:S12) -> 0 | Y12: =SUM(W12:X12) -> 0 | AD12: =SUM(AB12:AC12) -> 0 | AI12: =SUM(AG12:AH12) -> 0
A13: Ice Cream | B13: Parade Ring | C13: FALSE | D13: FALSE | E13: FALSE | F13: FALSE | G13: FALSE | H13: FALSE | I13: FALSE | J13: FALSE | O13: =SUM(M13:N13) -> 0 | T13: =SUM(R13:S13) -> 0 | Y13: =SUM(W13:X13) -> 0 | AD13: =SUM(AB13:AC13) -> 0 | AI13: =SUM(AG13:AH13) -> 0
A14: Ice Cream | B14: Parade Ring | C14: FALSE | D14: FALSE | E14: FALSE | F14: FALSE | G14: FALSE | H14: FALSE | I14: FALSE | J14: FALSE | O14: =SUM(M14:N14) -> 0 | T14: =SUM(R14:S14) -> 0 | Y14: =SUM(W14:X14) -> 0 | AD14: =SUM(AB14:AC14) -> 0 | AI14: =SUM(AG14:AH14) -> 0
A15: Ice Cream | B15: Sky Bar | C15: FALSE | D15: FALSE | E15: FALSE | F15: FALSE | G15: FALSE | H15: FALSE | I15: FALSE | J15: FALSE | O15: =SUM(M15:N15) -> 0 | T15: =SUM(R15:S15) -> 0 | Y15: =SUM(W15:X15) -> 0 | AD15: =SUM(AB15:AC15) -> 0 | AI15: =SUM(AG15:AH15) -> 0
A16: Electric Van | C16: FALSE | D16: FALSE | E16: FALSE | F16: FALSE | G16: FALSE | H16: FALSE | I16: FALSE | J16: FALSE | O16: =SUM(M16:N16) -> 0 | T16: =SUM(R16:S16) -> 0 | Y16: =SUM(W16:X16) -> 0 | AD16: =SUM(AB16:AC16) -> 0 | AI16: =SUM(AG16:AH16) -> 0
A17: 142-D Van | C17: FALSE | D17: FALSE | E17: FALSE | F17: FALSE | G17: FALSE | H17: FALSE | I17: FALSE | J17: FALSE | O17: =SUM(M17:N17) -> 0 | T17: =SUM(R17:S17) -> 0 | Y17: =SUM(W17:X17) -> 0 | AD17: =SUM(AB17:AC17) -> 0 | AI17: =SUM(AG17:AH17) -> 0
A18: Daily Total | K18: =SUM(K4:K17) -> 0 | L18: =SUM(L4:L17) -> 0 | M18: =SUM(M4:M17) -> 0 | N18: =SUM(N4:N17) -> 0 | O18: =SUM(O4:O17) -> 0 | P18: =SUM(P4:P17) -> 0 | Q18: =SUM(Q4:Q17) -> 0 | R18: =SUM(R4:R17) -> 0 | ... AI18: =SUM(AI4:AI17) -> 0
Z19: Zambrero | AD19: =SUM(AB19:AC19) -> 0 | AI19: =SUM(AG19:AH19) -> 0
A20: Overall Total | Z20: Off Beat | AD20: =SUM(AB20:AC20) -> 0 | AI20: =SUM(AG20:AH20) -> 0
A21: =SUM(O18, T18, Y18, AD18, AI18) -> 0 | Z21: Van Carnival | AD21: =SUM(AB21:AC21) -> 0 | AI21: =SUM(AG21:AH21) -> 0
Z22: Van Carnival | AD22: =SUM(AB22:AC22) -> 0 | AI22: =SUM(AG22:AH22) -> 0
A23: Vs Last Year | AC23: Total | AD23: =SUM(AD18:AD22) -> 0 | AH23: Total | AI23: =SUM(AI18:AI22) -> 0
A24: =SUM(K18, P18, U18, Z18, AE18) -> 0
D28: Staff | E28: Number | F28: Name | G28: Number
F29: Shannon
F30: Katelyn
F31: Lauren
F32: Megan
F33: Sam
F34: Megan
F35: Sean
F36: Nicola
F37: Nicola
F38: Leon
F39: Ann
F40: Amanda
... F58: Troy

Sheet Fairyhouse Grand National 
A2: Unit ID | B2: EHO Number | C2: Dimensions | D2: Power Req. | E2: Location (Currently) | F2: Vehicle & Run | G2: Driver | H2: Day
C3: L x W
A4: Loaded Burger | B4: 88122 | C4: 5.5M x 3M | D4: 125A | E4: Leopardstown | F4: INEOS 3 | G4: Tom | H4: Tuesday
A5: Thindi | B5: 16535 | C5: 5M x 3M | D5: 63A | E5: RDS | F5: 1 | G5: Serg | H5: Monday
A6: Toasted | B6: 76963 | C6: 4M x 3M | D6: 32A | E6: RDS | F6: Sprinter Fridge 2 | G6: Simon | H6: Monday
A7: Caffe Duomo 1 | B7: 88120 | C7: 5M x 3M | D7: 32A | E7: RDS | F7: Transit 1 | G7: Robo | H7: Monday
A8: Caffe Duomo 2 | B8: 76961 | C8: 3M x 3M | D8: 32A | E8: RDS | F8: Transit 3 | G8: Robo | H8: Monday
A9: Off Beat Donuts | B9: 76964 | C9: 5M x 3M | D9: 32A | E9: RDS | F9: INEOS 1 | G9: Simon | H9: Monday
A10: Pitt Bros BBQ | B10: 81939 | C10: 5M x 3M | D10: 63A | E10: RDS | F10: Custom 2 | G10: Kian | H10: Monday
A11: Fried Chicken Truck | B11: 30923 | C11: 6M x 3M | D11: 125A | E11: Unit | G11: Serg | H11: Monday
A12: Pink Bedford | B12: 81823 | C12: 4M x 3M | D12: 32A | E12: Unit | G12: Serg | H12: Tuesday
A13: Smash Burger 1 | B13: 76972 | C13: 5M x 3M | D13: 125A | E13: Punchestown | F13: Transit 3 | G13: Robo | H13: Tuesday
A14: Sprinkles Churros | B14: 98859 | C14: 5M x 3M | D14: 32A | E14: RDS | F14: INEOS 2 | G14: Tom | H14: Monday
A15: BMC | B15: 76973 | C15: 6M x 3M | D15: 32A + 13A | E15: Unit | G15: Serg | H15: Tuesday
A16: Caffe Duomo/Vintage | B16: 76962 | C16: 4M x 3M | D16: 32A x2 | E16: RDS | F16: Tow Truck 1 | G16: Tom | H16: Monday
A17: The Village Kiosk 1 | B17: 76970 | C17: 4M x 3M | D17: 32A | E17: RDS | F17: Drive on 1 | G17: Kian | H17: Monday
A18: The Village Kiosk 2 | B18: 81824 | C18: 4M x 3M | D18: 16A | E18: RDS | F18: Drive on 1 | G18: Kian | H18: Monday

Sheet DRF 26
A1: DRF 2025 | I1: Stock & Orders
A2: Stall/Unit Name | B2: Location | C2: 🅿️ | D2: 🧽 | E2: ⚡️ | F2: 💻 | G2: 🧯 | H2: 👥 | I2: Sysco | J2: Camile | K2: ReadyChef | L2: BWG | M2: Pitt Bros | N2: Sandwiches | O2: Bretzel
A3: Caffe Duomo | B3: Outside Gates | C3: FALSE | D3: FALSE | E3: FALSE | F3: FALSE | G3: FALSE | H3: FALSE | I3: TRUE | J3: TRUE | K3: FALSE | L3: FALSE | M3: TRUE | N3: FALSE | O3: TRUE
A4: toasted | B4: Marquee | C4: TRUE | D4: FALSE | E4: FALSE | F4: FALSE | G4: FALSE | H4: FALSE | I4: TRUE | J4: TRUE | K4: FALSE | L4: FALSE | M4: TRUE | N4: FALSE | O4: TRUE
A5: Pitt bros | B5: Marquee | C5: TRUE | D5: FALSE | E5: FALSE | F5: FALSE | G5: FALSE | H5: FALSE | I5: TRUE | J5: TRUE | K5: FALSE | L5: FALSE | M5: TRUE | N5: FALSE | O5: TRUE
A6: Thindi | B6: Marquee | C6: TRUE | D6: FALSE | E6: FALSE | F6: FALSE | G6: FALSE | H6: FALSE | I6: TRUE | J6: TRUE | K6: FALSE | L6: FALSE | M6: TRUE | N6: FALSE | O6: TRUE
A7: Kiosk | B7: Nightclub Doors | C7: FALSE | D7: FALSE | E7: FALSE | F7: FALSE | G7: FALSE | H7: FALSE | I7: TRUE | J7: TRUE | K7: FALSE | L7: FALSE | M7: TRUE | N7: FALSE | O7: TRUE
A8: Coffee van | B8: Parade Ring | C8: TRUE | D8: FALSE | E8: FALSE | F8: FALSE | G8: FALSE | H8: FALSE | I8: TRUE | J8: TRUE | K8: FALSE | L8: FALSE | M8: TRUE | N8: FALSE | O8: TRUE
A9: Offbeat | B9: Parade Ring | C9: TRUE | D9: FALSE | E9: FALSE | F9: FALSE | G9: FALSE | H9: FALSE | I9: TRUE | J9: TRUE | K9: FALSE | L9: FALSE | M9: TRUE | N9: FALSE | O9: TRUE
A10: Caffe duomo | B10: Saddling Stalls | C10: FALSE | D10: FALSE | E10: FALSE | F10: FALSE | G10: FALSE | H10: FALSE | I10: TRUE | J10: TRUE | K10: FALSE | L10: FALSE | M10: TRUE | N10: FALSE | O10: TRUE
A11: Fried chicken | B11: Saddling Stalls | C11: TRUE | D11: FALSE | E11: FALSE | F11: FALSE | G11: FALSE | H11: FALSE | I11: TRUE | J11: TRUE | K11: FALSE | L11: FALSE | M11: TRUE | N11: FALSE | O11: TRUE
A12: Camile | B12: Saddling Stalls | C12: TRUE | D12: FALSE | E12: FALSE | F12: FALSE | G12: FALSE | H12: FALSE | I12: TRUE | J12: TRUE | K12: FALSE | L12: FALSE | M12: TRUE | N12: FALSE | O12: TRUE
A13: Loaded | B13: Saddling Stalls | C13: TRUE | D13: FALSE | E13: FALSE | F13: FALSE | G13: FALSE | H13: FALSE | I13: TRUE | J13: TRUE | K13: FALSE | L13: FALSE | M13: TRUE | N13: FALSE | O13: TRUE
A14: Bao Bun | B14: Saddling Stalls | C14: FALSE | D14: FALSE | E14: FALSE | F14: FALSE | G14: FALSE | H14: FALSE | I14: TRUE | J14: TRUE | K14: FALSE | L14: FALSE | M14: TRUE | N14: FALSE | O14: TRUE
A18: To Do List
C35: Position
A36: Stall/Unit Name | B36: Location | C36: 1 | D36: 2 | E36: 3 | F36: 4 | G36: 5 | H36: 6 | I36: 7
A37: Caffe Duomo | B37: Outside Gates | C37: Gwen | D37: Layla
A38: Toasted | B38: Marquee | C38: Nicola | D38: Mustafa | E38: Lorita
A39: Pitt bros | B39: Marquee | C39: Lauren | D39: Megan | F39: Abbie | G39: Berkay
A40: Thindi | B40: Marquee | C40: Megan | D40: Jodie | E40: Sophie
A41: Kiosk | B41: Nightclub Doors | C41: Kayla | D41: Layla
A42: Coffee van | B42: Parade Ring | C42: Janet | D42: Nicola | E42: Chloe
A43: Offbeat | B43: Parade Ring | C43: Tammy | D43: Renee | E43: Cuma
A44: Caffe duomo | B44: Saddling Stalls | C44: Emma p | D44: Nicole | E44: Vishnu
A45: Fried chicken | B45: Saddling Stalls | C45: Triona | D45: Paloma | E45: Alan
A46: Camile | B46: Saddling Stalls | C46: Sam | E46: Rachel | F46: Toni | G46: Amanda
A47: Loaded | B47: Saddling Stalls | C47: Ann | D47: Jess | E47: Leanna | F47: Michelle | G47: Ricky | H47: Ash | I47: Shane
A48: Bao Bun | B48: Saddling Stalls | C48: Marco | D48: Dave
A51: Confirmed | F51: Position
A52: Wesley | B52: KP | D52: Stall/Unit Name | E52: Location | F52: 1 | G52: 2 | H52: 3 | I52: 4 | J52: 5 | K52: 6 | L52: 7
A53: Lidiane | B53: Serving | D53: Caffe Duomo | E53: Outside Gates
A54: Alan | B54: KP | D54: Toasted | E54: Marquee | F54: Lorita | G54: Nicola | H54: Ava
A55: Felipe | B55: Serving | D55: Pitt bros | E55: Marquee | F55: Lauren | G55: Katelyn | H55: Megan | I55: Abbie
A56: Paloma | B56: Serving/Prep | D56: Thindi | E56: Marquee | F56: Dani | G56: Megan | H56: Emily
A57: Camila | B57: Serving/Prep | D57: Kiosk | E57: Nightclub Doors | F57: Kayla | G57: Layla
A58: Giovanna | B58: Serving | C58: ✅ | D58: Coffee van | E58: Parade Ring | F58: Janet | G58: Chloe | H58: Paloma
A59: Marco | B59: Chef/HACCP | C59: ✅ | D59: Offbeat | E59: Parade Ring | F59: Tammy | G59: Renee | H59: Kadie
A60: Eduardo | B60: KP/Prep | D60: Caffe duomo | E60: Saddling Stalls | F60: Emma | G60: Tracey | H60: Shane
D61: Fried chicken | E61: Saddling Stalls | F61: Alan | G61: Triona | H61: Marco
D62: Camile | E62: Saddling Stalls | F62: Sam | G62: Amanda | H62: Rachel | I62: Abbie | J62: Dave
D63: Loaded | E63: Saddling Stalls | F63: Ann | G63: Michelle | H63: Leanna | I63: Jess | J63: Mandy
D64: Bao Bun | E64: Saddling Stalls

Sheet Google Engage
A1: Google Engage | I1: Stock & Orders
A2: Stall/Unit Name | B2: Location | C2: 🅿️ | D2: 🧽 | E2: ⚡️ | F2: 💻 | G2: 🧯 | H2: 👥 | I2: Sysco | J2: Camile | K2: ReadyChef | L2: BWG | M2: Pitt Bros | O2: Sandwiches | P2: Bretzel | Q2: Coffee Perfection
A3: Pizza Pasta | B3: Exit E | C3: FALSE | D3: FALSE | E3: FALSE | F3: FALSE | G3: FALSE | H3: FALSE | I3: FALSE | J3: FALSE | K3: FALSE | L3: FALSE | M3: FALSE | N3: FALSE | O3: FALSE | P3: FALSE | Q3: FALSE
A4: Pitt Bro's | C4: TRUE | D4: FALSE | E4: TRUE | F4: TRUE | G4: TRUE | H4: FALSE | I4: FALSE | J4: FALSE | K4: FALSE | L4: FALSE | M4: FALSE | N4: FALSE | O4: FALSE | P4: FALSE | Q4: FALSE
A5: Thindi | C5: TRUE | D5: FALSE | E5: FALSE | F5: TRUE | G5: TRUE | H5: FALSE | I5: FALSE | J5: FALSE | K5: FALSE | L5: FALSE | M5: FALSE | N5: FALSE | O5: FALSE | P5: FALSE | Q5: FALSE
A6: Toasted | C6: TRUE | D6: FALSE | E6: FALSE | F6: TRUE | G6: TRUE | H6: FALSE | I6: FALSE | J6: FALSE | K6: FALSE | L6: FALSE | M6: FALSE | N6: FALSE | O6: FALSE | P6: FALSE | Q6: FALSE
A7: Zambrero | C7: TRUE | D7: FALSE | E7: TRUE | F7: TRUE | G7: TRUE | H7: FALSE | I7: FALSE | J7: FALSE | K7: FALSE | L7: FALSE | M7: FALSE | N7: FALSE | O7: FALSE | P7: FALSE | Q7: FALSE
A8: Off Beat | C8: TRUE | D8: FALSE | E8: TRUE | F8: TRUE | G8: TRUE | H8: FALSE | I8: FALSE | J8: FALSE | K8: FALSE | L8: FALSE | M8: FALSE | N8: FALSE | O8: FALSE | P8: FALSE | Q8: FALSE
A9: Pizza Pasta | C9: TRUE | D9: FALSE | E9: TRUE | F9: TRUE | G9: TRUE | H9: FALSE | I9: FALSE | J9: FALSE | K9: FALSE | L9: FALSE | M9: FALSE | N9: FALSE | O9: FALSE | P9: FALSE | Q9: FALSE
A10: Cookie Bro | C10: TRUE | D10: FALSE | E10: TRUE | F10: TRUE | G10: FALSE | H10: FALSE | I10: FALSE | J10: FALSE | K10: FALSE | L10: FALSE | M10: FALSE | N10: FALSE | O10: FALSE | P10: FALSE | Q10: FALSE
A11: Popcorn | C11: TRUE | D11: FALSE | E11: FALSE | F11: TRUE | G11: FALSE | H11: FALSE | I11: FALSE | J11: FALSE | K11: FALSE | L11: FALSE | M11: FALSE | N11: FALSE | O11: FALSE | P11: FALSE | Q11: FALSE
A12: Candyfloss | C12: TRUE | D12: FALSE | E12: FALSE | F12: TRUE | G12: FALSE | H12: FALSE | I12: FALSE | J12: FALSE | K12: FALSE | L12: FALSE | M12: FALSE | N12: FALSE | O12: FALSE | P12: FALSE | Q12: FALSE
C13: FALSE | D13: FALSE | E13: FALSE | F13: FALSE | G13: FALSE | H13: FALSE | I13: FALSE | J13: FALSE | K13: FALSE | L13: FALSE | M13: FALSE | N13: FALSE | O13: FALSE | P13: FALSE | Q13: FALSE
C14: FALSE | D14: FALSE | E14: FALSE | F14: FALSE | G14: FALSE | H14: FALSE | I14: FALSE | J14: FALSE | K14: FALSE | L14: FALSE | M14: FALSE | N14: FALSE | O14: FALSE | P14: FALSE | Q14: FALSE
C15: FALSE | D15: FALSE | E15: FALSE | F15: FALSE | G15: FALSE | H15: FALSE | I15: FALSE | J15: FALSE | K15: FALSE | L15: FALSE | M15: FALSE | N15: FALSE | O15: FALSE | P15: FALSE | Q15: FALSE
C16: FALSE | D16: FALSE | E16: FALSE | F16: FALSE | G16: FALSE | H16: FALSE | I16: FALSE | J16: FALSE | K16: FALSE | L16: FALSE | M16: FALSE | N16: FALSE | O16: FALSE | P16: FALSE | Q16: FALSE
G21: Off Beat Donuts
A22: Zambrero | B22: LS NOTES | G22: EVENT MENU: (Donuts) | M22: Unit | N22: Number of staff | O22: Staff
A23: EVENT MENU: (Mexican) | M23: Pitt Bros | N23: 6 | O23: Lauren | P23: Ann | Q23: Mellisa | R23: Megan | S23: Katelyn | T23: Caoi
G24: Red Velvet (V) | K24: 2475 total servings | M24: Thindi | N24: 4 | O24: Megan | P24: Katelyn | Q24: Ava | R24: Sahill
A25: Burrito or Bowl | M25: Zambrero 8pm | N25: 8 | O25: Ryan | P25: Stacey | Q25: Lokesh | R25: Clara | S25: Sam | T25: Amanda
A26: Chicken | G26: Glazed (V) | M26: Pizza Pasta | N26: 6 | O26: Triona | P26: Lorrita | Q26: Tracey | R26: Mandy | S26: Marco
A27: Chilli “zin” carne (V, VG) | G27: Sprinkles (V) | M27: Toasted 9:45 | N27: 3 | O27: Janet | P27: Dean | Q27: Chaitanya
A28: WHITE RICE, PINTO BEANS, GUACAMOLE (with cos lettuce and lime), CHEESE, SOUR CREAM, JALAPENOS, SALSA (tomato, corn, onion) | G28: Unicorn (V) | M28: Cookie | N28: 3 | O28: Kadie | P28: Mariana | Q28: Chelsea
G29: Cookies & Cream (V) | M29: Popcorn | N29: 3 | O29: Karl | P29: Leah | Q29: Rachel
A30: Choice of Sauce | G30: Vegan Chocolate Cookie | M30: Candy floss | N30: 2 | O30: Dylan | P30: Kayleigh
A31: SECRET BBQ (Tamarind, cardamom and ginger) | G31: Vegan Caramel Speculoos | M31: Donut | N31: 3 | O31: Shannon | P31: Molly
A32: GARLIC (Roasted garlic, minced garlic, and creamy mayonnaise) | G32: Single donuts served in a bag - checking whether tray available | N32: =SUM(N23:N31) -> 38
A33: CHIPOTLE (Chipotle pepper, cayenne pepper, and lime) | G33: Can we please have a couple of vegan options | N33: Hot dog
A34: VERDE (Jalapeño peppers, mango, lemon, and coriander) | G34: Load in Friday 20th Feb Hall 1 | N34: Camile
N35: 42
A36: Side | G36: Cookiebro (Churros)
A37: Corn Tortillas with guacamole / salsa (V, VG) | G37: EVENT MENU: (Stuffed cookies)
K38: 1260 total servings
A39: Notes | G39: Oreo
A40: 7 Nov burrito was better filled than at horse show - please be consistent | G40: Crunchie
A41: Use smaller wrap to reduce burrito size | G41: Freddo | M41: Wages
A42: Tortilla chips come in big bag which will cause a lot of waste, so can we serve in a tray with some guacamole & salsa rather than whole bag | G42: Rollo | M42: Diego | N42: Braz | O42: Chelsea | P42: 100 | Q42: ✅
A43: Load in Friday 20th Feb Hall 1 | G43: Milky Bar | M43: Octa Sai | N43: Braz | O43: Mariana | P43: 105
G44: Lotus biscoff | M44: Wesley | N44: Braz | O44: Ahmed | P44: Braz
A45: Pizza & Pasta | G45: Load in TBC Hall 2 | L45: ✅ | M45: Katelyn | N45: 100 | O45: Nicolas | P45: Braz
A46: EVENT MENU: (Pizza & Pasta) | L46: ✅ | M46: Megan | N46: 100 | O46: Molly | P46: 100 | Q46: ✅
G47: Thindi | M47: Dean | N47: Paid | O47: Helen | P47: Braz
A48: PASTA & PIZZA BY THE SLICE | G48: EVENT MENU: (Indian) | L48: ✅ | M48: Ava | N48: 100 | O48: Gig | P48: 105
M49: Sahil | N49: 105 | O49: Chaitanya | P49: 105
A50: Penne Pomodoro (V, VG) (1 may contain 12) | G50: SPICE BAG | M50: Leopoldo | N50: Braz | O50: Leide | P50: Braz
A51: Tomato sauce with your choice of topping - aubergine, artichoke or nduja | L51: ✅ | M51: Dylan | N51: 100 | O51: Janet | P51: 100 | Q51: ✅
G52: CURRY BOWL | L52: ✅ | M52: Lauren | N52: 100
A53: Calabrian Pizza (1,6 may contain 9,12) | G53: Butter chicken curry bowl, Rice, Aloo Spinach | M53: Megan | N53: Paid
A54: Nduja, salami, San Marzano tomatoes, mozzarella, basil & chilli oil | G54: OR | M54: Katelyn | N54: Paid
G55: Chana masala curry bowl, Rice, Aloo Spinach(V, VG) | L55: ✅ | M55: Mellisa | N55: 100 | P55: 2300
A56: Margherita Pizza (V) (1,6 may contain 12) | L56: ✅ | M56: Ann | N56: 100
A57: San Marzano tomatoes, mozzarella, & basil | B57: Serve pizza by slice rather than whole pizza - how many slices? 4 | G57: Samosa | M57: Calio | N57: 105
L58: ✅ | M58: Kayleigh | N58: 100
A59: Vegetali Pizza (V) (1,6 may contain 12) | G59: Notes: | L59: ✅ | M59: Shannon | N59: 100
A60: Roasted artichokes & aubergines, San Marzano tomatoes, mozzarella & basil | G60: Food was really tasty but portion size at Horse show far too big | L60: ✅ | M60: Rachel | N60: 100
L61: ✅ | M61: Leah | N61: 100
A62: V - vegetarian | G62: Load in Friday 20th Feb Hall 4 | L62: ✅ | M62: Karl | N62: 100
A63: VG – vegan | L63: ✅ | M63: Triona | N63: 100
G64: Toasted | L64: ✅ | M64: Tracey | N64: 100
A65: 1: Wheat 2: Crustaceans 3: Eggs 4: Fish 5: Soybeans 6: Milk 7: Peanuts | G65: EVENT MENU: | L65: ✅ | M65: Mandy | N65: 100
A66: 8: Nuts 9: Celery 10: Mustard 11: Sesame 12: Sulphites 13: Lupin 14: Molluscs | M66: Lucio | N66: Braz
G67: Cheese Toastie (V) | L67: ✅ | M67: Lorrita | N67: 100
A68: If you have any dietary requirements or allergies please speak to a member of staff. | M68: Marco | N68: 105
D69: No vegan toastie needed | G69: Notes: | M69: Jerry | N69: Braz
A70: Notes: | G70: Good toastie but too big, serve half | M70: Luciana | N70: Braz
A71: Half portion in smaller bowls | G71: Load in Friday 20th Feb Hall 1 | M71: Ryan | N71: Zam
A72: Add some toppings or parsley to make look more appetising | M72: Clara | N72: Zam
A73: Load in Friday 20th Feb Hall 1 | M73: Tomas | N73: Zam
M74: Abu | N74: Zam
L75: ✅ | M75: Stacey | N75: 100
L76: ✅ | M76: Amanda | N76: 100
A77: Pitt Bros | M77: Paloma | N77: Braz
A78: EVENT MENU: (BBQ) | L78: ✅ | M78: Sam | N78: 100
M79: Jess | N79: Braz
A80: Pulled Pork Bun | L80: ✅ | M80: Kadie | N80: 100
A81: Slow smoked pulled pork, house pickles, chipotle slaw & Pitt Bros proper meat sauce
A82: Pitt Bros Bacon Burger
A83: Beef patty, white cheddar cheese, smoked bacon jus & caramelised onion relish
A84: Piggy Fries
A85: Fries topped with our smoked pulled pork, Pitt Bros proper meat sauce & chipotle mayo
A86: Mac & cheese (V) | D86: Need allergies for the sides
A87: Chipotle slaw (V)
A88: Load in Monday 5pm Hall 4

Sheet EP 25
A1: Electric Picnic | I1: Stock & Orders
A2: Stall/Unit Name | B2: Location | C2: 🅿️ | D2: 🧽 | E2: ⚡️ | F2: 💻 | G2: 🧯 | H2: 👥 | I2: Sysco | J2: Camile | K2: ReadyChef | L2: BWG | M2: Pitt Bros | N2: Sandwiches | O2: Bretzel | P2: Coffee Perfection | R2: Sleeping Arrangements
A3: Pizza Pasta | B3: Exit E | C3: FALSE | D3: FALSE | E3: FALSE | F3: FALSE | G3: FALSE | H3: FALSE | I3: FALSE | J3: FALSE | K3: FALSE | L3: FALSE | M3: FALSE | N3: FALSE | O3: FALSE | P3: FALSE | R3: Dads | S3: 4
A4: Pitt Bro's | B4: TBC | C4: FALSE | D4: FALSE | E4: FALSE | F4: FALSE | G4: FALSE | H4: FALSE | I4: TRUE | J4: TRUE | K4: FALSE | L4: TRUE | M4: TRUE | N4: FALSE | O4: TRUE | P4: TRUE | R4: Fiat | S4: 6
A5: Caffe Duomo | B5: TBC | C5: FALSE | D5: FALSE | E5: FALSE | F5: FALSE | G5: FALSE | H5: FALSE | I5: TRUE | J5: TRUE | K5: FALSE | L5: TRUE | M5: TRUE | N5: FALSE | O5: TRUE | P5: TRUE | R5: Transit | S5: 2
A6: Camile Thai | B6: TBC | C6: FALSE | D6: FALSE | E6: FALSE | F6: FALSE | G6: FALSE | H6: FALSE | I6: TRUE | J6: TRUE | K6: FALSE | L6: TRUE | M6: TRUE | N6: FALSE | O6: TRUE | P6: TRUE | R6: Showers | S6: 4
A7: Zambrero | B7: TBC | C7: FALSE | D7: FALSE | E7: FALSE | F7: FALSE | G7: FALSE | H7: FALSE | I7: TRUE | J7: TRUE | K7: FALSE | L7: TRUE | M7: TRUE | N7: FALSE | O7: TRUE | P7: TRUE | R7: VW | S7: 2
A8: Smash Burger 1 | B8: TBC | C8: FALSE | D8: FALSE | E8: FALSE | F8: FALSE | G8: FALSE | H8: FALSE | I8: TRUE | J8: TRUE | K8: FALSE | L8: TRUE | M8: TRUE | N8: FALSE | O8: TRUE | P8: TRUE | R8: Man Van | S8: 2
A9: Loaded Burger | B9: TBC | C9: FALSE | D9: FALSE | E9: FALSE | F9: FALSE | G9: FALSE | H9: FALSE | I9: TRUE | J9: TRUE | K9: FALSE | L9: TRUE | M9: TRUE | N9: FALSE | O9: TRUE | P9: TRUE | R9: Box Body | S9: 4
A10: Pizza/Pasta | B10: TBC | C10: FALSE | D10: FALSE | E10: FALSE | F10: FALSE | G10: FALSE | H10: FALSE | I10: FALSE | J10: TRUE | K10: FALSE | L10: TRUE | M10: TRUE | N10: FALSE | O10: TRUE | P10: TRUE | R10: Bedford | S10: 2
A11: Thindi | B11: TBC | C11: FALSE | D11: FALSE | E11: FALSE | F11: FALSE | G11: FALSE | H11: FALSE | I11: FALSE | J11: TRUE | K11: FALSE | L11: TRUE | M11: TRUE | N11: FALSE | O11: TRUE | P11: TRUE | R11: Total Beds | S11: =SUM(S3:S10) -> 26
A12: Ice Cream Vans | B12: TBC | C12: FALSE | D12: FALSE | E12: TRUE | F12: FALSE | G12: FALSE | H12: FALSE | I12: FALSE | J12: TRUE | K12: FALSE | L12: TRUE | M12: TRUE | N12: FALSE | O12: TRUE | P12: TRUE
A13: Ice Cream Unit 1 | B13: TBC | C13: FALSE | D13: FALSE | E13: FALSE | F13: FALSE | G13: FALSE | H13: FALSE | I13: FALSE | J13: TRUE | K13: FALSE | L13: TRUE | M13: TRUE | N13: FALSE | O13: TRUE | P13: TRUE
A14: Ice Cream Unit 2 | B14: TBC | C14: FALSE | D14: FALSE | E14: FALSE | F14: FALSE | G14: FALSE | H14: FALSE | I14: FALSE | J14: TRUE | K14: FALSE | L14: TRUE | M14: TRUE | N14: FALSE | O14: TRUE | P14: TRUE
A15: Ice Cream Unit 3 | B15: TBC | C15: FALSE | D15: FALSE | E15: FALSE | F15: FALSE | G15: FALSE | H15: FALSE | I15: FALSE | J15: TRUE | K15: FALSE | L15: TRUE | M15: TRUE | N15: FALSE | O15: TRUE | P15: TRUE
C16: FALSE | D16: FALSE | E16: FALSE | F16: FALSE | G16: FALSE | H16: FALSE | I16: FALSE | J16: TRUE | K16: FALSE | L16: TRUE | M16: TRUE | N16: FALSE | O16: TRUE | P16: TRUE | U16: Staff Names
U18: Staff Id | V18: Group Chat | W18: First Name | X18: Last Name | Y18: Phone Number | Z18: Email | AA18: Experience | AB18: Days Available
AB19: Thursday | AC19: Friday | AD19: Saturday | AE19: Sunday
A20: Unit ID | D20: Opening Hours | K20: Location | V20: FALSE | AB20: FALSE | AC20: FALSE | AD20: FALSE | AE20: FALSE
B21: # Staff | C21: Hrs | D21: # Staff | E21: Hrs | F21: # Staff | G21: Hrs | H21: # Staff | I21: Hrs | J21: # Staff | U21: 1 | V21: TRUE | W21: Thomas | X21: OBrien | Y21: 852402555 | Z21: thomas@obrieneventcatering.com | AB21: FALSE | AC21: FALSE | AD21: FALSE | AE21: FALSE
B22: Thursday | D22: Friday | F22: Saturday | H22: Sunday | J22: Monday | U22: =U21+1 -> 2 | V22: TRUE | W22: Patrick | X22: OBrien | Y22: 876192047 | AB22: FALSE | AC22: FALSE | AD22: FALSE | AE22: FALSE
A23: Pitt Bro's | B23: 2 | C23: 2 | D23: 5 | E23: 12 | F23: 6 | G23: 15 | H23: 6 | I23: 15 | K23: Main Arena | U23: =U22+1 -> 3 | V23: TRUE | W23: Kelly | X23: OBrien | Y23: 857106808 | AB23: FALSE | AC23: TRUE | AD23: TRUE | AE23: TRUE
A24: Caffe Duomo | B24: 2 | C24: 2 | D24: 5 | E24: 12 | F24: 6 | G24: 15 | H24: 6 | I24: 15 | K24: Main Arena | U24: =U23+1 -> 4 | V24: TRUE | W24: Flora | X24: OBrien | Y24: 872416613 | Z24: flora@obrieneventcatering.com | AB24: FALSE | AC24: FALSE | AD24: FALSE | AE24: FALSE
A25: Camile Thai | B25: 2 | C25: 2 | D25: 5 | E25: 12 | F25: 6 | G25: 15 | H25: 6 | I25: 15 | K25: Main Arena | U25: =U24+1 -> 5 | V25: TRUE | W25: Bridget | X25: Reid | AB25: FALSE | AC25: FALSE | AD25: FALSE | AE25: FALSE
A26: Zambrero | B26: 3 | C26: 4 | D26: 7 | E26: 12 | F26: 7 | G26: 15 | H26: 7 | I26: 15 | K26: Main Arena | U26: =U25+1 -> 6 | V26: TRUE | W26: Nicole | X26: Brady | AB26: FALSE | AC26: FALSE | AD26: FALSE | AE26: FALSE
A27: Smash Burger 1 | B27: 3 | C27: 2 | D27: 7 | E27: 12 | F27: 8 | G27: 15 | H27: 8 | I27: 15 | K27: Main Arena | U27: =U26+1 -> 7 | V27: TRUE | W27: Aaron | X27: Brady | AB27: FALSE | AC27: FALSE | AD27: FALSE | AE27: FALSE
A28: Loaded Burger | B28: 2 | C28: 2 | D28: 6 | E28: 12 | F28: 7 | G28: 15 | H28: 7 | I28: 15 | K28: Main Arena | U28: =U27+1 -> 8 | V28: TRUE | W28: Maisy | X28: Brady | AB28: FALSE | AC28: TRUE | AD28: TRUE | AE28: TRUE
A29: Pizza/Pasta | B29: 2 | C29: 2 | D29: 6 | E29: 12 | F29: 7 | G29: 15 | H29: 7 | I29: 15 | K29: Main Arena | U29: =U28+1 -> 9 | V29: TRUE | W29: Cian | X29: Ritchie | Y29: 877073894 | AA29: Ice Cream | AB29: FALSE | AC29: TRUE | AD29: TRUE | AE29: TRUE
A30: Thindi | B30: 2 | C30: 2 | D30: 6 | E30: 12 | F30: 7 | G30: 15 | H30: 7 | I30: 15 | K30: Main Arena | U30: =U29+1 -> 10 | V30: TRUE | W30: Cian | X30: Whelan | Y30: 877073894 | AA30: Ice Cream | AB30: FALSE | AC30: TRUE | AD30: TRUE | AE30: TRUE
A31: Ice Cream Vans | K31: Main Arena | U31: =U30+1 -> 11 | V31: TRUE | W31: Nicola | X31: Fennell | AB31: TRUE | AC31: TRUE | AD31: TRUE | AE31: TRUE
A32: Ice Cream Unit 1 | B32: 1 | C32: 1 | D32: 2 | E32: 12 | F32: 2 | G32: 15 | H32: 2 | I32: 15 | K32: Main Arena | U32: =U31+1 -> 12 | V32: TRUE | W32: Amanda | X32: Murray | AB32: TRUE | AC32: TRUE | AD32: TRUE | AE32: TRUE
A33: Ice Cream Unit 2 | B33: 1 | C33: 1 | D33: 2 | E33: 12 | F33: 2 | G33: 15 | H33: 2 | I33: 15 | K33: Main Arena | U33: =U32+1 -> 13 | V33: TRUE | W33: Donna | X33: ONeill | AB33: TRUE | AC33: TRUE | AD33: TRUE | AE33: TRUE
A34: Ice Cream Unit 3 | B34: 1 | C34: 1 | D34: 1 | E34: 12 | F34: 2 | G34: 15 | H34: 2 | I34: 15 | K34: Main Arena | U34: =U33+1 -> 14 | V34: TRUE | W34: Mandy | X34: Whelan | AB34: TRUE | AC34: TRUE | AD34: TRUE | AE34: TRUE
B35: 1 | C35: 1 | D35: 1 | E35: 12 | F35: 1 | G35: 15 | H35: 1 | I35: 15 | K35: Main Arena | U35: =U34+1 -> 15 | V35: TRUE | W35: Brooke | X35: ONeill | AB35: TRUE | AC35: TRUE | AD35: TRUE | AE35: TRUE
B36: 1 | C36: 1 | D36: 1 | E36: 12 | F36: 2 | G36: 15 | H36: 2 | I36: 15 | K36: Main Arena | U36: =U35+1 -> 16 | V36: TRUE | W36: Emily | X36: Whelan | AB36: TRUE | AC36: TRUE | AD36: TRUE | AE36: TRUE
A37: Stock Boys | B37: 4 | C37: 10 | D37: 5 | E37: 12 | F37: 5 | G37: 12 | H37: 5 | I37: 12 | K37: Main Arena | U37: =U36+1 -> 17 | V37: TRUE | W37: Karla | X37: Brady | AB37: FALSE | AC37: TRUE | AD37: TRUE | AE37: TRUE
U38: =U37+1 -> 18 | V38: TRUE | W38: Dylan | X38: ODriscoll | Y38: 857645690 | Z38: dylanodriscoll00@gmail.com | AB38: FALSE | AC38: TRUE | AD38: TRUE | AE38: TRUE
U39: =U38+1 -> 19 | V39: TRUE | W39: Darren | X39: ODriscoll | Y39: 858159925 | Z39: darrenodriscoll2019@gmail.com | AA39: Food | AB39: FALSE | AC39: TRUE | AD39: TRUE | AE39: TRUE
U40: =U39+1 -> 20 | V40: TRUE | W40: Jade | X40: Malone | Y40: 852022709 | Z40: jademalone1993@live.com | AA40: Food | AB40: FALSE | AC40: TRUE | AD40: TRUE | AE40: TRUE
A41: Totals Needed | B41: =SUM(B23:B40) -> 27 | C41: =SUM(C23:C40) -> 33 | D41: =SUM(D23:D40) -> 59 | E41: =SUM(E23:E40) -> 168 | F41: =SUM(F23:F40) -> 68 | G41: =SUM(G23:G40) -> 207 | H41: =SUM(H23:H40) -> 68 | I41: =SUM(I23:I40) -> 207 | J41: =SUM(J23:J40) -> 0 | U41: =U40+1 -> 21 | V41: TRUE | W41: Louise | X41: Malone | Y41: 857302419 | Z41: louisemalone21@gmail.com | AA41: Food | AB41: FALSE | AC41: FALSE | AD41: TRUE | AE41: TRUE
U42: =U41+1 -> 22 | V42: TRUE | W42: Jennifer | X42: ONeill | Y42: 874682865 | Z42: jennyoneill1990@hotmail.com | AA42: Both | AB42: FALSE | AC42: TRUE | AD42: TRUE | AE42: TRUE
A43: Exodus | E43: Takings | U43: =U42+1 -> 23 | V43: TRUE | W43: Molly | X43: Clarke Bowes | Y43: 871897979 | Z43: mollyclarkebowess@icloud.com | AA43: Ice cream /Coffee | AB43: FALSE | AC43: TRUE | AD43: TRUE | AE43: TRUE
A44: Vehicle | B44: Towing Vehicle | C44: Driver | E44: Stall/Unit Name | F44: Location | G44: Day | J44: Total | K44: FC | U44: =U43+1 -> 24 | V44: TRUE | W44: Abbie | X44: Bowes | Y44: 857629296 | Z44: abbyclarkebowes@icloud.com | AA44: Ice cream / Coffee | AB44: FALSE | AC44: TRUE | AD44: TRUE | AE44: TRUE
A45: Pitt Bro's | B45: 152 | C45: Chris | E45: Pizza Pasta | F45: Exit E | G45: Friday | H45: Saturday | I45: Sunday | U45: =U44+1 -> 25 | V45: TRUE | W45: Conal | X45: McEneff | Y45: 872929079 | Z45: conalmc2005@icloud.com | AA45: Food | AB45: FALSE | AC45: TRUE | AD45: TRUE | AE45: TRUE
A46: Caffe Duomo | E46: Pitt Bro's | F46: Main Arena | G46: 7490 | H46: 10775 | I46: 10145 | J46: =SUM(G46:I46) -> 28410 | K46: 40000 | U46: =U45+1 -> 26 | V46: TRUE | W46: Catriona | X46: Moore | Y46: 857191732 | Z46: samanthaobrien12345@yahoo.com | AA46: Food | AB46: FALSE | AC46: TRUE | AD46: TRUE | AE46: TRUE
A47: Camile Thai | B47: Man Van | C47: Kian | E47: Caffe Duomo | F47: Main Arena | G47: 4229 | H47: 7393 | I47: 7820.5 | J47: =SUM(G47:I47) -> 19442.5 | K47: 25000 | U47: =U46+1 -> 27 | V47: TRUE | W47: Ann Marie | X47: Price | Y47: 861992532 | Z47: annmariemccar@yahoo.co.uk | AA47: Food | AB47: FALSE | AC47: TRUE | AD47: TRUE | AE47: TRUE
A48: Zambrero | E48: Camile Thai | F48: Main Arena | G48: 21087 | H48: 34732 | I48: 31400 | J48: =SUM(G48:I48) -> 87219 | K48: 80000 | U48: =U47+1 -> 28 | V48: TRUE | W48: Sean | X48: Rausch | Y48: 899785268 | Z48: seanrausch99@gmail.com | AA48: Food | AB48: TRUE | AC48: TRUE | AD48: TRUE | AE48: TRUE
A49: Smash Burger 1 | B49: 07 truck | C49: Tom | E49: Zambrero | F49: Main Arena | G49: 12211 | H49: 17604 | I49: 16130 | J49: =SUM(G49:I49) -> 45945 | K49: 50000 | U49: =U48+1 -> 29 | V49: TRUE | W49: Nicole | X49: Phillips | Y49: 894487843 | Z49: nicolephillips1612@gmail.com | AA49: Ice Cream / Cofee | AB49: FALSE | AC49: FALSE | AD49: TRUE | AE49: TRUE
A50: Loaded Burger | B50: Grenadier | C50: Simon | E50: Smash Burger 1 | F50: Late Night | G50: 10511 | H50: 11600 | I50: 12816.5 | J50: =SUM(G50:I50) -> 34927.5 | K50: 60000 | U50: =U49+1 -> 30 | V50: TRUE | W50: Emma | X50: Phillips | Y50: 862327466 | Z50: emmaphillips0024@hotmail.com | AA50: Ice Cream / Coffee | AB50: FALSE | AC50: FALSE | AD50: TRUE | AE50: TRUE
A51: Pizza/Pasta | B51: Toms Van | C51: Tom Snr | E51: Loaded Burger | F51: Late Night | G51: 10997 | H51: 12500 | I51: 11023 | J51: =SUM(G51:I51) -> 34520 | K51: 50000 | U51: =U50+1 -> 31 | V51: TRUE | W51: Tammy | X51: Quinn | Y51: 851801005 | Z51: tammyquinnx@gmail.com | AA51: Ice Cream / Coffee | AB51: FALSE | AC51: TRUE | AD51: TRUE | AE51: TRUE
A52: Thindi | B52: Tow truck | E52: Thindi | F52: Main Arena | G52: 8495 | H52: 9332 | I52: 7569 | J52: =SUM(G52:I52) -> 25396 | K52: 30000 | U52: =U51+1 -> 32 | V52: TRUE | W52: Islam | X52: Boulbassir | Y52: 851053891 | Z52: islamboulbassir1@gmail.com | AA52: Food | AB52: FALSE | AC52: FALSE | AD52: FALSE | AE52: FALSE
A53: Ice Cream Unit 1 | C53: Chris Halligan | E53: Pizza/Pasta | F53: Main Arena | G53: 10910 | H53: 14546 | I53: 13214 | J53: =SUM(G53:I53) -> 38670 | K53: 50000 | U53: =U52+1 -> 33 | V53: TRUE | W53: Abdelrahman | X53: Belakhdar | Y53: 894919005 | Z53: abdelsig7@gmail.com | AA53: Food | AB53: FALSE | AC53: FALSE | AD53: FALSE | AE53: FALSE
A54: Ice Cream Unit 2 | C54: Serg | E54: Ice Cream Vans | J54: =SUM(G54:I54) -> 0 | U54: =U53+1 -> 34 | V54: FALSE | AA54: Food | AB54: FALSE | AC54: FALSE | AD54: FALSE | AE54: FALSE
A55: Ice Cream Unit 3 | C55: Maisy | E55: Ice Cream Unit 1 | F55: Late Night | G55: 3828 | H55: 4204 | I55: 4310 | J55: =SUM(G55:I55) -> 12342 | U55: =U54+1 -> 35 | V55: TRUE | W55: Moad | X55: Raguragui | Y55: 873354999 | Z55: moadrgrg1618@gmail.com | AA55: Food | AB55: FALSE | AC55: FALSE | AD55: FALSE | AE55: FALSE
A56: Dads Camper | C56: Patrick | E56: Ice Cream Unit 2 | F56: Late Night | G56: 2385 | H56: 3116 | I56: 2985 | J56: =SUM(G56:I56) -> 8486 | U56: =U55+1 -> 36 | V56: FALSE | AA56: Food | AB56: FALSE | AC56: FALSE | AD56: FALSE | AE56: FALSE
A57: Fiat Camper | E57: Vintage Ice Cream | F57: Main Arena | G57: 4166 | H57: 6494 | I57: 6332.5 | J57: =SUM(G57:I57) -> 16992.5 | U57: =U56+1 -> 37 | V57: TRUE | W57: Omar | X57: Teyehi | Y57: 894904731 | Z57: otayahi@gmail.com | AA57: Food | AB57: FALSE | AC57: FALSE | AD57: FALSE | AE57: FALSE
A58: Transit Camper | C58: Triona | J58: =SUM(G58:I58) -> 0 | U58: =U57+1 -> 38 | V58: TRUE | W58: Karla | X58: Brady | AA58: Food | AB58: FALSE | AC58: FALSE | AD58: FALSE | AE58: FALSE
A59: VW Camper | C59: Janet | F59: Total | G59: =SUM(G46:G57) -> 96309 | H59: =SUM(H46:H57) -> 132296 | I59: =SUM(I46:I57) -> 123745.5 | J59: =SUM(J46:J58) -> 352350.5 | K59: =SUM(K46:K58) -> 385000 | U59: =U58+1 -> 39 | V59: TRUE | W59: Karl | X59: Haide | Y59: 834257193 | Z59: karlhaide@gmail.com | AA59: Food | AB59: FALSE | AC59: FALSE | AD59: FALSE | AE59: FALSE
A60: Showers | F60: Commission | G60: =G59*0.2 -> 19261.8 | H60: =H59*0.2 -> 26459.2 | I60: =I59*0.2 -> 24749.1 | J60: =J59*0.2 -> 70470.1 | U60: =U59+1 -> 40 | V60: TRUE | W60: Marcella | X60: McGrane | Y60: 858203259 | Z60: marcella.mcgrane@gmail.com | AA60: Food | AB60: FALSE | AC60: FALSE | AD60: FALSE | AE60: FALSE
A61: Man Van | C61: Kian | F61: Expected Payout | J61: =J59-J60 -> 281880.4 | U61: =U60+1 -> 41 | V61: TRUE | W61: Patryk | X61: Daszkiewicz | Y61: 851619098 | Z61: paddydaz@icloud.com | AA61: Ice cream | AB61: FALSE | AC61: FALSE | AD61: FALSE | AE61: FALSE
A62: Deli Truck 07 | C62: Tom | F62: Actual Payout | U62: =U61+1 -> 42 | V62: TRUE | W62: Carolanne | X62: OSullivan | Y62: 862733958 | Z62: carolannesc@gmail.com | AA62: Coffee | AB62: FALSE | AC62: TRUE | AD62: TRUE | AE62: TRUE
A63: Deli Truck 06 | C63: Colly?? | F63: WIFI/Power/Card | U63: =U62+1 -> 43 | V63: TRUE | W63: Saoirse | X63: Maher | Y63: 871237228 | Z63: katiephelan07@icloud.com | AA63: Coffee | AB63: FALSE | AC63: TRUE | AD63: TRUE | AE63: TRUE
A64: Grenadier | C64: Simench | U64: =U63+1 -> 44 | V64: TRUE | W64: Barry | X64: Orr | Y64: 851203406 | Z64: aimeemcglashan11@gmail.com | AA64: Ice cream | AB64: TRUE | AC64: TRUE | AD64: TRUE | AE64: TRUE
A65: Toms Van | U65: =U64+1 -> 45 | V65: TRUE | W65: Aimee | X65: McGlashan | Y65: 831988755 | Z65: aine.kavanagh2005@gmail.com | AA65: Ice cream | AB65: FALSE | AC65: TRUE | AD65: TRUE | AE65: TRUE
A66: 10WW | U66: =U65+1 -> 46 | V66: TRUE | W66: Aine | X66: Kavanagh | Y66: 831988755 | Z66: katiedunne2022@gmail.com | AA66: Ice cream | AB66: FALSE | AC66: TRUE | AD66: TRUE | AE66: TRUE
A67: Flat bed | U67: =U66+1 -> 47 | V67: TRUE | W67: Katie | X67: Dunne | Y67: 858614894 | Z67: evan_wallace09@icloud.com | AA67: New | AB67: FALSE | AC67: TRUE | AD67: TRUE | AE67: TRUE
A68: 142 Small Van | C68: Oisin | U68: =U67+1 -> 48 | V68: TRUE | W68: Evan | X68: Wallace | Y68: 858416456 | AA68: New | AB68: FALSE | AC68: FALSE | AD68: FALSE | AE68: FALSE
A69: Tow truck | U69: =U68+1 -> 49 | V69: TRUE | Z69: lorrrussell@gmail.com | AB69: FALSE | AC69: FALSE | AD69: TRUE | AE69: TRUE
A70: Friday | U70: =U69+1 -> 50 | V70: TRUE | W70: Lorraine | X70: Russell | Y70: 851353337 | AA70: Coffee | AB70: FALSE | AC70: FALSE | AD70: TRUE | AE70: TRUE
U71: =U70+1 -> 51 | V71: TRUE | Z71: medikateunow@gmail.com | AB71: TRUE | AC71: TRUE | AD71: TRUE | AE71: TRUE
B72: 12:00pm-8:00pm | F72: 2:00pm-10:00pm | I72: 3:00pm-12:00am | U72: =U71+1 -> 52 | V72: TRUE | W72: Katarzyna | X72: Kawecka | Y72: 864551310 | Z72: vmcmirian_23@hotmail.com | AA72: Food | AB72: FALSE | AC72: TRUE | AD72: TRUE | AE72: TRUE
A73: Stall/Unit Name | B73: 1 | C73: 2 | D73: 3 | E73: 4 | F73: 5 | G73: 6 | H73: 7 | I73: 8 | J73: 9 | U73: =U72+1 -> 53 | V73: TRUE | W73: Valquiria | X73: Coutinho | Y73: 833407875 | Z73: eoinernesthughes@gmail.com | AA73: Food | AB73: FALSE | AC73: TRUE | AD73: TRUE | AE73: TRUE
A74: Thindi | U74: =U73+1 -> 54 | V74: TRUE | W74: Eoin | X74: Hughes | Y74: 894684748 | Z74: robert157mahon@gmail.com | AA74: Food | AB74: FALSE | AC74: TRUE | AD74: TRUE | AE74: TRUE
A75: Smash | U75: =U74+1 -> 55 | V75: TRUE | W75: Robert | X75: Mahon | Y75: 852788111 | Z75: simonoconnor964@gmail.com | AA75: Stock | AB75: TRUE | AC75: TRUE | AD75: TRUE | AE75: TRUE
A76: Loaded Burger | U76: =U75+1 -> 56 | V76: TRUE | W76: Simon | X76: OConnor | Y76: 851948435 | AA76: Stock | AB76: TRUE | AC76: TRUE | AD76: TRUE | AE76: TRUE
A77: Pizza Pasta | U77: =U76+1 -> 57 | V77: TRUE | W77: Kian | X77: McCarton | Y77: 873500234 | Z77: kian.macker@gmail.com | AA77: Stock | AB77: TRUE | AC77: TRUE | AD77: TRUE | AE77: TRUE
A78: Zambrero | U78: =U77+1 -> 58 | V78: TRUE | W78: Oisin | X78: ONeill | Y78: 857825980 | Z78: oisinon24@gmail.com | AA78: Stock | AB78: TRUE | AC78: TRUE | AD78: TRUE | AE78: TRUE
A79: Pitt Bros | U79: =U78+1 -> 59 | V79: FALSE | AB79: FALSE | AC79: FALSE | AD79: FALSE | AE79: FALSE
A80: Coffee | U80: =U79+1 -> 60 | V80: FALSE | AB80: FALSE | AC80: FALSE | AD80: FALSE | AE80: FALSE
A81: Camile | U81: =U80+1 -> 61 | V81: TRUE | AB81: FALSE | AC81: FALSE | AD81: TRUE | AE81: TRUE
A82: Ice Cream Vans | U82: =U81+1 -> 62 | V82: FALSE | AB82: FALSE | AC82: FALSE | AD82: FALSE | AE82: FALSE
A83: Ice Cream Unit 1 | U83: =U82+1 -> 63 | V83: TRUE | W83: Sergejs | X83: Troscenko | Y83: 871930629 | Z83: sergejstroscenko@gmail.com | AA83: N/a | AB83: TRUE | AC83: TRUE | AD83: TRUE | AE83: TRUE
A84: Ice Cream Unit 2 | U84: =U83+1 -> 64 | V84: TRUE | W84: Stacey | X84: Smyth | Y84: 852448103 | Z84: smyth.stacey7@gmail.com | AA84: Food | AB84: FALSE | AC84: FALSE | AD84: TRUE | AE84: TRUE
A85: Vintage Van | U85: =U84+1 -> 65 | V85: TRUE | AB85: TRUE | AC85: TRUE | AD85: TRUE | AE85: TRUE
U86: =U85+1 -> 66 | V86: FALSE | AB86: FALSE | AC86: FALSE | AD86: FALSE | AE86: FALSE
U87: =U86+1 -> 67 | V87: FALSE | AB87: FALSE | AC87: FALSE | AD87: FALSE | AE87: FALSE
A88: Saturday | U88: =U87+1 -> 68 | V88: FALSE | AB88: FALSE | AC88: FALSE | AD88: FALSE | AE88: FALSE
U89: =U88+1 -> 69 | V89: FALSE | AB89: FALSE | AC89: FALSE | AD89: FALSE | AE89: FALSE
D90: 11:00am-8:00pm | F90: 1:00pm-10:00pm | H90: 3:00pm-1:00am | U90: =U89+1 -> 70 | V90: TRUE | W90: Janet | X90: Orr | Y90: 877675495 | Z90: orr.janet@yahoo.ie | AA90: Coffee | AB90: FALSE | AC90: TRUE | AD90: TRUE | AE90: TRUE
A91: Stall/Unit Name | B91: 1 | C91: 2 | D91: 3 | E91: 4 | F91: 5 | G91: 6 | H91: 7 | I91: 8 | J91: 9 | K91: 10 | U91: =U90+1 -> 71 | V91: TRUE | W91: Alessandra | X91: Maurizi | Y91: 899888102 | Z91: murizialessandra@gmail.com | AA91: Food | AB91: FALSE | AC91: TRUE | AD91: TRUE | AE91: TRUE
A92: Thindi | U92: =U91+1 -> 72 | V92: TRUE | W92: Celine | X92: Cryan | Y92: 892562230 | Z92: celinecryan@gmail.com | AA92: New | AB92: FALSE | AC92: TRUE | AD92: TRUE | AE92: TRUE
A93: Smash | U93: =U92+1 -> 73 | V93: TRUE | W93: Ethan | X93: OHalloran | Y93: 857563725 | Z93: ethanohalloran8@gmail.com | AA93: New | AB93: FALSE | AC93: TRUE | AD93: TRUE | AE93: TRUE
A94: Pizza Pasta | U94: =U93+1 -> 74 | V94: FALSE | AB94: FALSE | AC94: FALSE | AD94: FALSE | AE94: FALSE
A95: Loaded Burger | U95: =U94+1 -> 75 | V95: FALSE | AB95: FALSE | AC95: FALSE | AD95: FALSE | AE95: FALSE
A96: Zambrero | U96: =U95+1 -> 76 | V96: FALSE | AB96: FALSE | AC96: FALSE | AD96: FALSE | AE96: FALSE
A97: Pitt Bros | U97: =U96+1 -> 77 | V97: FALSE | AB97: FALSE | AC97: FALSE | AD97: FALSE | AE97: FALSE
A98: Coffee | U98: =U97+1 -> 78 | V98: FALSE | AB98: FALSE | AC98: FALSE | AD98: FALSE | AE98: FALSE
A99: Camile | U99: =U98+1 -> 79 | V99: FALSE | AB99: FALSE | AC99: FALSE | AD99: FALSE | AE99: FALSE
A100: Ice Cream Vans | U100: =U99+1 -> 80 | V100: TRUE | W100: Niall | X100: OConnor | Z100: n.oconnor@zambrero.com | AB100: FALSE | AC100: TRUE | AD100: TRUE | AE100: TRUE
A101: Ice Cream Unit 1 | U101: =U100+1 -> 81 | V101: TRUE | W101: Newton | X101: Galhardo | Z101: newtonfgalhardo@gmail.com | AB101: FALSE | AC101: TRUE | AD101: TRUE | AE101: TRUE
...

Sheet Iveagh Gardens Takings 
A1: Date | B1: Cash | C1: Card
A2: 45841 | B2: 150 | C2: 1601
A3: 45842 | B3: 114 | C3: 896
A4: 45844 | B4: 218 | C4: 1104
A5: 45849 | B5: 210 | C5: 1738
A6: 45850 | B6: 300 | C6: 1951
A7: 45851 | B7: 435 | C7: 1951
A8: 45855 | B8: 395 | C8: 2547
A9: 45856 | B9: 222 | C9: 1596
A10: 45857 | B10: 250 | C10: 1078
A11: 45858 | B11: 465 | C11: 2130
A12: Total | B12: =SUM(B2:B11) -> 2759 | C12: =SUM(C2:C11) -> 16592
A13: 45862 | B13: 60 | C13: 1478.5
A14: 45863 | B14: 60.5 | C14: 2037
A15: 45864 | B15: 330 | C15: 2393
A16: 45865 | B16: 621 | C16: 1200.5

Sheet Staff & Trailers
A1: Name | B1: Trailers | C1: Trailers
A2: Samantha
A3: Lauren
A4: Stacey | B4: Camile pitt bros Zamb Thindi chip | C4: Pizza
A5: Ava | B5: "
A6: Dylan | B6: Ice cream pizza Camile chip coffee
A7: Dani | B7: Pizza camile Thindi chip ice cream
A8: Ann Marie | B8: Chip Pitt bros Zamb pizza
A9: Amanda | B9: " & camile
A10: Megan | B10: Camile Thindi pizza Pitt bros chip
A11: Shannon | B11: Toasty coffee ice cream pizza Camile chip
A12: Katelyn | B12: Chip ice cream Pitt bros pizza
A13: Nicola | B13: Coffee chip
A14: Lisa | B14: Toasty coffee chip
A15: Laura | B15: Toasty ice cream coffee chip
A16: Janet | B16: Toasty coffee
... A53: Taylor | B53: Cook
A54: Brophy
A55: Sean (Taylor) | B55: Chip
A56: Charlie Nolan | B56: Ice cream
A57: Caitlin Nolan | B57: Ice cream coffee
A58: Hilary | B58: Coffee
A59: Kyle | B59: Chip
A60: Lisa (viv) | B60: Coffee
A61: Sean (Nicola) | B61: Chip
A62: Aidan (Nicola) | B62: Chip
A63: Katie (triona) | B63: Chip pit bros
A64: Casandra (triona) | B64: Chip
A65: Becky (triona) | B65: Coffee
A66: Jess (Lorraine) | B66: Chip Zamb
... A71: Michelle | B71: Chip coffee ice cream

Sheet Zach Bryan
A1: Zach Bryan | I1: Stock & Orders
A2: Stall/Unit Name | B2: Location | C2: 🅿️ | D2: 🧽 | E2: ⚡️ | F2: 💻 | G2: 🧯 | H2: 👥 | I2: Sysco | J2: Camile | L2: ReadyChef | M2: BWG | N2: Pitt Bros | O2: Delimeats | P2: Bretzel
A3: Pizza Pasta | B3: Exit E | C3: FALSE | D3: FALSE | E3: FALSE | F3: FALSE | G3: FALSE | H3: FALSE | I3: FALSE | J3: FALSE | K3: FALSE | L3: FALSE | M3: FALSE | N3: FALSE | O3: FALSE | P3: FALSE
A4: Loaded | B4: Toilets | C4: TRUE | D4: TRUE | E4: TRUE | F4: FALSE | G4: FALSE | H4: FALSE | I4: FALSE | J4: TRUE | K4: FALSE | L4: FALSE | M4: TRUE | N4: TRUE | O4: TRUE | P4: FALSE
A5: Smash | B5: Toilets | C5: TRUE | D5: TRUE | E5: TRUE | F5: FALSE | G5: FALSE | H5: FALSE | I5: FALSE | J5: TRUE | K5: FALSE | L5: FALSE | M5: TRUE | N5: TRUE | O5: TRUE | P5: FALSE
A6: Camile | B6: Side Stage | C6: TRUE | D6: TRUE | E6: TRUE | F6: FALSE | G6: FALSE | H6: FALSE | I6: FALSE | J6: TRUE | K6: FALSE | L6: FALSE | M6: TRUE | N6: TRUE | O6: TRUE | P6: FALSE
A7: Pitt Bros | B7: Toilets (Back Line) | C7: TRUE | D7: TRUE | E7: TRUE | F7: FALSE | G7: FALSE | H7: FALSE | I7: FALSE | J7: TRUE | K7: FALSE | L7: FALSE | M7: TRUE | N7: TRUE | O7: TRUE | P7: FALSE
A8: Thindi | B8: Toilets (Back Line) | C8: TRUE | D8: TRUE | E8: TRUE | F8: FALSE | G8: FALSE | H8: FALSE | I8: FALSE | J8: TRUE | K8: FALSE | L8: FALSE | M8: TRUE | N8: TRUE | O8: TRUE | P8: FALSE
A9: Zambrero | B9: Back Of Main Arena (Spine) | C9: TRUE | D9: TRUE | E9: TRUE | F9: FALSE | G9: FALSE | H9: FALSE | I9: FALSE | J9: TRUE | K9: FALSE | L9: FALSE | M9: TRUE | N9: TRUE | O9: TRUE | P9: FALSE
A10: Off Beat | B10: Back Of Main Arena (Spine) | C10: TRUE | D10: TRUE | E10: TRUE | F10: FALSE | G10: FALSE | H10: FALSE | I10: FALSE | J10: TRUE | K10: FALSE | L10: FALSE | M10: TRUE | N10: TRUE | O10: TRUE | P10: FALSE
A11: Smash | B11: Toilets (Back Line) | C11: TRUE | D11: TRUE | E11: TRUE | F11: FALSE | G11: FALSE | H11: FALSE | I11: FALSE | J11: TRUE | K11: FALSE | L11: FALSE | M11: TRUE | N11: TRUE | O11: TRUE | P11: FALSE
A12: Pizza/Pasta | B12: Toilets (Back Line) | C12: TRUE | D12: TRUE | E12: TRUE | F12: FALSE | G12: FALSE | H12: FALSE | I12: FALSE | J12: TRUE | K12: FALSE | L12: FALSE | M12: TRUE | N12: TRUE | O12: TRUE | P12: FALSE
A13: Kiosk | B13: Back Of Main Arena (Spine) | C13: TRUE | D13: TRUE | E13: TRUE | F13: FALSE | G13: FALSE | H13: FALSE | I13: FALSE | J13: TRUE | K13: FALSE | L13: FALSE | M13: TRUE | N13: TRUE | O13: TRUE | P13: FALSE
A14: Coffee | B14: Family Area | C14: FALSE | D14: FALSE | E14: TRUE | F14: FALSE | G14: FALSE | H14: FALSE | I14: FALSE | J14: TRUE | K14: FALSE | L14: FALSE | M14: TRUE | N14: TRUE | O14: TRUE | P14: FALSE
... A16: Ice Cream | B16: N/A | C16: FALSE | D16: FALSE | E16: FALSE | F16: FALSE | G16: FALSE | H16: FALSE | I16: FALSE | J16: TRUE | K16: FALSE | L16: FALSE | M16: TRUE | N16: TRUE | O16: TRUE | P16: FALSE
A20: Unit ID | B20: Opening Hours | I20: Location | L20: Takings
B21: # Staff | C21: Hrs | D21: # Staff | E21: Hrs | F21: # Staff | G21: Hrs | H21: # Staff | L21: Stall/Unit Name | M21: Location | P21: Day | S21: Total
B22: Friday | D22: Saturday | F22: Sunday | H22: Monday | L22: Pizza Pasta | M22: Exit E | P22: Friday | Q22: Saturday | R22: Sunday
A23: Loaded | B23: 8 | C23: 9 | D23: 8 | E23: 9 | F23: 8 | G23: 9 | I23: Toilets | L23: Loaded | M23: Toilets | P23: 6438 | Q23: 7258.5 | R23: 6871.05 | S23: =SUM(P23:R23) -> 20567.55
A24: Smash | B24: 8 | C24: 9 | D24: 8 | E24: 9 | F24: 8 | G24: 9 | I24: Toilets | L24: Smash | M24: Toilets | P24: 4497 | Q24: 4895.3 | R24: 5993.65 | S24: =SUM(P24:R24) -> 15385.95
A25: Camile | B25: 8 | C25: 9 | D25: 8 | E25: 9 | F25: 8 | G25: 9 | I25: Side Stage | L25: Camile | M25: Side Stage | P25: 11955 | Q25: 15466.25 | R25: 13656.25 | S25: =SUM(P25:R25) -> 41077.5
A26: Pitt Bros | B26: 5 | C26: 9 | D26: 5 | E26: 9 | F26: 5 | G26: 9 | I26: Toilets (Back Line) | L26: Pitt Bros | M26: Toilets (Back Line) | P26: 5373.5 | Q26: 5612.45 | R26: 6929.3 | S26: =SUM(P26:R26) -> 17915.25
A27: Thindi | B27: 4 | C27: 9 | D27: 4 | E27: 9 | F27: 4 | G27: 9 | I27: Toilets (Back Line) | L27: Thindi | M27: Toilets (Back Line) | P27: 1644.31 | Q27: 2033.23 | R27: 1256.93 | S27: =SUM(P27:R27) -> 4934.47
A28: Zambrero | B28: 8 | C28: 9 | D28: 8 | E28: 9 | F28: 8 | G28: 9 | I28: Back Of Main Arena (Spine) | L28: Zambrero | M28: Back Of Main Arena (Spine) | P28: 8938 | Q28: 11569.3 | R28: 11057.65 | S28: =SUM(P28:R28) -> 31564.95
A29: Off Beat | B29: 3 | C29: 9 | D29: 3 | E29: 9 | F29: 3 | G29: 9 | I29: Back Of Main Arena (Spine) | L29: Off Beat | M29: Back Of Main Arena (Spine) | P29: 4448.75 | Q29: 5884.61 | R29: 4940.3 | S29: =SUM(P29:R29) -> 15273.66
A30: Smash | B30: 8 | C30: 9 | D30: 8 | E30: 9 | F30: 8 | G30: 9 | I30: Toilets (Back Line) | L30: Smash | M30: Toilets (Back Line) | P30: 7930 | Q30: 10858.3 | R30: 11961.6 | S30: =SUM(P30:R30) -> 30749.9
A31: Pizza/Pasta | B31: 5 | C31: 9 | D31: 5 | E31: 9 | F31: 5 | G31: 9 | I31: Toilets (Back Line) | L31: Pizza/Pasta | M31: Toilets (Back Line) | P31: 4727 | Q31: 7852.6 | R31: 6081.15 | S31: =SUM(P31:R31) -> 18660.75
A32: Kiosk | B32: 3 | C32: 9 | D32: 3 | E32: 9 | F32: 3 | G32: 9 | I32: Back Of Main Arena (Spine) | L32: Kiosk | M32: Back Of Main Arena (Spine) | P32: 9258.25 | Q32: 10832.5 | R32: 8694.5 | S32: =SUM(P32:R32) -> 28785.25
A33: Coffee | B33: 3 | C33: 9 | D33: 3 | E33: 9 | F33: 3 | G33: 9 | I33: Family Area | L33: Coffee | M33: Family Area | P33: 2022.8 | Q33: 3619.3 | R33: 2871.45 | S33: =SUM(P33:R33) -> 8513.55
A34: Coffee | B34: 2 | C34: 9 | D34: 2 | E34: 9 | F34: 2 | G34: 9 | I34: Toilets (Back Line) | L34: Coffee | M34: Toilets (Back Line) | P34: 3026.9 | Q34: 3843.55 | R34: 4243.15 | S34: =SUM(P34:R34) -> 11113.6
A35: Ice Cream | B35: 2 | C35: 9 | D35: 2 | E35: 9 | F35: 2 | G35: 9 | I35: N/A | L35: Ice Cream | M35: Middle Arena Bar | P35: 5385 | Q35: 4060.6 | R35: 2374.1 | S35: =SUM(P35:R35) -> 11819.7
A36: Ice Cream | B36: 2 | C36: 9 | D36: 2 | E36: 9 | F36: 2 | G36: 9 | I36: N/A | L36: Ice Cream | M36: Early Entry/Gate 4 | P36: 4000 | Q36: 3289 | R36: 1710 | S36: =SUM(P36, Q36, R36) -> 8999
L37: Ice Cream | M37: Chesterfield Av @ Aras Gates | P37: (Sat/Sun Only) | Q37: 3755 | R37: 2690
O38: Total | P38: =SUM(P23:P37) -> 79644.51 | Q38: =SUM(Q23:Q37) -> 100830.49 | R38: =SUM(R23:R35) -> 86931.08 | S38: =SUM(P38, Q38, R38) -> 267406.08
A39: Stock Boys | B39: 4 | C39: 9 | D39: 4 | E39: 9 | F39: 4 | G39: 9 | I39: Main Arena | O39: Commission | P39: =P38*20% -> 15928.902 | Q39: =Q38*20% -> 20166.098 | R39: =R38*20% -> 17386.216 | S39: =SUM(P39, Q39, R39) -> 53481.216
A40: Total | B40: =SUM(B23:B39) -> 73 | O40: Expected Payout | P40: =P38-P39 -> 63715.608 | Q40: =Q38-Q39 -> 80664.392 | R40: =R38-R39 -> 69544.864 | S40: =SUM(P40, Q40, R40) -> 213924.86
O41: Actual Payout
O42: WIFI/Power/Card
A44: Staff Names
A46: Staff Id | B46: Group Chat | C46: First Name | D46: Last Name | E46: Phone Number | F46: Email | G46: Source | H46: Days Available | K46: Wages
H47: Friday | I47: Saturday | J47: Sunday | K47: Paid | L47: Total Days | M47: Total Owed
B48: FALSE | C48: Lauren | D48: Obrien | E48: 857140539 | H48: FALSE | I48: FALSE | J48: FALSE | K48: FALSE | L48: =COUNTIF(H48:J48,TRUE) -> 0 | M48: =L48*120 -> 0
B49: FALSE | C49: Thomas | D49: Obrien | E49: 852402555 | H49: FALSE | I49: FALSE | J49: FALSE | K49: FALSE | L49: =COUNTIF(H49:J49,TRUE) -> 0 | M49: =L49*120 -> 0
B50: FALSE | C50: Thomas | D50: Obrien | E50: 862539642 | H50: FALSE | I50: FALSE | J50: FALSE | K50: FALSE | L50: =COUNTIF(H50:J50,TRUE) -> 0 | M50: =L50*120 -> 0
B51: FALSE | C51: Patrick | D51: Obrien | E51: 876192047 | H51: FALSE | I51: FALSE | J51: FALSE | K51: FALSE | L51: =COUNTIF(H51:J51,TRUE) -> 0 | M51: =L51*120 -> 0
B52: FALSE | C52: Sophie | D52: Obrien | E52: 852194071 | H52: FALSE | I52: FALSE | J52: FALSE | K52: FALSE | L52: =COUNTIF(H52:J52,TRUE) -> 0 | M52: =L52*120 -> 0
B53: FALSE | C53: Jack | D53: Savage | E53: 858321069 | H53: FALSE | I53: FALSE | J53: FALSE | K53: FALSE | L53: =COUNTIF(H53:J53,TRUE) -> 0 | M53: =L53*120 -> 0
B54: FALSE | C54: Robert | D54: Mahon | E54: 852788111 | H54: TRUE | I54: TRUE | J54: TRUE | K54: FALSE | L54: =COUNTIF(H54:J54,TRUE) -> 3 | M54: =L54*120 -> 360
B55: FALSE | C55: Barry | D55: Or | E55: 851203406 | H55: TRUE | I55: TRUE | J55: TRUE | K55: FALSE | L55: =COUNTIF(H55:J55,TRUE) -> 3 | M55: =L55*120 -> 360
B56: FALSE | C56: Simon | D56: Oconnor | E56: 851948435 | H56: TRUE | I56: TRUE | J56: TRUE | K56: FALSE | L56: =COUNTIF(H56:J56,TRUE) -> 3 | M56: =L56*120 -> 360
B57: FALSE | C57: Karl | D57: Brennan | E57: 852184259 | H57: TRUE | I57: TRUE | J57: TRUE | K57: FALSE | L57: =COUNTIF(H57:J57,TRUE) -> 3 | M57: =L57*120 -> 360
B58: FALSE | C58: Kerri | D58: Lynch | E58: 857553712 | H58: TRUE | I58: TRUE | J58: TRUE | K58: FALSE | L58: =COUNTIF(H58:J58,TRUE) -> 3 | M58: =L58*120 -> 360
B59: FALSE | C59: Lauren | D59: Jordan | E59: 876971204 | H59: TRUE | I59: TRUE | J59: TRUE | K59: FALSE | L59: =COUNTIF(H59:J59,TRUE) -> 3 | M59: =L59*120 -> 360
... B99: FALSE | C99: Vivekanda | D99: suttul | E99: 862738909 | H99: FALSE | I99: FALSE | J99: FALSE | K99: FALSE | L99: =COUNTIF(H99:J99,TRUE) -> 0 | M99: =L99*120 -> 0
B100: FALSE | C100: Diyar | D100: ohagibad | E100: ]0863672890 | H100: TRUE | I100: FALSE | J100: TRUE | K100: FALSE | L100: =COUNTIF(H100:J100,TRUE) -> 2 | M100: =L100*120 -> 240
B101: FALSE | C101: MAriana | D101: rual | E101: 872536478 | H101: TRUE | I101: TRUE | J101: FALSE | K101: FALSE | L101: =COUNTIF(H101:J101,TRUE) -> 2 | M101: =L101*120 -> 240
B102: FALSE | C102: Surya | D102: Santos | E102: 867263548 | H102: TRUE | I102: FALSE | J102: TRUE | K102: FALSE | L102: =COUNTIF(H102:J102,TRUE) -> 2 | M102: =L102*120 -> 240
B103: FALSE | C103: Lorraine | D103: Thompson | E103: 862789067 | H103: TRUE | I103: TRUE | J103: TRUE | K103: FALSE | L103: =COUNTIF(H103:J103,TRUE) -> 3 | M103: =L103*120 -> 360
B104: FALSE | C104: Michelle | D104: Nolan | E104: 862908936 | H104: TRUE | I104: TRUE | J104: TRUE | K104: FALSE | L104: =COUNTIF(H104:J104,TRUE) -> 3 | M104: =L104*120 -> 360
B105: FALSE | C105: Leighanna | D105: Wakefield | E105: 864087290 | H105: TRUE | I105: TRUE | J105: TRUE | K105: FALSE | L105: =COUNTIF(H105:J105,TRUE) -> 3 | M105: =L105*120 -> 360
B106: FALSE | C106: Bridget | D106: Reid | E106: 879273645 | H106: TRUE | I106: TRUE | J106: TRUE | K106: FALSE | L106: =COUNTIF(H106:J106,TRUE) -> 3 | M106: =L106*120 -> 360
B107: FALSE | C107: Nickolla | D107: Brady | E107: 896357289 | H107: TRUE | I107: TRUE | J107: TRUE | K107: FALSE | L107: =COUNTIF(H107:J107,TRUE) -> 3 | M107: =L107*120 -> 360
B108: FALSE | C108: Akhil | D108: madueza | E108: 862789098 | H108: FALSE | I108: FALSE | J108: FALSE | K108: FALSE | L108: =COUNTIF(H108:J108,TRUE) -> 0 | M108: =L108*120 -> 0
B109: FALSE | C109: Beatriz | D109: mariato | E109: 872567890 | H109: FALSE | I109: FALSE | J109: FALSE | K109: FALSE | L109: =COUNTIF(H109:J109,TRUE) -> 0 | M109: =L109*120 -> 0
B110: FALSE | C110: Aoife | D110: Obrien | E110: 867263546 | H110: TRUE | I110: TRUE | J110: TRUE | K110: FALSE | L110: =COUNTIF(H110:J110,TRUE) -> 3 | M110: =L110*120 -> 360
B111: FALSE | C111: Jordan | D111: Keating | E111: 872567890 | H111: TRUE | I111: TRUE | J111: TRUE | K111: FALSE | L111: =COUNTIF(H111:J111,TRUE) -> 3 | M111: =L111*120 -> 360
B112: FALSE | C112: KAtelyn | D112: toalw | E112: 856253645 | H112: TRUE | I112: TRUE | J112: TRUE | K112: FALSE | L112: =COUNTIF(H112:J112,TRUE) -> 3 | M112: =L112*120 -> 360
... B119: FALSE | C119: Lisa | D119: Iveagh | E119: 852364789 | H119: TRUE | I119: FALSE | J119: FALSE | K119: FALSE | L119: =COUNTIF(H119:J119,TRUE) -> 1 | M119: =L119*120 -> 120
C120: Abbie | D120: Brennan | E120: 872563789 | H120: TRUE | I120: TRUE | J120: TRUE | L120: =COUNTIF(H120:J120,TRUE) -> 3 | M120: =L120*120 -> 360
C121: Cian | D121: Richie | E121: 862746890 | H121: TRUE | I121: FALSE | J121: TRUE | L121: =COUNTIF(H121:J121,TRUE) -> 2 | M121: =L121*120 -> 240
C122: Kayla | D122: Mahon | E122: 867878535 | H122: TRUE | I122: TRUE | J122: TRUE | L122: =COUNTIF(H122:J122,TRUE) -> 3 | M122: =L122*120 -> 360
C123: Ava | D123: Brown | E123: 876566789 | H123: TRUE | I123: TRUE | J123: TRUE | L123: =COUNTIF(H123:J123,TRUE) -> 3 | M123: =L123*120 -> 360
C124: Megan | D124: Creighton | E124: 856176533 | H124: TRUE | I124: TRUE | J124: TRUE | L124: =COUNTIF(H124:J124,TRUE) -> 3 | M124: =L124*120 -> 360
C125: Ashleigh | D125: Brannigan | E125: 857060891 | H125: FALSE | I125: FALSE | J125: FALSE | L125: =COUNTIF(H125:J125,TRUE) -> 0 | M125: =L125*120 -> 0
C126: Troy | D126: Obrien | E126: 852676553 | H126: FALSE | I126: TRUE | J126: TRUE | L126: =COUNTIF(H126:J126,TRUE) -> 2 | M126: =L126*120 -> 240
C127: Melissa | D127: Or | E127: 862765633 | H127: FALSE | I127: TRUE | J127: FALSE | L127: =COUNTIF(H127:J127,TRUE) -> 1 | M127: =L127*120 -> 120
C128: Craig | D128: Fenlon | E128: 853678998 | H128: TRUE | I128: FALSE | J128: FALSE | L128: =COUNTIF(H128:J128,TRUE) -> 1 | M128: =L128*120 -> 120
C129: Kelly | D129: Price | E129: 830618223 | H129: FALSE | I129: FALSE | J129: FALSE | L129: =COUNTIF(H129:J129,TRUE) -> 0 | M129: =L129*120 -> 0
C130: Sean | D130: Tracey | E130: 852340300 | H130: TRUE | I130: TRUE | J130: TRUE | L130: =COUNTIF(H130:J130,TRUE) -> 3 | M130: =L130*120 -> 360
C131: Taylor | D131: Gillespie | E131: 874534223 | H131: TRUE | I131: TRUE | J131: TRUE | L131: =COUNTIF(H131:J131,TRUE) -> 3 | M131: =L131*120 -> 360
... C146: Dylan | D146: Harvey | E146: 862789667 | H146: FALSE | I146: FALSE | J146: FALSE | L146: =COUNTIF(H146:J146,TRUE) -> 0 | M146: =L146*120 -> 0
L147: =COUNTIF(H147:J147,TRUE) -> 0 | M147: =L147*120 -> 0
L149: =SUM(L48:L148) -> 204 | M149: =SUM(M48:M147) -> 24480

Sheet Kaleidoscope 25
B3: Kaleidoscope | J3: Stock & Orders
B4: Stall/Unit Name | C4: Location | D4: 🅿️ | E4: 🧽 | F4: ⚡️ | G4: 💻 | H4: 🧯 | I4: 👥 | J4: Sysco | K4: Camile | M4: ReadyChef | N4: BWG | O4: Pitt Bros | P4: Delimeats | Q4: Off Beat
B5: Pizza Pasta | C5: Exit E | D5: FALSE | E5: FALSE | F5: FALSE | G5: FALSE | H5: FALSE | I5: FALSE | J5: FALSE | K5: FALSE | L5: FALSE | M5: FALSE | N5: FALSE | O5: FALSE | P5: FALSE | Q5: FALSE
B6: Loaded | D6: TRUE | E6: FALSE | F6: FALSE | G6: FALSE | H6: FALSE | I6: FALSE | J6: FALSE | K6: TRUE | L6: FALSE | M6: FALSE | N6: TRUE | O6: FALSE | P6: TRUE | Q6: TRUE
B7: Camille | D7: TRUE | E7: FALSE | F7: FALSE | G7: FALSE | H7: FALSE | I7: FALSE | J7: FALSE | K7: TRUE | L7: FALSE | M7: FALSE | N7: TRUE | O7: FALSE | P7: TRUE | Q7: TRUE
B8: Pizza Pasta | D8: TRUE | E8: FALSE | F8: FALSE | G8: TRUE | H8: FALSE | I8: FALSE | J8: FALSE | K8: TRUE | L8: FALSE | M8: FALSE | N8: TRUE | O8: FALSE | P8: TRUE | Q8: TRUE
B9: Toasted | D9: TRUE | E9: FALSE | F9: FALSE | G9: FALSE | H9: FALSE | I9: FALSE | J9: FALSE | K9: TRUE | L9: FALSE | M9: FALSE | N9: TRUE | O9: FALSE | P9: TRUE | Q9: TRUE
B10: Off Beat | D10: TRUE | E10: FALSE | F10: FALSE | G10: FALSE | H10: FALSE | I10: FALSE | J10: FALSE | K10: TRUE | L10: FALSE | M10: FALSE | N10: TRUE | O10: FALSE | P10: TRUE | Q10: TRUE
B11: Zambrero | D11: TRUE | E11: FALSE | F11: FALSE | G11: FALSE | H11: FALSE | I11: FALSE | J11: FALSE | K11: TRUE | L11: FALSE | M11: FALSE | N11: TRUE | O11: FALSE | P11: TRUE | Q11: TRUE
B12: Duomo - relocated | D12: TRUE | E12: FALSE | F12: FALSE | G12: FALSE | H12: FALSE | I12: FALSE | J12: FALSE | K12: TRUE | L12: FALSE | M12: FALSE | N12: TRUE | O12: FALSE | P12: TRUE | Q12: TRUE
B13: Ice Cream | D13: TRUE | E13: FALSE | F13: FALSE | G13: FALSE | H13: FALSE | I13: FALSE | J13: FALSE | K13: TRUE | L13: FALSE | M13: FALSE | N13: TRUE | O13: FALSE | P13: TRUE | Q13: TRUE
B14: Ice Cream | D14: TRUE | E14: FALSE | F14: FALSE | G14: FALSE | H14: FALSE | I14: FALSE | J14: FALSE | K14: TRUE | L14: FALSE | M14: FALSE | N14: TRUE | O14: FALSE | P14: TRUE | Q14: TRUE
B15: Ice Cream | D15: TRUE | E15: FALSE | F15: FALSE | G15: FALSE | H15: FALSE | I15: FALSE | J15: FALSE | K15: TRUE | L15: FALSE | M15: FALSE | N15: TRUE | O15: FALSE | P15: TRUE | Q15: TRUE
D16: FALSE | E16: FALSE | F16: FALSE | G16: FALSE | H16: FALSE | I16: FALSE | J16: FALSE | K16: TRUE | L16: FALSE | M16: FALSE | N16: TRUE | O16: FALSE | P16: TRUE | Q16: TRUE
D17: FALSE | E17: FALSE | F17: FALSE | G17: FALSE | H17: FALSE | I17: FALSE | J17: FALSE | K17: TRUE | L17: FALSE | M17: FALSE | N17: TRUE | O17: FALSE | P17: TRUE | Q17: TRUE
D18: FALSE | E18: FALSE | F18: FALSE | G18: FALSE | H18: FALSE | I18: FALSE | J18: FALSE | K18: TRUE | L18: FALSE | M18: FALSE | N18: TRUE | O18: FALSE | P18: TRUE | Q18: TRUE
B22: Unit ID | C22: Opening Hours | J22: Location | M22: Takings
C23: # Staff | D23: Hrs | E23: # Staff | F23: Hrs | G23: # Staff | H23: Hrs | I23: # Staff | M23: Stall/Unit Name | N23: Location | Q23: Day | T23: Total
C24: Friday | E24: Saturday | G24: Sunday | I24: Monday | M24: Pizza Pasta | N24: Exit E | Q24: Friday | R24: Saturday | S24: Sunday
B25: Loaded | C25: 5 | D25: 9 | E25: 8 | F25: 9 | G25: 8 | H25: 9 | M25: Loaded | T25: =SUM(Q25:S25) -> 0
B26: Camille | C26: 5 | D26: 9 | E26: 8 | F26: 9 | G26: 8 | H26: 9 | M26: Camille | T26: =SUM(Q26:S26) -> 0
B27: Pizza Pasta | C27: 4 | D27: 9 | E27: 5 | F27: 9 | G27: 5 | H27: 9 | M27: Pizza Pasta | T27: =SUM(Q27:S27) -> 0
B28: Toasted | C28: 3 | D28: 9 | E28: 4 | F28: 9 | G28: 4 | H28: 9 | M28: Toasted | T28: =SUM(Q28:S28) -> 0
B29: Off Beat | C29: 3 | D29: 9 | E29: 4 | F29: 9 | G29: 4 | H29: 9 | M29: Off Beat | T29: =SUM(Q29:S29) -> 0
B30: Zambrero | C30: 6 | D30: 9 | E30: 8 | F30: 9 | G30: 8 | H30: 9 | M30: Zambrero | T30: =SUM(Q30:S30) -> 0
B31: Duomo - relocated | C31: 2 | D31: 9 | E31: 3 | F31: 9 | G31: 3 | H31: 9 | M31: Duomo - relocated | T31: =SUM(Q31:S31) -> 0
B32: Ice Cream | C32: 1 | D32: 9 | E32: 2 | F32: 9 | G32: 2 | H32: 9 | M32: Ice Cream | T32: =SUM(Q32:S32) -> 0
B33: Ice Cream | C33: 1 | D33: 9 | E33: 2 | F33: 9 | G33: 2 | H33: 9 | M33: Ice Cream | T33: =SUM(Q33:S33) -> 0
B34: Ice Cream | C34: 1 | D34: 9 | E34: 1 | F34: 9 | G34: 1 | H34: 9 | M34: Ice Cream | T34: =SUM(Q34:S34) -> 0
T35: =SUM(Q35:S35) -> 0
T36: =SUM(Q36:S36) -> 0
T37: =SUM(Q37:S37) -> 0
T38: =SUM(Q38, R38, S38) -> 0
P40: Total | Q40: =SUM(Q25:Q39) -> 0 | R40: =SUM(R25:R39) -> 0 | S40: =SUM(S25:S37) -> 0 | T40: =SUM(Q40, R40, S40) -> 0
B41: Stock Boys | C41: 2 | D41: 9 | E41: 3 | F41: 9 | G41: 3 | H41: 9 | J41: Main Arena | P41: Commission | Q41: =Q40*20% -> 0 | R41: =R40*20% -> 0 | S41: =S40*20% -> 0 | T41: =SUM(Q41, R41, S41) -> 0
B42: Total | C42: =SUM(C25:C41) -> 33 | D42: =SUM(D25:D41) -> 99 | E42: =SUM(E25:E41) -> 48 | F42: =SUM(F25:F41) -> 99 | G42: =SUM(G25:G41) -> 48 | H42: =SUM(H25:H41) -> 99 | I42: =SUM(I25:I41) -> 0 | J42: =SUM(J25:J41) -> 0 | K42: =SUM(K25:K41) -> 0 | P42: Expected Payout | Q42: =Q40-Q41 -> 0 | R42: =R40-R41 -> 0 | S42: =S40-S41 -> 0 | T42: =SUM(Q42, R42, S42) -> 0
P43: Actual Payout
P44: WIFI/Power/Card
B46: Staff Names
B48: Staff Id | C48: Group Chat | D48: First Name | E48: Last Name | F48: Phone Number | G48: Email | H48: Source | I48: Days Available | L48: Wages
I49: Friday | J49: Saturday | K49: Sunday | L49: Paid | M49: Total Days | N49: Total Owed
C50: FALSE | D50: Lauren | E50: Obrien | I50: FALSE | J50: FALSE | K50: FALSE | L50: FALSE | M50: =COUNTIF(I50:K50,TRUE) -> 0 | N50: =M50*120 -> 0
C51: FALSE | D51: Thomas | E51: Obrien | I51: FALSE | J51: FALSE | K51: FALSE | L51: FALSE | M51: =COUNTIF(I51:K51,TRUE) -> 0 | N51: =M51*120 -> 0
C52: FALSE | D52: Robert | E52: Mahon | I52: FALSE | J52: FALSE | K52: FALSE | L52: FALSE | M52: =COUNTIF(I52:K52,TRUE) -> 0 | N52: =M52*120 -> 0
C53: FALSE | D53: Barry | E53: Or | I53: FALSE | J53: FALSE | K53: FALSE | L53: FALSE | M53: =COUNTIF(I53:K53,TRUE) -> 0 | N53: =M53*120 -> 0
C54: FALSE | D54: Kian | E54: McCarton | I54: FALSE | J54: FALSE | K54: FALSE | L54: FALSE | M54: =COUNTIF(I54:K54,TRUE) -> 0 | N54: =M54*120 -> 0
C55: FALSE | D55: Simon | E55: OConnor | I55: FALSE | J55: FALSE | K55: FALSE | L55: FALSE | M55: =COUNTIF(I55:K55,TRUE) -> 0 | N55: =M55*120 -> 0
C56: FALSE | D56: Oisin | E56: ONeill | I56: FALSE | J56: FALSE | K56: FALSE | L56: FALSE | M56: =COUNTIF(I56:K56,TRUE) -> 0 | N56: =M56*120 -> 0
C57: FALSE | D57: Samantha | E57: OBrien | I57: TRUE | J57: TRUE | K57: TRUE | L57: FALSE | M57: =COUNTIF(I57:K57,TRUE) -> 3 | N57: =M57*120 -> 360
C58: FALSE | D58: Dylan | E58: ODriscoll | I58: TRUE | J58: TRUE | K58: TRUE | L58: FALSE | M58: =COUNTIF(I58:K58,TRUE) -> 3 | N58: =M58*120 -> 360
C59: FALSE | D59: Darren | E59: ODriscoll | I59: FALSE | J59: TRUE | K59: TRUE | L59: FALSE | M59: =COUNTIF(I59:K59,TRUE) -> 2 | N59: =M59*120 -> 240
C60: FALSE | D60: Jade | E60: ODriscoll | I60: FALSE | J60: TRUE | K60: TRUE | L60: FALSE | M60: =COUNTIF(I60:K60,TRUE) -> 2 | N60: =M60*120 -> 240
C61: FALSE | D61: Louise | E61: ODriscoll | I61: FALSE | J61: TRUE | K61: TRUE | L61: FALSE | M61: =COUNTIF(I61:K61,TRUE) -> 2 | N61: =M61*120 -> 240
... C108: FALSE | D108: Aidan | E108: Fennell | I108: TRUE | J108: TRUE | K108: TRUE | L108: FALSE | M108: =COUNTIF(I108:K108,TRUE) -> 3 | N108: =M108*120 -> 360
C109: FALSE | I109: FALSE | J109: FALSE | K109: FALSE | L109: FALSE | M109: =COUNTIF(I109:K109,TRUE) -> 0 | N109: =M109*120 -> 0
C110: FALSE | I110: FALSE | J110: FALSE | K110: FALSE | L110: FALSE | M110: =COUNTIF(I110:K110,TRUE) -> 0 | N110: =M110*120 -> 0
C111: FALSE | I111: FALSE | J111: FALSE | K111: FALSE | L111: FALSE | M111: =COUNTIF(I111:K111,TRUE) -> 0 | N111: =M111*120 -> 0
C112: FALSE | I112: FALSE | J112: FALSE | K112: FALSE | L112: FALSE | M112: =COUNTIF(I112:K112,TRUE) -> 0 | N112: =M112*120 -> 0
C113: FALSE | I113: FALSE | J113: FALSE | K113: FALSE | L113: FALSE | M113: =COUNTIF(I113:K113,TRUE) -> 0 | N113: =M113*120 -> 0
C114: FALSE | I114: FALSE | J114: FALSE | K114: FALSE | L114: FALSE | M114: =COUNTIF(I114:K114,TRUE) -> 0 | N114: =M114*120 -> 0
C115: FALSE | I115: FALSE | J115: FALSE | K115: FALSE | L115: FALSE | M115: =COUNTIF(I115:K115,TRUE) -> 0 | N115: =M115*120 -> 0
C116: FALSE | I116: FALSE | J116: FALSE | K116: FALSE | L116: FALSE | M116: =COUNTIF(I116:K116,TRUE) -> 0 | N116: =M116*120 -> 0
C117: FALSE | I117: FALSE | J117: FALSE | K117: FALSE | L117: FALSE | M117: =COUNTIF(I117:K117,TRUE) -> 0 | N117: =M117*120 -> 0
C118: FALSE | I118: FALSE | J118: FALSE | K118: FALSE | L118: FALSE | M118: =COUNTIF(I118:K118,TRUE) -> 0 | N118: =M118*120 -> 0
C119: FALSE | I119: FALSE | J119: FALSE | K119: FALSE | L119: FALSE | M119: =COUNTIF(I119:K119,TRUE) -> 0 | N119: =M119*120 -> 0
C120: FALSE | I120: FALSE | J120: FALSE | K120: FALSE | L120: FALSE | M120: =COUNTIF(I120:K120,TRUE) -> 0 | N120: =M120*120 -> 0
C121: FALSE | I121: FALSE | J121: FALSE | K121: FALSE | L121: FALSE | M121: =COUNTIF(I121:K121,TRUE) -> 0 | N121: =M121*120 -> 0
I122: FALSE | J122: FALSE | K122: FALSE | M122: =COUNTIF(I122:K122,TRUE) -> 0 | N122: =M122*120 -> 0
I123: FALSE | J123: FALSE | K123: FALSE | M123: =COUNTIF(I123:K123,TRUE) -> 0 | N123: =M123*120 -> 0
I124: FALSE | J124: FALSE | K124: FALSE | M124: =COUNTIF(I124:K124,TRUE) -> 0 | N124: =M124*120 -> 0
I125: FALSE | J125: FALSE | K125: FALSE | M125: =COUNTIF(I125:K125,TRUE) -> 0 | N125: =M125*120 -> 0
I126: FALSE | J126: FALSE | K126: FALSE | M126: =COUNTIF(I126:K126,TRUE) -> 0 | N126: =M126*120 -> 0
I127: FALSE | J127: FALSE | K127: FALSE | M127: =COUNTIF(I127:K127,TRUE) -> 0 | N127: =M127*120 -> 0
I128: FALSE | J128: FALSE | K128: FALSE | M128: =COUNTIF(I128:K128,TRUE) -> 0 | N128: =M128*120 -> 0
I129: FALSE | J129: FALSE | K129: FALSE | M129: =COUNTIF(I129:K129,TRUE) -> 0 | N129: =M129*120 -> 0
I130: FALSE | J130: FALSE | K130: FALSE | M130: =COUNTIF(I130:K130,TRUE) -> 0 | N130: =M130*120 -> 0
I131: FALSE | J131: FALSE | K131: FALSE | M131: =COUNTIF(I131:K131,TRUE) -> 0 | N131: =M131*120 -> 0
I132: FALSE | J132: FALSE | K132: FALSE | M132: =COUNTIF(I132:K132,TRUE) -> 0 | N132: =M132*120 -> 0
I133: FALSE | J133: FALSE | K133: FALSE | M133: =COUNTIF(I133:K133,TRUE) -> 0 | N133: =M133*120 -> 0
... I149: FALSE | J149: FALSE | K149: FALSE | M149: =COUNTIF(I149:K149,TRUE) -> 0 | N149: =M149*120 -> 0
I150: FALSE | J150: FALSE | K150: FALSE
I151: FALSE | J151: FALSE | K151: FALSE | M151: =SUM(M50:M150) -> 104 | N151: =SUM(N50:N149) -> 12480

Sheet LATM
A1: Live at the Marquee
A2: Stall/Unit Name | C2: 🅿️ | D2: 🧽 | E2: ⚡️ | F2: 🌡️ | G2: 💻
A3: Pizza Pasta | C3: FALSE | D3: FALSE | E3: FALSE | F3: FALSE | G3: FALSE | H3: FALSE
A4: Smash Burger | C4: FALSE | D4: FALSE | E4: FALSE | F4: FALSE | G4: FALSE | H4: FALSE
A5: Pitt Bros BBQ | C5: FALSE | D5: FALSE | E5: FALSE | F5: FALSE | G5: FALSE | H5: FALSE
A6: Franks Hot Dog | C6: FALSE | D6: FALSE | E6: FALSE | F6: FALSE | G6: FALSE | H6: FALSE
A7: Angelo's Pizza | C7: FALSE | D7: FALSE | E7: FALSE | F7: FALSE | G7: FALSE | H7: FALSE
A8: Kiosk | C8: FALSE | D8: FALSE | E8: FALSE | F8: FALSE | G8: FALSE | H8: FALSE
A9: Caffe Duomo | C9: FALSE | D9: FALSE | E9: FALSE | F9: FALSE | G9: FALSE | H9: FALSE
A10: Coca Cola Can | C10: FALSE | D10: FALSE | E10: FALSE | F10: FALSE | G10: FALSE | H10: FALSE
A11: Ice Cream Van | C11: FALSE | D11: FALSE | E11: FALSE | F11: FALSE | G11: FALSE | H11: FALSE
A14: Takings | C14: 45833 | E14: 45834 | G14: 45835 | I14: 45836 | K14: 45837 | M14: 45839 | O14: 45840 | Q14: 45841 | S14: 45842 | U14: 45843 | W14: 45845 | Y14: 45846 | AA14: 45847 | AC14: 45848 | AE14: 45849 | AG14: 45850 | AI14: 45851 | AK14: 45854 | AM14: 45855 | AO14: 45856 | AQ14: 45857 | AS14: 45858 | AU14: 45860 | AW14: 45861 | AY14: 45862 | BA14: 45863 | BC14: 45864 | BE14: 45865
C15: Picture This -Sold Out | E15: Picture This -Extra Date Added | G15: The Coronas | I15: Christy Moore -Sold Out | K15: Dara O‘Briain | M15: Joe Bonamassa Plays Rory Gallagher -Sold Out | O15: Joe Bonamassa Plays Rory Gallagher -Sold Out | Q15: Joe Bonamassa Plays Rory Gallagher -Extra Date | S15: Tommy Tiernan | U15: Tommy Tiernan - Sold Out | W15: Roy Keane and Roddy Doyle - Sold Out | Y15: Roy Keane and Roddy Doyle - Sold Out | AA15: Roy Keane and Roddy Doyle - Sold Out | AC15: The Waterboys | AE15: Chris Kent | AG15: Dec Pierce | AI15: Olly Murs | AK15: Kingfishr - Sold Out | AM15: Amble - Sold Out | AO15: The Mary Wallopers | AQ15: Cian Ducrot - Sold Out | AS15: Cian Ducrot | AU15: D-Block Europe | AW15: D-Block Europe - Sold Out | AY15: Kingfishr - Sold Out | BA15: Michael McIntyre - Sold Out | BC15: Michael McIntyre - Sold Out | BE15: Michael McIntyre - Sold Out
C16: Cash | D16: Card | E16: Cash | F16: Card | G16: Cash | H16: Card | I16: Cash | J16: Card | K16: Cash | L16: Card | M16: Cash | N16: Card | O16: Cash | P16: Card | Q16: Cash | R16: Card | S16: Cash | T16: Card | U16: Cash | V16: Card | W16: Cash | X16: Card | Y16: Cash | Z16: Card | AA16: Cash | AB16: Card | AC16: Cash | AD16: Card | AE16: Cash | AF16: Card | AG16: Cash | AH16: Card | AI16: Cash | AJ16: Card | AK16: Cash | AL16: Card | AM16: Cash | AN16: Card | AO16: Cash | AP16: Card | AQ16: Cash | AR16: Card | AS16: Cash | AT16: Card | AU16: Cash | AV16: Card | AW16: Cash | AX16: Card | AY16: Cash | AZ16: Card | BA16: Cash | BB16: Card | BC16: Cash | BD16: Card | BE16: Cash | BF16: Card | BG16: Cash | BH16: Card
A17: Smash Burger | C17: 360 | D17: 2980 | E17: 490 | F17: 2856 | BG17: =SUM(C17, E17, G17, I17, K17, M17, O17, Q17, S17, U17, W17, Y17, AA17, AC17, AE17, AG17, AI17, AK17, AM17, AO17, AQ17, AS17, AU17, AW17, AY17, BA17, BC17, BE17) -> 850 | BH17: =SUM(D17, F17, H17, J17, L17, N17, P17, R17, T17, V17, X17, Z17, AB17, AD17, AF17, AH17, AJ17, AL17, AN17, AP17, AR17, AT17, AV17, AX17, AZ17, BB17, BD17, BF17) -> 5836
A18: Pitt Bros BBQ | C18: 790 | D18: 531 | E18: 510 | F18: 962 | BG18: =SUM(C18, E18, G18, I18, K18, M18, O18, Q18, S18, U18, W18, Y18, AA18, AC18, AE18, AG18, AI18, AK18, AM18, AO18, AQ18, AS18, AU18, AW18, AY18, BA18, BC18, BE18) -> 1300 | BH18: =SUM(D18, F18, H18, J18, L18, N18, P18, R18, T18, V18, X18, Z18, AB18, AD18, AF18, AH18, AJ18, AL18, AN18, AP18, AR18, AT18, AV18, AX18, AZ18, BB18, BD18, BF18) -> 1493
A19: Franks Hot Dog | C19: 300 | D19: 1564 | E19: 390 | F19: 1600 | BG19: =SUM(C19, E19, G19, I19, K19, M19, O19, Q19, S19, U19, W19, Y19, AA19, AC19, AE19, AG19, AI19, AK19, AM19, AO19, AQ19, AS19, AU19, AW19, AY19, BA19, BC19, BE19) -> 690 | BH19: =SUM(D19, F19, H19, J19, L19, N19, P19, R19, T19, V19, X19, Z19, AB19, AD19, AF19, AH19, AJ19, AL19, AN19, AP19, AR19, AT19, AV19, AX19, AZ19, BB19, BD19, BF19) -> 3164
A20: Angelo's Pizza | C20: 250 | D20: 1080 | E20: 190 | F20: 1000 | BG20: =SUM(C20, E20, G20, I20, K20, M20, O20, Q20, S20, U20, W20, Y20, AA20, AC20, AE20, AG20, AI20, AK20, AM20, AO20, AQ20, AS20, AU20, AW20, AY20, BA20, BC20, BE20) -> 440 | BH20: =SUM(D20, F20, H20, J20, L20, N20, P20, R20, T20, V20, X20, Z20, AB20, AD20, AF20, AH20, AJ20, AL20, AN20, AP20, AR20, AT20, AV20, AX20, AZ20, BB20, BD20, BF20) -> 2080
A21: Kiosk | C21: 415 | D21: 2864 | E21: 580 | F21: 1609 | BG21: =SUM(C21, E21, G21, I21, K21, M21, O21, Q21, S21, U21, W21, Y21, AA21, AC21, AE21, AG21, AI21, AK21, AM21, AO21, AQ21, AS21, AU21, AW21, AY21, BA21, BC21, BE21) -> 995 | BH21: =SUM(D21, F21, H21, J21, L21, N21, P21, R21, T21, V21, X21, Z21, AB21, AD21, AF21, AH21, AJ21, AL21, AN21, AP21, AR21, AT21, AV21, AX21, AZ21, BB21, BD21, BF21) -> 4473
A22: Caffe Duomo | C22: 650 | D22: 420 | E22: 120 | F22: 760 | BG22: =SUM(C22, E22, G22, I22, K22, M22, O22, Q22, S22, U22, W22, Y22, AA22, AC22, AE22, AG22, AI22, AK22, AM22, AO22, AQ22, AS22, AU22, AW22, AY22, BA22, BC22, BE22) -> 770 | BH22: =SUM(D22, F22, H22, J22, L22, N22, P22, R22, T22, V22, X22, Z22, AB22, AD22, AF22, AH22, AJ22, AL22, AN22, AP22, AR22, AT22, AV22, AX22, AZ22, BB22, BD22, BF22) -> 1180
A23: Coca Cola Can | BG23: =SUM(C23, E23, G23, I23, K23, M23, O23, Q23, S23, U23, W23, Y23, AA23, AC23, AE23, AG23, AI23, AK23, AM23, AO23, AQ23, AS23, AU23, AW23, AY23, BA23, BC23, BE23) -> 0 | BH23: =SUM(D23, F23, H23, J23, L23, N23, P23, R23, T23, V23, X23, Z23, AB23, AD23, AF23, AH23, AJ23, AL23, AN23, AP23, AR23, AT23, AV23, AX23, AZ23, BB23, BD23, BF23) -> 0
A24: Ice Cream Van | C24: 280 | D24: 870 | E24: 250 | F24: 516 | BG24: =SUM(C24, E24, G24, I24, K24, M24, O24, Q24, S24, U24, W24, Y24, AA24, AC24, AE24, AG24, AI24, AK24, AM24, AO24, AQ24, AS24, AU24, AW24, AY24, BA24, BC24, BE24) -> 530 | BH24: =SUM(D24, F24, H24, J24, L24, N24, P24, R24, T24, V24, X24, Z24, AB24, AD24, AF24, AH24, AJ24, AL24, AN24, AP24, AR24, AT24, AV24, AX24, AZ24, BB24, BD24, BF24) -> 1386
A25: Total | C25: =SUM(C17:C24) -> 3045 | D25: =SUM(D17:D24) -> 10309 | E25: =SUM(E17:E24) -> 2530 | F25: =SUM(F17:F24) -> 9303 | G25: =SUM(G17:G24) -> 0 | H25: =SUM(H17:H24) -> 0 | I25: =SUM(I17:I24) -> 0 | J25: =SUM(J17:J24) -> 0 | ... BH25: =SUM(BH17:BH24) -> 19612
A28: Staff | C28: 45833 | E28: 45834 | G28: 45835 | I28: 45836 | K28: 45837 | M28: 45839 | O28: 45840 | Q28: 45841 | S28: 45842 | U28: 45843 | W28: 45845 | Y28: 45846 | AA28: 45847 | AC28: 45848 | AE28: 45849 | AG28: 45850 | AI28: 45851 | AK28: 45854 | AM28: 45855 | AO28: 45856 | AQ28: 45857 | AS28: 45858 | AU28: 45860 | AW28: 45861 | AY28: 45862 | BA28: 45863 | BC28: 45864 | BE28: 45865
C29: Picture This -Sold Out | E29: Picture This -Extra Date Added | G29: The Coronas | I29: Christy Moore -Sold Out | K29: Dara O‘Briain | M29: Joe Bonamassa Plays Rory Gallagher -Sold Out | O29: Joe Bonamassa Plays Rory Gallagher -Sold Out | Q29: Joe Bonamassa Plays Rory Gallagher -Extra Date | S29: Tommy Tiernan | U29: Tommy Tiernan - Sold Out | W29: Roy Keane and Roddy Doyle - Sold Out | Y29: Roy Keane and Roddy Doyle - Sold Out | AA29: Roy Keane and Roddy Doyle - Sold Out | AC29: The Waterboys | AE29: Chris Kent | AG29: Dec Pierce | AI29: Olly Murs | AK29: Kingfishr - Sold Out | AM29: Amble - Sold Out | AO29: The Mary Wallopers | AQ29: Cian Ducrot - Sold Out | AS29: Cian Ducrot | AU29: D-Block Europe | AW29: D-Block Europe - Sold Out | AY29: Kingfishr - Sold Out | BA29: Michael McIntyre - Sold Out | BC29: Michael McIntyre - Sold Out | BE29: Michael McIntyre - Sold Out
A30: Smash Burger | BG30: =SUM(C30, E30, G30, I30, K30, M30, O30, Q30, S30, U30, W30, Y30, AA30, AC30, AE30, AG30, AI30, AK30, AM30, AO30, AQ30, AS30, AU30, AW30, AY30, BA30, BC30, BE30) -> 0 | BH30: =SUM(D30, F30, H30, J30, L30, N30, P30, R30, T30, V30, X30, Z30, AB30, AD30, AF30, AH30, AJ30, AL30, AN30, AP30, AR30, AT30, AV30, AX30, AZ30, BB30, BD30, BF30) -> 0
A33: Pitt Bros BBQ | BG33: =SUM(C33, E33, G33, I33, K33, M33, O33, Q33, S33, U33, W33, Y33, AA33, AC33, AE33, AG33, AI33, AK33, AM33, AO33, AQ33, AS33, AU33, AW33, AY33, BA33, BC33, BE33) -> 0 | BH33: =SUM(D33, F33, H33, J33, L33, N33, P33, R33, T33, V33, X33, Z33, AB33, AD33, AF33, AH33, AJ33, AL33, AN33, AP33, AR33, AT33, AV33, AX33, AZ33, BB33, BD33, BF33) -> 0
A35: Franks Hot Dog | BG35: =SUM(C35, E35, G35, I35, K35, M35, O35, Q35, S35, U35, W35, Y35, AA35, AC35, AE35, AG35, AI35, AK35, AM35, AO35, AQ35, AS35, AU35, AW35, AY35, BA35, BC35, BE35) -> 0 | BH35: =SUM(D35, F35, H35, J35, L35, N35, P35, R35, T35, V35, X35, Z35, AB35, AD35, AF35, AH35, AJ35, AL35, AN35, AP35, AR35, AT35, AV35, AX35, AZ35, BB35, BD35, BF35) -> 0
A37: Angelo's Pizza | BG37: =SUM(C37, E37, G37, I37, K37, M37, O37, Q37, S37, U37, W37, Y37, AA37, AC37, AE37, AG37, AI37, AK37, AM37, AO37, AQ37, AS37, AU37, AW37, AY37, BA37, BC37, BE37) -> 0 | BH37: =SUM(D37, F37, H37, J37, L37, N37, P37, R37, T37, V37, X37, Z37, AB37, AD37, AF37, AH37, AJ37, AL37, AN37, AP37, AR37, AT37, AV37, AX37, AZ37, BB37, BD37, BF37) -> 0
A39: Kiosk | BG39: =SUM(C39, E39, G39, I39, K39, M39, O39, Q39, S39, U39, W39, Y39, AA39, AC39, AE39, AG39, AI39, AK39, AM39, AO39, AQ39, AS39, AU39, AW39, AY39, BA39, BC39, BE39) -> 0 | BH39: =SUM(D39, F39, H39, J39, L39, N39, P39, R39, T39, V39, X39, Z39, AB39, AD39, AF39, AH39, AJ39, AL39, AN39, AP39, AR39, AT39, AV39, AX39, AZ39, BB39, BD39, BF39) -> 0
A41: Caffe Duomo | BG41: =SUM(C41, E41, G41, I41, K41, M41, O41, Q41, S41, U41, W41, Y41, AA41, AC41, AE41, AG41, AI41, AK41, AM41, AO41, AQ41, AS41, AU41, AW41, AY41, BA41, BC41, BE41) -> 0 | BH41: =SUM(D41, F41, H41, J41, L41, N41, P41, R41, T41, V41, X41, Z41, AB41, AD41, AF41, AH41, AJ41, AL41, AN41, AP41, AR41, AT41, AV41, AX41, AZ41, BB41, BD41, BF41) -> 0
A43: Coca Cola Can | BG43: =SUM(C43, E43, G43, I43, K43, M43, O43, Q43, S43, U43, W43, Y43, AA43, AC43, AE43, AG43, AI43, AK43, AM43, AO43, AQ43, AS43, AU43, AW43, AY43, BA43, BC43, BE43) -> 0 | BH43: =SUM(D43, F43, H43, J43, L43, N43, P43, R43, T43, V43, X43, Z43, AB43, AD43, AF43, AH43, AJ43, AL43, AN43, AP43, AR43, AT43, AV43, AX43, AZ43, BB43, BD43, BF43) -> 0
A44: Ice Cream Van | BG44: =SUM(C44, E44, G44, I44, K44, M44, O44, Q44, S44, U44, W44, Y44, AA44, AC44, AE44, AG44, AI44, AK44, AM44, AO44, AQ44, AS44, AU44, AW44, AY44, BA44, BC44, BE44) -> 0 | BH44: =SUM(D44, F44, H44, J44, L44, N44, P44, R44, T44, V44, X44, Z44, AB44, AD44, AF44, AH44, AJ44, AL44, AN44, AP44, AR44, AT44, AV44, AX44, AZ44, BB44, BD44, BF44) -> 0
A45: Total | C45: =COUNTA(C30:D44) -> 0 | E45: =COUNTA(E30:F44) -> 0 | G45: =COUNTA(G30:H44) -> 0 | I45: =COUNTA(I30:J44) -> 0 | K45: =COUNTA(K30:L44) -> 0 | M45: =COUNTA(M30:N44) -> 0 | O45: =COUNTA(O30:P44) -> 0 | Q45: =COUNTA(Q30:R44) -> 0 | S45: =COUNTA(S30:T44) -> 0 | U45: =COUNTA(U30:V44) -> 0 | W45: =COUNTA(W30:X44) -> 0 | Y45: =COUNTA(Y30:Z44) -> 0 | AA45: =COUNTA(AA30:AB44) -> 0 | AC45: =COUNTA(AC30:AD44) -> 0 | AE45: =COUNTA(AE30:AF44) -> 0 | AG45: =COUNTA(AG30:AH44) -> 0 | AI45: =COUNTA(AI30:AJ44) -> 0 | AK45: =COUNTA(AK30:AL44) -> 0 | AM45: =COUNTA(AM30:AN44) -> 0 | AO45: =COUNTA(AO30:AP44) -> 0 | AQ45: =COUNTA(AQ30:AR44) -> 0 | AS45: =COUNTA(AS30:AT44) -> 0 | AU45: =COUNTA(AU30:AV44) -> 0 | AW45: =COUNTA(AW30:AX44) -> 0 | AY45: =COUNTA(AY30:AZ44) -> 0 | BA45: =COUNTA(BA30:BB44) -> 0 | BC45: =COUNTA(BC30:BD44) -> 0 | BE45: =COUNTA(BE30:BF44) -> 0 | BG45: =SUM(BG30:BG44) -> 0 | BH45: =SUM(BH30:BH44) -> 0

Sheet LATIG
A1: Live at the Marquee
A2: Stall/Unit Name | C2: 🅿️ | D2: 🧽 | E2: ⚡️ | F2: 🌡️ | G2: 💻
A3: Pizza Pasta | C3: FALSE | D3: FALSE | E3: FALSE | F3: FALSE | G3: FALSE | H3: FALSE
A4: Thindi | C4: FALSE | D4: FALSE | E4: FALSE | F4: FALSE | G4: FALSE | H4: FALSE
A5: Pitt Bros BBQ | C5: FALSE | D5: FALSE | E5: FALSE | F5: FALSE | G5: FALSE | H5: FALSE
A8: Takings | C8: 45841 | D8: 45842 | E8: 45844 | F8: 45849 | G8: 45850 | H8: 45851 | I8: 45855 | J8: 45856 | K8: 45857 | L8: 45858 | M8: 45839 | O8: 45840 | Q8: 45841 | S8: 45842 | U8: 45843
C9: Picture This -Sold Out | E9: Picture This -Extra Date Added | G9: The Coronas | I9: Christy Moore -Sold Out | K9: Dara O‘Briain | M9: Joe Bonamassa Plays Rory Gallagher -Sold Out | O9: Joe Bonamassa Plays Rory Gallagher -Sold Out | Q9: Joe Bonamassa Plays Rory Gallagher -Extra Date | S9: Tommy Tiernan | U9: Tommy Tiernan - Sold Out
C10: Cash | D10: Card | E10: Cash | F10: Card | G10: Cash | H10: Card | I10: Cash | J10: Card | K10: Cash | L10: Card | M10: Cash | N10: Card | O10: Cash | P10: Card | Q10: Cash | R10: Card | S10: Cash | T10: Card | U10: Cash | V10: Card
A11: Thindi
A12: Pitt Bros BBQ
A13: Total | C13: =SUM(C11:C12) -> 0 | D13: =SUM(D11:D12) -> 0 | E13: =SUM(E11:E12) -> 0 | F13: =SUM(F11:F12) -> 0 | G13: =SUM(G11:G12) -> 0 | H13: =SUM(H11:H12) -> 0 | I13: =SUM(I11:I12) -> 0 | J13: =SUM(J11:J12) -> 0 | ... V13: =SUM(V11:V12) -> 0
A16: Staff | C16: 45833 | E16: 45834 | G16: 45835 | I16: 45836 | K16: 45837 | M16: 45839 | O16: 45840 | Q16: 45841 | S16: 45842 | U16: 45843
C17: Picture This -Sold Out | E17: Picture This -Extra Date Added | G17: The Coronas | I17: Christy Moore -Sold Out | K17: Dara O‘Briain | M17: Joe Bonamassa Plays Rory Gallagher -Sold Out | O17: Joe Bonamassa Plays Rory Gallagher -Sold Out | Q17: Joe Bonamassa Plays Rory Gallagher -Extra Date | S17: Tommy Tiernan | U17: Tommy Tiernan - Sold Out
A18: Thindi
A21: Pitt Bros BBQ
A23: Total | C23: =COUNTA(C18:D22) -> 0 | E23: =COUNTA(E18:F22) -> 0 | G23: =COUNTA(G18:H22) -> 0 | I23: =COUNTA(I18:J22) -> 0 | K23: =COUNTA(K18:L22) -> 0 | M23: =COUNTA(M18:N22) -> 0 | O23: =COUNTA(O18:P22) -> 0 | Q23: =COUNTA(Q18:R22) -> 0 | S23: =COUNTA(S18:T22) -> 0 | U23: =COUNTA(U18:V22) -> 0

Sheet Rate Cards
B2: Rate Card
B3: Concept Name | C3: Cuisine / Theme | D3: Description | E3: Min. Daily Rate (€ ex. VAT) | F3: Min. Price Per Head (€)
B4: Camile Thai | C4: Thai Street Food | D4: Ireland’s top Thai food brand. Award-winning dishes & sustainability focus. | E4: 2750 | F4: 13.75
B5: Zambrero | C5: Mexican / Burrito Bowls | D5: Fast-growing global Mexican brand. Freshly made bowls, burritos, and nachos. | E5: 2500 | F5: 12.5
B6: Offbeat Donuts | C6: Artisan Donuts & Coffee | D6: Fresh daily donuts & coffee. Popular at both internal events and public gatherings. | E6: 1800 | F6: 9
B7: Pitt Bros BBQ | C7: American BBQ | D7: Smoked meats, BBQ sides. A crowd-pleasing option with a high volume service capacity. | E7: 2750 | F7: 13.75
B8: Thindi | C8: Indian Street Food | D8: Trendy Indian food from a restored French vintage truck. Colourful and flavour-packed. | E8: 2500 | F8: 12.5
B9: Sprinkles | C9: Loaded Churros / Desserts | D9: Churros and desserts concept, very popular with families and casual events. | E9: 1500 | F9: 9
B10: Desserts by Sprinkles | C10: Sweet Treats | D10: Expanded dessert concept from our Sprinkles brand – ideal for after-lunch or evening events. | E10: 1500 | F10: 9
B11: Caffe Duomo | C11: Coffee & Pastries | D11: Authentic Italian-style café concept. Great for breakfast activations and AM service. | E11: 1500 | F11: 7.5
B12: Angelo’s Neapolitan Pizza | C12: Neapolitan Pizza | D12: Traditional-style pizza made fresh on-site. High visual appeal and broad appeal. | E12: 2500 | F12: 12.5
B13: Toasted. | C13: Toasties, Coffee & Pastries | D13: Comfort food at its best – gourmet sourdough toasties, with optional coffee and pastries. | E13: 2200 | F13: 11
B14: Loaded | C14: Premium Burgers & Fries | D14: Smash burgers, loaded fries. 5 trucks available for high-demand setups. | E14: 2500 | F14: 15
B15: O’Brien’s Ice Cream | C15: Soft Serve & Treats | D15: Classic Irish ice cream trucks. 18 units available to cover all scales of events. | E15: 1500 | F15: 3
... B17: Ice Cream Trikes | C17: Portable Frozen Treats | D17: Ideal for indoor or courtyard events – serving popsicles, iced coffee, scoop ice cream. | E17: 1500 | F17: 5
B22: Rate Card
B23: Concept Name | C23: Cuisine / Theme | D23: Description | E23: Min. Daily Rate (€ ex. VAT) | F23: Min. Price Per Head (€)
B24: Camile Thai | C24: Thai Street Food | D24: Ireland’s top Thai food brand. Award-winning dishes & sustainability focus. | E24: =E4*0.9 -> 2475 | F24: =(F4*0.9) -> 12.375
B25: Zambrero | C25: Mexican / Burrito Bowls | D25: Fast-growing global Mexican brand. Freshly made bowls, burritos, and nachos. | E25: =E5*0.9 -> 2250 | F25: =F5*0.9 -> 11.25
B26: Offbeat Donuts | C26: Artisan Donuts & Coffee | D26: Fresh daily donuts & coffee. Popular at both internal events and public gatherings. | E26: =E6*0.9 -> 1620 | F26: =F6*0.9 -> 8.1
B27: Pitt Bros BBQ | C27: American BBQ | D27: Smoked meats, BBQ sides. A crowd-pleasing option with a high volume service capacity. | E27: =E7*0.9 -> 2475 | F27: =F7*0.9 -> 12.375
B28: Thindi | C28: Indian Street Food | D28: Trendy Indian food from a restored French vintage truck. Colourful and flavour-packed. | E28: =E8*0.9 -> 2250 | F28: =F8*0.9 -> 11.25
B29: Sprinkles | C29: Loaded Churros / Desserts | D29: Churros and desserts concept, very popular with families and casual events. | E29: =E9*0.9 -> 1350 | F29: =F9*0.9 -> 8.1
B30: Desserts by Sprinkles | C30: Sweet Treats | D30: Expanded dessert concept from our Sprinkles brand – ideal for after-lunch or evening events. | E30: =E10*0.9 -> 1350 | F30: =F10*0.9 -> 8.1
B31: Caffe Duomo | C31: Coffee & Pastries | D31: Authentic Italian-style café concept. Great for breakfast activations and AM service. | E31: =E11*0.9 -> 1350 | F31: =F11*0.9 -> 6.75
B32: Angelo’s Neapolitan Pizza | C32: Neapolitan Pizza | D32: Traditional-style pizza made fresh on-site. High visual appeal and broad appeal. | E32: =E12*0.9 -> 2250 | F32: =F12*0.9 -> 11.25
B33: Toasted. | C33: Toasties, Coffee & Pastries | D33: Comfort food at its best – gourmet sourdough toasties, with optional coffee and pastries. | E33: =E13*0.9 -> 1980 | F33: =F13*0.9 -> 9.9
B34: Loaded | C34: Premium Burgers & Fries | D34: Smash burgers, loaded fries. 5 trucks available for high-demand setups. | E34: =E14*0.9 -> 2250 | F34: =F14*0.9 -> 13.5
B35: O’Brien’s Ice Cream | C35: Soft Serve & Treats | D35: Classic Irish ice cream trucks. 18 units available to cover all scales of events. | E35: =E15*0.9 -> 1350 | F35: =F15*0.9 -> 2.7
B36: Vintage Ice Cream Vans | C36: Retro Ice Cream | D36: Fully restored vintage ice cream vans. Great for summer and nostalgic activations. | E36: =E16*0.9 -> 1620 | F36: =F16*0.9 -> 6.3
B37: Ice Cream Trikes | C37: Portable Frozen Treats | D37: Ideal for indoor or courtyard events – serving popsicles, iced coffee, scoop ice cream. | E37: =E17*0.9 -> 1350 | F37: =F17*0.9 -> 4.5

Sheet Cash Lifts
A1: Cash Lifts
A2: Event | B2: Date | C2: Unit | D2: Venue | E2: Lift 1 | F2: Lift 2 | G2: Lift 3 | H2: Lift 4 | I2: Total
A3: Christmas Festival | B3: 45653 | C3: Toasted | D3: Leopardstown | E3: 300 | F3: 200 | G3: 300 | H3: 430 | I3: =SUM(E3:H3) -> 1230
C4: Loaded | D4: Leopardstown | E4: 700 | F4: 1000 | G4: 400 | H4: 1620 | I4: =SUM(E4:H4) -> 3720
C5: Pitt Bros | D5: Leopardstown | E5: 400 | F5: 400 | G5: 500 | H5: 420 | I5: =SUM(E5:H5) -> 1720
C6: Thindi | D6: Leopardstown | E6: 150 | F6: 400 | G6: 110 | I6: =SUM(E6:H6) -> 660
C7: Camile | D7: Leopardstown | E7: 700 | F7: 710 | G7: 290 | I7: =SUM(E7:H7) -> 1700
C8: Kiosk | D8: Leopardstown | E8: 450 | F8: 350 | G8: 760 | I8: =SUM(E8:H8) -> 1560
C9: Vintage Coffee | D9: Leopardstown | E9: 450 | F9: 820 | I9: =SUM(E9:H9) -> 1270
C10: Off Beat Donut | D10: Leopardstown | E10: 450 | F10: 150 | G10: 360 | I10: =SUM(E10:H10) -> 960
C11: Coffee (Trackside) | D11: Leopardstown | E11: 150 | F11: 130 | I11: =SUM(E11:H11) -> 280
A12: Christmas Festival | B12: 45654 | C12: Toasted | D12: Leopardstown | E12: 535 | F12: 210 | G12: 275 | I12: =SUM(E12:H12) -> 1020
C13: Loaded | D13: Leopardstown | E13: 910 | F13: 910 | G13: 460 | H13: 570 | I13: =SUM(E13:H13) -> 2850
C14: Pitt Bros | D14: Leopardstown | E14: 800 | F14: 560 | I14: =SUM(E14:H14) -> 1360
C15: Thindi | D15: Leopardstown | E15: 150 | F15: 700 | I15: =SUM(E15:H15) -> 850
C16: Camile | D16: Leopardstown | E16: 580 | F16: 550 | I16: =SUM(E16:H16) -> 1130
C17: Kiosk | D17: Leopardstown | E17: 655 | I17: =SUM(E17:H17) -> 655
C18: Vintage Coffee | D18: Leopardstown | I18: =SUM(E18:H18) -> 0
C19: Off Beat Donut | D19: Leopardstown | E19: 535 | I19: =SUM(E19:H19) -> 535
C20: Coffee (Trackside) | D20: Leopardstown | E20: 530 | I20: =SUM(E20:H20) -> 530
A21: Christmas Festival | B21: 45655 | C21: Toasted | D21: Leopardstown | E21: 250 | I21: =SUM(E21:H21) -> 250
C22: Loaded | D22: Leopardstown | E22: 500 | F22: 600 | I22: =SUM(E22:H22) -> 1100
C23: Pitt Bros | D23: Leopardstown | E23: 200 | I23: =SUM(E23:H23) -> 200
C24: Thindi | D24: Leopardstown | E24: 50 | I24: =SUM(E24:H24) -> 50
C25: Camile | D25: Leopardstown | E25: 250 | I25: =SUM(E25:H25) -> 250
C26: Kiosk | D26: Leopardstown | E26: 300 | I26: =SUM(E26:H26) -> 300
C27: Vintage Coffee | D27: Leopardstown | E27: 300 | I27: =SUM(E27:H27) -> 300
C28: Off Beat Donut | D28: Leopardstown | E28: 200 | I28: =SUM(E28:H28) -> 200
C29: Coffee (Trackside) | D29: Leopardstown | I29: =SUM(E29:H29) -> 0
I30: =SUM(I3:I11) -> 13100
A34: Float
A36: Event | B36: Date | C36: Unit | D36: Venue | E36: Float
A37: Christmas Festival | B37: 45653 | C37: Toasted | D37: Leopardstown | E37: 175
C38: Loaded | D38: Leopardstown | E38: 175
C39: Pitt Bros | D39: Leopardstown | E39: 175
C40: Thindi | D40: Leopardstown | E40: 175
C41: Camile | D41: Leopardstown | E41: 150
C42: Kiosk | D42: Leopardstown | E42: 175
C43: Vintage Coffee | D43: Leopardstown | E43: 175
C44: Off Beat Donut | D44: Leopardstown | E44: 175
C45: Coffee (Trackside) | D45: Leopardstown | E45: 175
E46: =SUM(E37:E45) -> 1550

Sheet FitzersLevy
A1: Fitzers/Levy Commission Sheet 2024 | I1: Fitzers/Levy Commission Sheet 2024
A2: Event | B2: Date(s) | C2: Unit Name | D2: Venue | E2: Turnover | F2: Vouchers | I2: Event | J2: Date(s) | K2: Unit Name | L2: Venue | M2: Turnover | N2: Vouchers
A3: Champions Weekend | B3: 45178 | C3: Vintage Coffee | D3: Leopardstown | E3: 1205 | I3: American Football | J3: 45164 | K3: Candyfloss | L3: Aviva | M3: 230 | N3: -
C4: Ice Cream | D4: Leopardstown | E4: 700 | K4: Popcorn | L4: Aviva | M4: 2379 | N4: -
C5: Toasted | D5: Leopardstown | E5: 1000 | K5: Ice Cream | L5: Aviva | M5: 44 | N5: -
C6: Zambrero | D6: Leopardstown | E6: 1800 | K6: Offbeat | L6: Aviva | M6: 2535 | N6: -
C7: Pitt Bros | D7: Leopardstown | E7: 1920 | K7: Zambrero | L7: Aviva | M7: 1155.9 | N7: -
C8: Off Beat | D8: Leopardstown | E8: 1200 | I8: FAI Women's Intl | J8: 45192 | K8: Offbeat | L8: Aviva | M8: 1577 | N8: -
C9: Ice Cream | D9: Leopardstown | E9: 1100 | I9: FAI Cup Final | J9: 45242 | K9: Offbeat | L9: Aviva | M9: - | N9: -
K10: Candyfloss | L10: Aviva | M10: - | N10: -
A11: Winter Festival | B11: 45262 | C11: Toasted | D11: Fairyhouse | E11: 1260 | K11: Popcorn | L11: Aviva | M11: - | N11: -
C12: Caffe Duomo | D12: Fairyhouse | E12: 710 | I12: Six Nations | J12: 45333 | K12: Offbeat | L12: Aviva | M12: - | N12: -
C13: Off Beat | D13: Fairyhouse | E13: 590 | I13: Taylor Swift | J13: 45471 | K13: Camile | L13: Aviva | M13: 4450 | N13: -
K14: Burger | L14: Aviva | M14: 8035 | N14: -
B15: 45263 | C15: Toasted | D15: Fairyhouse | E15: 2920 | K15: Ice Cream | L15: Aviva | M15: 1586 | N15: -
C16: Caffe Duomo | D16: Fairyhouse | E16: 1530 | K16: Offbeat | L16: Aviva | M16: 2260.3 | N16: -
C17: Off Beat | D17: Fairyhouse | E17: 1470 | I17: Taylor Swift | J17: 45472 | K17: Camile | L17: Aviva | M17: 2659 | N17: -
K18: Burger | L18: Aviva | M18: 8749.5 | N18: -
A19: Christmas Festival | B19: 45286 | C19: Caffe Duomo | D19: Leopardstown | E19: 3720 | K19: Ice Cream | L19: Aviva | M19: 852.5 | N19: -
C20: Pitt Bros | D20: Leopardstown | E20: 3680 | K20: Offbeat | L20: Aviva | M20: 2686.5 | N20: -
C21: Loaded | D21: Leopardstown | E21: 5980 | I21: Taylor Swift | J21: 45473 | K21: Camile | L21: Aviva | M21: 3012 | N21: -
C22: Off Beat | D22: Leopardstown | E22: 2035 | K22: Burger | L22: Aviva | M22: 7001 | N22: -
K23: Van | L23: Aviva | M23: 1206 | N23: -
B24: 45287 | C24: Caffe Duomo | D24: Leopardstown | E24: 3752 | K24: Offbeat | L24: Aviva | M24: - | N24: -
C25: Pitt Bros | D25: Leopardstown | E25: 5816 | I25: American Football | J25: 45528 | K25: Offbeat | L25: Aviva | M25: - | N25: -
C26: Loaded | D26: Leopardstown | E26: 1880 | K26: Popcorn | L26: Aviva | M26: - | N26: -
C27: Off Beat | D27: Leopardstown | E27: 3713
C28: Caffe Duomo Trackside | D28: Leopardstown | E28: 1788
M29: =SUM(M2:M26) -> 50418.7
B30: 45288 | C30: Caffe Duomo | D30: Leopardstown | E30: 3834
C31: Pitt Bros | D31: Leopardstown | E31: 5380
C32: Loaded | D32: Leopardstown | E32: 2224
C33: Off Beat | D33: Leopardstown | E33: 2618
C34: Caffe Duomo Trackside | D34: Leopardstown | E34: 2008
B36: 45289 | C36: Caffe Duomo | D36: Leopardstown | E36: 2650
C37: Pitt Bros | D37: Leopardstown | E37: 940
C38: Loaded | D38: Leopardstown | E38: 2640
C39: Off Beat | D39: Leopardstown | E39: 1236
C40: Caffe Duomo Trackside | D40: Leopardstown | E40: 1256
A43: Dublin Racing Festival | B43: 45325 | C43: Pitt Bros | D43: Leopardstown | E43: 4892
C44: Off Beat | D44: Leopardstown | E44: 2529
C45: Camile Thai | D45: Leopardstown | E45: 5210.6
C46: Caffe Duomo | D46: Leopardstown | E46: 3040
C47: Vintage Coffee | D47: Leopardstown | E47: 1514
C48: Caffe Duomo Trackside | D48: Leopardstown | E48: 2018.5
B50: 45326 | C50: Pitt Bros | D50: Leopardstown | E50: 4034
C51: Off Beat | D51: Leopardstown | E51: 2420.2
C52: Camile Thai | D52: Leopardstown | E52: 6392.5
C53: Caffe Duomo | D53: Leopardstown | E53: 3322.4
C54: Vintage Coffee | D54: Leopardstown | E54: 2609.5
C55: Caffe Duomo Trackside | D55: Leopardstown | E55: 2758
A57: Irish Grand National | B57: 45381 | C57: Nobo | D57: Fairyhouse | E57: 286
C58: Caffe Duomo | D58: Fairyhouse | E58: 789.6
C59: Off Beat | D59: Fairyhouse | E59: 632.5
C60: Toasted | D60: Fairyhouse | E60: 527
C61: Camile Thai | D61: Fairyhouse | E61: 935
B63: 45382 | C63: Nobo | D63: Fairyhouse | E63: 410
C64: Caffe Duomo | D64: Fairyhouse | E64: 1880.5
C65: Sprinkles | D65: Fairyhouse | E65: 711
C66: Toasted | D66: Fairyhouse | E66: 1184.3
C67: Off Beat | D67: Fairyhouse | E67: 1770
C68: Loaded | D68: Fairyhouse | E68: 2253
C69: Camile Thai | D69: Fairyhouse | E69: 1520
C70: Pitt Bros | E70: 2880
C71: Caffe Duomo | E71: 634.85
B73: 45383 | C73: Nobo | D73: Fairyhouse | E73: 675
C74: Caffe Duomo | D74: Fairyhouse | E74: 3294.5
C75: Sprinkles | D75: Fairyhouse | E75: 432.5
C76: Toasted | D76: Fairyhouse | E76: 3253.3
C77: Off Beat | D77: Fairyhouse | E77: 3093
C78: Loaded | D78: Fairyhouse | E78: 5461.54
C79: Camile Thai | D79: Fairyhouse | E79: 2696
C80: Pitt Bros | D80: Fairyhouse | E80: 4832
C81: Caffe Duomo | D81: Fairyhouse | E81: 1144.55
A84: Student Raceday | B84: 45392 | C84: Loaded | D84: Leopardstown | E84: 5665.5
C85: Camile Thai | D85: Leopardstown | E85: 4020
C86: Pizza | D86: Leopardstown | E86: 5039.3
C87: Pitt Bros | D87: Leopardstown | E87: 2412.5
C88: Churro | D88: Leopardstown | E88: 1014
B90: 45471 | C90: Smash | D90: Curragh | E90: 660 | F90: 18 | G90: 50 vouchers @ €15 Sheehys
B91: 45472 | C91: Smash | D91: Curragh | E91: 1050 | F91: 12
B92: 45473 | C92: Smash | D92: Curragh | E92: 760 | F92: 17
A94: Bulmers Live | B94: 45484 | C94: Pizza | D94: Leopardstown | E94: 605 | F94: 120
B96: 45491 | C96: Pizza | D96: Leopardstown | E96: 855 | F96: 142
C97: Smash | D97: Leopardstown | E97: 2361 | F97: 182
C98: Ice Cream | D98: Leopardstown | E98: 870
B100: 45498 | C100: Pizza | D100: Leopardstown | E100: 936 | F100: 134
C101: Smash | D101: Leopardstown | E101: 2472 | F101: 245
C102: Ice Cream | D102: Leopardstown | E102: 805
B104: 45512 | C104: Camile | D104: Leopardstown | E104: 2221 | F104: 234
C105: Smash | D105: Leopardstown | E105: 3480 | F105: 245
C106: Ice Cream | D106: Leopardstown | E106: 872
B108: 45526 | C108: Smash | D108: Leopardstown | E108: 3010 | F108: 242
C109: Thindi | D109: Leopardstown | E109: 616 | F109: 137
C110: Pitt Bros | D110: Leopardstown | E110: 1280 | F110: 163
C111: Ice Cream | D111: Leopardstown | E111: 350
A113: Pink Run | B113: 45535 | C113: Caffe Duomo | D113: Leopardstown | E113: 1764 | F113: 130
C114: Toasted | D114: Leopardstown | E114: 1820.8
C115: Ice Cream | D115: Leopardstown | E115: 1588
A117: Champions Stake | B117: 45549 | C117: Smash | D117: Leopardstown | E117: 5551.2 | F117: 172
...

Sheet Suppliers
A1: Suppliers
A2: Supplier ID | B2: Business Name | C2: Contact Name | D2: Contact Number | E2: Email | F2: IBAN | G2: Balance | H2: Payment Method | I2: Payment Terms
A4: AIK001 | B4: Aiken Promotions | F4: IE14AIBK93106343476092 | G4: 49373 | H4: Account | I4: Account
A5: ALC001 | B5: A&L Castors LTD | H5: Cash On Delivery | I5: On Delivery
A6: ALL001 | B6: Allegen LTD | H6: Account | I6: Account
A7: ALL002 | B7: all stop trading | H7: Account | I7: Account
A8: APP001 | B8: Appsharp | H8: Cash On Delivery | I8: On Delivery
A9: APP002 | B9: Applus NCT | H9: Cash On Delivery | I9: On Delivery
A10: AUT001 | B10: Autoval | H10: Cash On Delivery | I10: On Delivery
A11: AUT002 | B11: Auto Start | H11: Cash On Delivery | I11: On Delivery
A12: AUT003 | B12: Auto & Trailer Spares Ltd | H12: Cash On Delivery | I12: On Delivery
A13: BAL001 | B13: Ballinlough Workshop | H13: Cash On Delivery | I13: On Delivery
A14: BOR001 | B14: Bord Gais | H14: Account | I14: Account
A15: BQ001 | B15: B&Q | H15: Cash On Delivery | I15: On Delivery
A16: BRE001 | B16: Bretzel Bakery | H16: Direct Debit | I16: Weekly
... A20: CAM001 | B20: Camile Ireland | H20: Direct Debit | I20: Weekly
A21: CAM002 | B21: Campion Insurance | G21: 44000 | H21: Account | I21: Account
A22: CAN001 | B22: Canavan Enterprises | H22: Account | I22: Account
A23: CAR001 | B23: Cartridge Expert | H23: Cash On Delivery | I23: On Delivery
A24: CAT001 | B24: Caterboss | H24: Cash On Delivery | I24: On Delivery
A25: CAT002 | B25: Caterline | H25: Account | I25: Account
A26: CEL001 | B26: Celuplast | H26: Cash On Delivery | I26: On Delivery
A27: CEN001 | B27: Century Fasteners Ltd | H27: Cash On Delivery | I27: On Delivery
A28: CEN002 | B28: Central Fusion | H28: Account | I28: Account
A29: CHA001 | B29: Charles Camping | H29: Cash On Delivery | I29: On Delivery
A30: CLO001 | B30: Close Brothers | H30: Direct Debit | I30: 30 Days
A31: COC001 | B31: Coca Cola | H31: Account | I31: Account
A32: COE001 | B32: COE Enterprises Ltd T/A Fabco | G32: 28000 | H32: Account | I32: Account
A33: COF001 | B33: Coffee Perfection | F33: IE66BOFI90055169389712 | G33: 15000 | H33: Account | I33: Account
A34: COM001 | B34: Commercial Sinks Ltd | H34: Cash On Delivery | I34: On Delivery
A35: CON001 | B35: Connectix LTD | H35: Cash On Delivery | I35: On Delivery
A36: CON002 | B36: Conway Prepared Fruit & Veg | H36: Cash On Delivery | I36: On Delivery
A37: CON003 | B37: Construction Spares | H37: Cash On Delivery | I37: On Delivery
A38: COO001 | B38: Cookie Bro | H38: Account | I38: Account
A39: COS001 | B39: Cosy Campers | H39: Cash On Delivery | I39: On Delivery
A40: CRA001 | B40: Crane & Care | H40: Cash On Delivery | I40: On Delivery
A41: CUR001 | B41: Currys | H41: Cash On Delivery | I41: On Delivery
A42: CUS001 | B42: Cuspal | H42: Account | I42: Account
A43: DAN001 | B43: Dan Ryan Truck Rental | H43: Cash On Delivery | I43: On Delivery
A44: DCI001 | B44: DCI | H44: Direct Debit | I44: 30 Days
A45: DEA001 | B45: Dealz | H45: Cash On Delivery | I45: On Delivery
... A115: PET001 | B115: Petrogas Group Ltd | H115: Cash On Delivery | I115: On Delivery
A116: PIT001 | B116: Pitt Bros BBQ | F116: IE58REVO99036026483020 | G116: 17308 | H116: Account | I116: Account
A117: PJG001 | B117: P&J Gaffney | H117: Account | I117: Account
A118: POD001 | B118: POD Festivals | H118: Account | I118: Account
A119: POW001 | B119: Powertool Hub | H119: Cash On Delivery | I119: On Delivery
A120: POW002 | B120: Powertool Hub | H120: Cash On Delivery | I120: On Delivery
A121: RAD001 | B121: Radionics Ltd | H121: Cash On Delivery | I121: On Delivery
A122: RAT001 | B122: Rathcoole Commercial | H122: Account | I122: Account
A123: RAT002 | B123: Rathcoole Motor Factors | H123: Account | I123: Account
A124: RAW001 | B124: Raw Juices & Smoothies | H124: Account | I124: Account
A125: RCL001 | B125: RCL Cash & Carry | H125: Account | I125: Account
A126: REA001 | B126: Ready Chef | H126: Direct Debit | I126: 30 Days
A127: REG001 | B127: Reg Farrell Engineering Ltd | H127: Cash On Delivery | I127: On Delivery
A128: RFS001 | B128: RFS The Fastener Company | H128: Cash On Delivery | I128: On Delivery
... A181: WOO001 | B181: Woodies DIY | H181: Cash On Delivery | I181: On Delivery
A182: WIN001 | B182: Wincom Engineering Ltd. | F182: 1E25AIBK93331786103009 | H182: Account | I182: Account
A183: WOR001 | B183: Worldpay | H183: Direct Debit | I183: Weekly
A184: ZAM001 | B184: Zambrero | H184: Account | I184: Account
A185: ZTE001 | B185: Zteck | H185: Cash On Delivery | I185: On Delivery

Sheet Punchestown Festival
B1: Punchestown Festival 2024
K2: Last Year | L2: FC | M2: Cash | N2: Card | O2: Total | P2: Last Year | Q2: FC | R2: Cash | S2: Card | T2: Total | U2: Last Year | V2: FC | W2: Cash | X2: Card | Y2: Total | Z2: Last Year | AA2: FC | AB2: Cash | AC2: Card | AD2: Total | AE2: Last Year | AF2: FC | AG2: Cash | AH2: Card | AI2: Total
A3: Units | B3: Location | C3: 🚚 | D3: 🅿️ | E3: 🧼 | F3: ⚡️ | G3: 📠 | H3: 🧾 | I3: 🌡 | J3: 🧯 | K3: Tuesday | P3: Wednesday | U3: Thursday | Z3: Friday | AE3: Saturday
A4: Caffe Duomo Trailer | B4: Parade Ring | C4: FALSE | D4: TRUE | E4: TRUE | F4: TRUE | G4: TRUE | H4: FALSE | I4: FALSE | J4: TRUE | K4: 1971 | L4: 2500 | O4: =SUM(M4, N4) -> 0 | P4: 2670 | T4: =SUM(R4, S4) -> 0 | U4: 2181 | Y4: =SUM(W4:X4) -> 0 | Z4: 2671 | AD4: =SUM(AB4:AC4) -> 0 | AE4: 2985 | AI4: =SUM(AG4:AH4) -> 0
A5: Caffe Duomo Trailer | B5: Parade Ring | C5: FALSE | D5: TRUE | E5: FALSE | F5: TRUE | G5: FALSE | H5: TRUE | I5: FALSE | J5: TRUE | K5: 2595 | L5: 3000 | O5: =SUM(M5, N5) -> 0 | P5: 2285 | T5: =SUM(R5, S5) -> 0 | U5: 2345 | Y5: =SUM(W5:X5) -> 0 | Z5: 2490 | AD5: =SUM(AB5:AC5) -> 0 | AE5: 2411 | AI5: =SUM(AG5:AH5) -> 0
A6: Off Beat | B6: Parade Ring | C6: TRUE | D6: TRUE | E6: TRUE | F6: TRUE | G6: TRUE | H6: FALSE | I6: FALSE | J6: TRUE | K6: 1175 | L6: 1500 | O6: =SUM(M6, N6) -> 0 | P6: 1235 | T6: =SUM(R6, S6) -> 0 | U6: 1450 | Y6: =SUM(W6:X6) -> 0 | Z6: 2007 | AD6: =SUM(AB6:AC6) -> 0 | AE6: 2065 | AI6: =SUM(AG6:AH6) -> 0
A7: Kiosk Trailer | B7: Parade Ring | C7: FALSE | D7: TRUE | E7: TRUE | F7: TRUE | G7: FALSE | H7: FALSE | I7: FALSE | J7: TRUE | K7: 615 | L7: 800 | O7: =SUM(M7, N7) -> 0 | P7: 1125 | T7: =SUM(R7, S7) -> 0 | U7: 825 | Y7: =SUM(W7:X7) -> 0 | Z7: 1836 | AD7: =SUM(AB7:AC7) -> 0 | AE7: 2360 | AI7: =SUM(AG7:AH7) -> 0
A8: Toasted | B8: Ladbrokes | C8: FALSE | D8: TRUE | E8: TRUE | F8: TRUE | G8: TRUE | H8: FALSE | I8: FALSE | J8: TRUE | K8: 620 | L8: 1500 | O8: =SUM(M8:N8) -> 0 | P8: 1500 | T8: =SUM(R8:S8) -> 0 | U8: 1530 | Y8: =SUM(W8:X8) -> 0 | Z8: 3016 | AD8: =SUM(AB8:AC8) -> 0 | AE8: 2800 | AI8: =SUM(AG8:AH8) -> 0
A9: Camile | B9: Ladbrokes | C9: FALSE | D9: TRUE | E9: TRUE | F9: TRUE | G9: TRUE | H9: FALSE | I9: FALSE | J9: TRUE | K9: 1095 | L9: 2800 | O9: =SUM(M9:N9) -> 0 | P9: 3524 | T9: =SUM(R9:S9) -> 0 | U9: 3090 | Y9: =SUM(W9:X9) -> 0 | Z9: 7422 | AD9: =SUM(AB9:AC9) -> 0 | AE9: 5635 | AI9: =SUM(AG9:AH9) -> 0
A10: Pitt Bros | B10: Sky Bar | C10: TRUE | D10: TRUE | E10: TRUE | F10: TRUE | G10: FALSE | H10: FALSE | I10: FALSE | J10: TRUE | K10: 1055 | L10: 1200 | O10: =SUM(M10:N10) -> 0 | P10: 655 | T10: =SUM(R10:S10) -> 0 | U10: 1072 | Y10: =SUM(W10:X10) -> 0 | Z10: 1550 | AD10: =SUM(AB10:AC10) -> 0 | AE10: 1483 | AI10: =SUM(AG10:AH10) -> 0
A11: Loaded | B11: Sky Bar | C11: FALSE | D11: TRUE | E11: TRUE | F11: TRUE | G11: TRUE | H11: FALSE | I11: FALSE | J11: TRUE | K11: 2150 | L11: 800 | O11: =SUM(M11:N11) -> 0 | P11: 1520 | T11: =SUM(R11:S11) -> 0 | U11: 1080 | Y11: =SUM(W11:X11) -> 0 | Z11: 1230 | AD11: =SUM(AB11:AC11) -> 0 | AE11: 2686 | AI11: =SUM(AG11:AH11) -> 0
A12: Smash | B12: Sky Bar | C12: FALSE | D12: TRUE | E12: TRUE | F12: TRUE | G12: TRUE | H12: FALSE | I12: FALSE | J12: TRUE | K12: 1770 | L12: 1500 | O12: =SUM(M12:N12) -> 0 | P12: 1410 | T12: =SUM(R12:S12) -> 0 | U12: 1462 | Y12: =SUM(W12:X12) -> 0 | Z12: 4115 | AD12: =SUM(AB12:AC12) -> 0 | AE12: 2780 | AI12: =SUM(AG12:AH12) -> 0
A13: Ice Cream | B13: Parade Ring | C13: FALSE | D13: TRUE | E13: TRUE | F13: FALSE | G13: FALSE | H13: FALSE | I13: FALSE | J13: FALSE | K13: 1200 | L13: 2000 | O13: =SUM(M13:N13) -> 0 | P13: 2285 | T13: =SUM(R13:S13) -> 0 | U13: 2861 | Y13: =SUM(W13:X13) -> 0 | Z13: 6010 | AD13: =SUM(AB13:AC13) -> 0 | AE13: 4160 | AI13: =SUM(AG13:AH13) -> 0
A14: Ice Cream | B14: Parade Ring | C14: FALSE | D14: TRUE | E14: FALSE | F14: FALSE | G14: FALSE | H14: FALSE | I14: FALSE | J14: FALSE | K14: 0 | O14: =SUM(M14:N14) -> 0 | P14: 0 | T14: =SUM(R14:S14) -> 0 | U14: 0 | Y14: =SUM(W14:X14) -> 0 | Z14: 1050 | AD14: =SUM(AB14:AC14) -> 0 | AE14: 2020 | AI14: =SUM(AG14:AH14) -> 0
A15: Ice Cream | B15: Sky Bar | C15: FALSE | D15: TRUE | E15: FALSE | F15: TRUE | G15: FALSE | H15: FALSE | I15: FALSE | J15: FALSE | K15: 0 | O15: =SUM(M15:N15) -> 0 | P15: 0 | T15: =SUM(R15:S15) -> 0 | U15: 0 | Y15: =SUM(W15:X15) -> 0 | Z15: 740 | AD15: =SUM(AB15:AC15) -> 0 | AE15: 1000 | AI15: =SUM(AG15:AH15) -> 0
A16: Electric Van | C16: FALSE | D16: TRUE | E16: FALSE | F16: FALSE | G16: FALSE | H16: FALSE | I16: FALSE | J16: FALSE | K16: 0 | O16: =SUM(M16:N16) -> 0 | P16: 510 | T16: =SUM(R16:S16) -> 0 | U16: 0 | Y16: =SUM(W16:X16) -> 0 | Z16: 850 | AD16: =SUM(AB16:AC16) -> 0 | AE16: 1230 | AI16: =SUM(AG16:AH16) -> 0
A17: 142-D Van | C17: FALSE | D17: FALSE | E17: FALSE | F17: FALSE | G17: FALSE | H17: FALSE | I17: FALSE | J17: FALSE | K17: 0 | O17: =SUM(M17:N17) -> 0 | P17: 770 | T17: =SUM(R17:S17) -> 0 | U17: 400 | Y17: =SUM(W17:X17) -> 0 | Z17: 2020 | AD17: =SUM(AB17:AC17) -> 0 | AE17: 2505 | AI17: =SUM(AG17:AH17) -> 0
A18: Daily Total | K18: =SUM(K4:K17) -> 14246 | L18: =SUM(L4:L17) -> 17600 | M18: =SUM(M4:M17) -> 0 | N18: =SUM(N4:N17) -> 0 | O18: =SUM(O4:O17) -> 0 | P18: =SUM(P4:P17) -> 19489 | Q18: =SUM(Q4:Q17) -> 0 | R18: =SUM(R4:R17) -> 0 | ... AI18: =SUM(AI4:AI17) -> 0
Z19: Zambrero | AD19: =SUM(AB19:AC19) -> 0 | AI19: =SUM(AG19:AH19) -> 0
A20: Overall Total | Z20: Off Beat | AD20: =SUM(AB20:AC20) -> 0 | AI20: =SUM(AG20:AH20) -> 0
A21: =SUM(O18, T18, Y18, AD18, AI18) -> 0 | Z21: Van Carnival | AD21: =SUM(AB21:AC21) -> 0 | AI21: =SUM(AG21:AH21) -> 0
Z22: Van Carnival | AD22: =SUM(AB22:AC22) -> 0 | AI22: =SUM(AG22:AH22) -> 0
A23: Vs Last Year | AC23: Total | AD23: =SUM(AD18:AD22) -> 0 | AH23: Total | AI23: =SUM(AI18:AI22) -> 0
A24: =SUM(K18, P18, U18, Z18, AE18) -> 125158

Sheet EP 24
A1: Electric Picnic | I1: Stock & Orders
A2: Stall/Unit Name | B2: Location | C2: 🅿️ | D2: 🧽 | E2: ⚡️ | F2: 💻 | G2: 🧯 | H2: 👥 | I2: Sysco | J2: Camile | K2: ReadyChef | L2: BWG | M2: Pitt Bros | N2: Sandwiches | O2: Bretzel | Q2: Sleeping Arrangements
A3: Pizza Pasta | B3: Exit E | C3: FALSE | D3: FALSE | E3: FALSE | F3: FALSE | G3: FALSE | H3: FALSE | I3: FALSE | J3: FALSE | K3: FALSE | L3: FALSE | M3: FALSE | N3: FALSE | O3: FALSE | Q3: Dads | R3: 4
A4: Pitt Bro's | B4: Exit E | C4: TRUE | D4: FALSE | E4: FALSE | F4: FALSE | G4: FALSE | H4: FALSE | I4: TRUE | J4: FALSE | K4: FALSE | L4: FALSE | M4: TRUE | N4: FALSE | O4: TRUE | Q4: Fiat | R4: 6 | T4: Sophie | U4: Molly | V4: Mia | W4: Grainne | X4: Zoe | Y4: Donna
A5: Caffe Duomo | B5: Exit E | C5: TRUE | D5: FALSE | E5: FALSE | F5: FALSE | G5: FALSE | H5: FALSE | I5: TRUE | J5: FALSE | K5: FALSE | L5: FALSE | M5: TRUE | N5: FALSE | O5: TRUE | Q5: Transit | R5: 2 | T5: Triona | U5: Katie | V5: Emma
A6: Camile Thai | B6: Back of Main Arena (Spine) | C6: TRUE | D6: FALSE | E6: FALSE | F6: FALSE | G6: FALSE | H6: FALSE | I6: TRUE | J6: FALSE | K6: FALSE | L6: FALSE | M6: TRUE | N6: FALSE | O6: TRUE | Q6: Showers | R6: 4 | T6: Tom | U6: Leon | V6: Josh
A7: Zambrero | B7: Back of Main Arena (Spine) | C7: TRUE | D7: FALSE | E7: FALSE | F7: FALSE | G7: FALSE | H7: FALSE | I7: TRUE | J7: FALSE | K7: FALSE | L7: FALSE | M7: TRUE | N7: FALSE | O7: TRUE | Q7: VW | R7: 2 | T7: Lauren | U7: Ava | V7: Aoife
A8: Smash Burger 1 | B8: Back Bar 2 / Casa Bacardi | C8: TRUE | D8: FALSE | E8: FALSE | F8: FALSE | G8: FALSE | H8: FALSE | I8: FALSE | J8: FALSE | K8: FALSE | L8: FALSE | M8: TRUE | N8: FALSE | O8: TRUE | Q8: Man Van | R8: 2 | T8: Simon | U8: Cora
A9: Loaded Burger | B9: Back Of Main Arena (Spine) | C9: TRUE | D9: FALSE | E9: FALSE | F9: FALSE | G9: FALSE | H9: FALSE | I9: FALSE | J9: FALSE | K9: FALSE | L9: FALSE | M9: TRUE | N9: FALSE | O9: TRUE | Q9: Box Body | R9: 4
A10: Smash Burger 2 | B10: Back Of Main Arena (Spine) | C10: TRUE | D10: FALSE | E10: FALSE | F10: FALSE | G10: FALSE | H10: FALSE | I10: FALSE | J10: FALSE | K10: FALSE | L10: FALSE | M10: TRUE | N10: FALSE | O10: TRUE | Q10: Bedford | R10: 2 | T10: Suzie | U10: Pete
A11: Ice Cream Vans | C11: FALSE | D11: FALSE | E11: FALSE | F11: FALSE | G11: FALSE | H11: FALSE | I11: FALSE | J11: FALSE | K11: FALSE | L11: FALSE | M11: TRUE | N11: FALSE | O11: TRUE | Q11: Total Beds | R11: =SUM(R3:R10) -> 26
A12: Ice Cream Unit 1 | B12: Walkway/Main Arena | C12: FALSE | D12: FALSE | E12: FALSE | F12: FALSE | G12: FALSE | H12: FALSE | I12: FALSE | J12: FALSE | K12: FALSE | L12: FALSE | M12: TRUE | N12: FALSE | O12: TRUE
A13: Ice Cream Unit 2 | B13: Walkway/Late Night | C13: FALSE | D13: FALSE | E13: FALSE | F13: FALSE | G13: FALSE | H13: FALSE | I13: FALSE | J13: FALSE | K13: FALSE | L13: FALSE | M13: TRUE | N13: FALSE | O13: TRUE
A14: Ice Cream Unit 3 | B14: Electric Arena | C14: FALSE | D14: FALSE | E14: FALSE | F14: FALSE | G14: FALSE | H14: FALSE | I14: FALSE | J14: FALSE | K14: FALSE | L14: FALSE | M14: TRUE | N14: FALSE | O14: TRUE
A15: Ice Cream Unit 4 | B15: Rankins Wood | C15: FALSE | D15: FALSE | E15: FALSE | F15: FALSE | G15: FALSE | H15: FALSE | I15: FALSE | J15: FALSE | K15: FALSE | L15: FALSE | M15: TRUE | N15: FALSE | O15: TRUE
A16: Vintage Van | B16: MA/Tree | C16: TRUE | D16: FALSE | E16: FALSE | F16: FALSE | G16: FALSE | H16: FALSE | I16: FALSE | J16: FALSE | K16: FALSE | L16: FALSE | M16: TRUE | N16: FALSE | O16: TRUE
N19: Staff Names
A20: Unit ID | D20: Opening Hours | K20: Location
B21: # Staff | C21: Hrs | D21: # Staff | E21: Hrs | F21: # Staff | G21: Hrs | H21: # Staff | I21: Hrs | J21: # Staff | N21: Staff Id | O21: Group Chat | P21: First Name | Q21: Last Name | R21: Phone Number | S21: Email | T21: Experience | U21: Days Available
B22: Thursday | D22: Friday | F22: Saturday | H22: Sunday | J22: Monday | U22: Thursday | V22: Friday | W22: Saturday | X22: Sunday
A23: Pizza Pasta | B23: 2 | C23: 2 | D23: 5 | E23: 12 | F23: 6 | G23: 15 | H23: 6 | I23: 15 | K23: Main Arena | O23: FALSE | U23: FALSE | V23: FALSE | W23: FALSE | X23: FALSE
A24: Pitt Bro's | B24: 2 | C24: 2 | D24: 5 | E24: 12 | F24: 6 | G24: 15 | H24: 6 | I24: 15 | K24: Main Arena | O24: FALSE | P24: Thomas | Q24: obrien | R24: 852402555 | U24: FALSE | V24: FALSE | W24: FALSE | X24: FALSE
A25: Caffe Duomo | B25: 2 | C25: 2 | D25: 5 | E25: 12 | F25: 6 | G25: 15 | H25: 6 | I25: 15 | K25: Main Arena | O25: FALSE | P25: Thomas | Q25: obrien | R25: 862539642 | U25: TRUE | V25: FALSE | W25: FALSE | X25: FALSE
A26: Camile Thai | B26: 3 | C26: 4 | D26: 7 | E26: 12 | F26: 7 | G26: 15 | H26: 7 | I26: 15 | K26: Main Arena | O26: FALSE | U26: FALSE | V26: FALSE | W26: FALSE | X26: FALSE
A27: Zambrero | B27: 3 | C27: 2 | D27: 7 | E27: 12 | F27: 8 | G27: 15 | H27: 8 | I27: 15 | K27: Main Arena | O27: FALSE | P27: Flora | Q27: obrien | R27: 872416613 | U27: FALSE | V27: FALSE | W27: FALSE | X27: FALSE
A28: Smash Burger | B28: 2 | C28: 2 | D28: 6 | E28: 12 | F28: 7 | G28: 15 | H28: 7 | I28: 15 | K28: Main Arena | O28: FALSE | P28: Pat | Q28: obrien | R28: 872539642 | U28: FALSE | V28: FALSE | W28: FALSE | X28: FALSE
A29: Loaded Burger | B29: 2 | C29: 2 | D29: 6 | E29: 12 | F29: 7 | G29: 15 | H29: 7 | I29: 15 | K29: Main Arena | O29: FALSE | P29: Sophie | Q29: obrien | R29: 852154091 | T29: Coffee | U29: FALSE | V29: FALSE | W29: FALSE | X29: FALSE
A30: Smash Burger | B30: 2 | C30: 2 | D30: 6 | E30: 12 | F30: 7 | G30: 15 | H30: 7 | I30: 15 | K30: Main Arena | O30: FALSE | P30: mia | Q30: obrien | R30: 858740734 | T30: Ice cream | U30: FALSE | V30: FALSE | W30: FALSE | X30: FALSE
K31: Main Arena | O31: FALSE | P31: rachel | Q31: obrien | R31: 862539642 | T31: Coffee | U31: FALSE | V31: FALSE | W31: FALSE | X31: FALSE
A32: Ice Cream Unit 1 | B32: 1 | C32: 1 | D32: 2 | E32: 12 | F32: 2 | G32: 15 | H32: 2 | I32: 15 | K32: Main Arena | O32: FALSE | P32: Lewis | Q32: Jacob | T32: Coffee | U32: FALSE | V32: FALSE | W32: FALSE | X32: FALSE
A33: Ice Cream Unit 2 | B33: 1 | C33: 1 | D33: 2 | E33: 12 | F33: 2 | G33: 15 | H33: 2 | I33: 15 | K33: Main Arena | O33: FALSE | P33: sarah | Q33: lawlor | R33: 872227688 | T33: Coffee | U33: FALSE | V33: FALSE | W33: FALSE | X33: FALSE
A34: Ice Cream Unit 3 | B34: 1 | C34: 1 | D34: 1 | E34: 12 | F34: 2 | G34: 15 | H34: 2 | I34: 15 | K34: Main Arena | O34: FALSE | P34: martin | Q34: lawlor | R34: 872588964 | U34: FALSE | V34: FALSE | W34: FALSE | X34: FALSE
A35: Ice Cream Unit 4 | B35: 1 | C35: 1 | D35: 1 | E35: 12 | F35: 1 | G35: 15 | H35: 1 | I35: 15 | K35: Main Arena | O35: FALSE | P35: grainne | Q35: noctor | R35: 833826017 | T35: Coffee | U35: FALSE | V35: FALSE | W35: FALSE | X35: FALSE
A36: Vintage Van | B36: 1 | C36: 1 | D36: 1 | E36: 12 | F36: 2 | G36: 15 | H36: 2 | I36: 15 | K36: Main Arena | O36: FALSE | P36: jack | Q36: Savage | R36: 858321069 | T36: None | U36: FALSE | V36: FALSE | W36: FALSE | X36: FALSE
A37: Stock Boys | B37: 4 | C37: 10 | D37: 5 | E37: 12 | F37: 5 | G37: 12 | H37: 5 | I37: 12 | K37: Main Arena | O37: FALSE | P37: Rachel | Q37: Bergin | T37: None | U37: FALSE | V37: FALSE | W37: FALSE | X37: FALSE
O38: FALSE | P38: vivienne | Q38: Nolan | R38: 857481740 | T38: Coffee | U38: FALSE | V38: FALSE | W38: FALSE | X38: FALSE
O39: FALSE | P39: Angela | Q39: mckenzie | R39: 871622026 | T39: Coffee | U39: FALSE | V39: FALSE | W39: FALSE | X39: FALSE
O40: FALSE | P40: Molly | Q40: Clarke | T40: Coffee | U40: FALSE | V40: FALSE | W40: FALSE | X40: FALSE
A41: Totals Needed | B41: =SUM(B23:B40) -> 27 | C41: =SUM(C23:C40) -> 33 | D41: =SUM(D23:D40) -> 59 | E41: =SUM(E23:E40) -> 168 | F41: =SUM(F23:F40) -> 68 | G41: =SUM(G23:G40) -> 207 | H41: =SUM(H23:H40) -> 68 | I41: =SUM(I23:I40) -> 207 | J41: =SUM(J23:J40) -> 0 | O41: FALSE | P41: barry | Q41: or | R41: 851203406 | U41: FALSE | V41: FALSE | W41: FALSE | X41: FALSE
O42: FALSE | P42: Cattiona | Q42: Moore | T42: Coffee | U42: FALSE | V42: FALSE | W42: FALSE | X42: FALSE
A43: Exodus | E43: Takings | O43: FALSE | P43: Katie | Q43: Moore | T43: Coffee | U43: FALSE | V43: FALSE | W43: FALSE | X43: FALSE
A44: Vehicle | B44: Towing Vehicle | C44: Driver | E44: Stall/Unit Name | F44: Location | I44: Day | L44: Total | O44: FALSE | P44: Zoe | Q44: Oneill | T44: Food | U44: FALSE | V44: FALSE | W44: FALSE | X44: FALSE
A45: Loaded Burger | B45: Deli Truck 07 | C45: Tom | E45: Pizza Pasta | F45: Exit E | I45: Friday | J45: Saturday | K45: Sunday | O45: FALSE | P45: Sharon | Q45: Kelly | T45: Both | U45: FALSE | V45: FALSE | W45: FALSE | X45: FALSE
A46: Pitt Bro's | B46: 152 | C46: Tony | E46: Pitt Bro's | F46: Exit E | I46: 7127 | J46: 10918.5 | K46: 10497.5 | L46: =SUM(I46:K46) -> 28543 | O46: FALSE | P46: Monica | T46: Food | U46: FALSE | V46: FALSE | W46: FALSE | X46: FALSE
A47: Caffe Duomo | B47: 10WW | C47: Adam | E47: Caffe Duomo | F47: Exit E | I47: 4285 | J47: 7737.5 | K47: 8971.5 | L47: =SUM(I47:K47) -> 20994 | O47: FALSE | P47: lauren | Q47: obrien | R47: 852270819 | T47: Food | U47: FALSE | V47: FALSE | W47: FALSE | X47: FALSE
A48: Camile Thai | B48: Man Van | C48: Simon | E48: Camile Thai | F48: Back of Main Arena (Spine) | I48: 17658.5 | J48: 28256 | K48: 24044 | L48: =SUM(I48:K48) -> 69958.5 | O48: FALSE | P48: Carolann | T48: Food | U48: FALSE | V48: FALSE | W48: FALSE | X48: FALSE
A49: Zambrero | B49: Jeep | C49: Kian | E49: Zambrero | F49: Exit E | I49: 10319.5 | J49: 16766 | K49: 15961.5 | L49: =SUM(I49:K49) -> 43047 | O49: FALSE | P49: aoife | Q49: obrien | R49: 852825716 | T49: Food | U49: FALSE | V49: FALSE | W49: FALSE | X49: FALSE
A50: Smash Burger | B50: 09 Ice Cream | C50: Chris | E50: Smash Burger 1 | F50: Back Bar 2 / Casa Bacardi | I50: 6844.5 | J50: 12670.5 | K50: 11074.5 | L50: =SUM(I50:K50) -> 30589.5 | O50: FALSE | P50: Medikate | T50: Food | U50: FALSE | V50: FALSE | W50: FALSE | X50: FALSE
A51: Karl Caravan | B51: Q7 | C51: Sophie | E51: Loaded Burger | F51: Back Of Main Arena (Spine) | I51: 11906.5 | J51: 11749.5 | K51: 13173 | L51: =SUM(I51:K51) -> 36829 | O51: FALSE | P51: Thiago | T51: Food | U51: FALSE | V51: FALSE | W51: FALSE | X51: FALSE
A52: Smash Burger | B52: 07 RN | E52: Smash Burger 2 | F52: Back Of Main Arena (Spine) | I52: 11569 | J52: 17123 | K52: 21880.5 | L52: =SUM(I52:K52) -> 50572.5 | O52: FALSE | P52: Vera | T52: Food | U52: FALSE | V52: FALSE | W52: FALSE | X52: FALSE
A53: Ice Cream Unit 1 | B53: - | E53: Ice Cream Vans | L53: =SUM(I53:K53) -> 0 | O53: FALSE | P53: Shannon | Q53: Fields | T53: Food | U53: FALSE | V53: FALSE | W53: FALSE | X53: FALSE
A54: Ice Cream Unit 2 | B54: - | E54: Ice Cream Unit 1 | F54: Walkway/Main Arena | I54: 2362 | J54: 4733.5 | K54: 4396 | L54: =SUM(I54:K54) -> 11491.5 | O54: FALSE | P54: suzie | Q54: Sykes | R54: 851331264 | T54: Food | U54: FALSE | V54: FALSE | W54: FALSE | X54: FALSE
A55: Ice Cream Unit 3 | B55: - | E55: Ice Cream Unit 2 | F55: Walkway/Late Night | I55: 2519.5 | J55: 2308 | K55: 5228 | L55: =SUM(I55:K55) -> 10055.5 | O55: FALSE | P55: Peter | Q55: murphy | R55: 851331264 | T55: Food | U55: FALSE | V55: FALSE | W55: FALSE | X55: FALSE
A56: 10WW | B56: - | E56: Ice Cream Unit 3 | F56: Electric Arena | I56: 2473 | J56: 4016 | K56: 4242 | L56: =SUM(I56:K56) -> 10731 | O56: FALSE | P56: Aiden | Q56: Murphy | T56: Ice cream | U56: FALSE | V56: FALSE | W56: FALSE | X56: FALSE
A57: Vintage Van | B57: - | C57: Tom Snr | E57: Ice Cream Unit 4 | F57: Ferris Wheel | I57: 6091.5 | J57: 7576.5 | K57: 5483 | L57: =SUM(I57:K57) -> 19151 | O57: FALSE | P57: Seàn | Q57: Murphy | T57: Coffee | U57: FALSE | V57: FALSE | W57: FALSE | X57: FALSE
A58: Dads Camper | B58: - | C58: Jack | E58: Vintage Van | F58: Ma/Tree | I58: 5199 | J58: 4436 | K58: 4868 | L58: =SUM(I58:K58) -> 14503 | O58: FALSE | P58: Donna | Q58: O’Neill | R58: 852213053 | T58: Food | U58: FALSE | V58: FALSE | W58: FALSE | X58: FALSE
A59: Fiat Camper | B59: - | H59: Total | I59: =SUM(I46:I58) -> 88355 | J59: =SUM(J46:J58) -> 128291 | K59: =SUM(K46:K58) -> 129819.5 | L59: =SUM(L46:L58) -> 346465.5 | O59: FALSE | P59: Cora | Q59: Lynch | T59: Food | U59: FALSE | V59: FALSE | W59: FALSE | X59: FALSE
A60: Transit Camper | B60: - | H60: Commission | I60: =I59*22.5% -> 19879.875 | J60: =J59*22.5% -> 28865.475 | K60: =K59*22.5% -> 29209.388 | L60: =L59*22.5% -> 77954.738 | O60: FALSE | P60: Moia | Q60: McCarTon | T60: Coffee | U60: FALSE | V60: FALSE | W60: FALSE | X60: FALSE
A61: Showers | B61: Grey Sprinter | H61: Expected Payout | I61: =I59-I60 -> 68475.125 | J61: =J59-J60 -> 99425.525 | K61: =K59-K60 -> 100610.11 | L61: =L59-L60 -> 268510.76 | O61: FALSE | P61: eddie | Q61: Bergin | R61: 868092185 | T61: Food | U61: FALSE | V61: FALSE | W61: FALSE | X61: FALSE
A62: VW | B62: - | H62: Actual Payout | L62: 236629.72 | O62: FALSE | P62: karen | Q62: nolan | R62: 857118027 | T62: Coffee | U62: FALSE | V62: FALSE | W62: FALSE | X62: FALSE
A63: Man Van | B63: - | H63: WIFI/Power/Card | L63: =L61-L62 -> 31881.043 | O63: FALSE | P63: adam | Q63: halligan | R63: 871497999 | T63: Ice cream | U63: FALSE | V63: FALSE | W63: FALSE | X63: FALSE
A64: Box Body | B64: - | O64: FALSE | P64: katelynn | Q64: osullivan | R64: 851619098 | T64: Ice cream | U64: FALSE | V64: FALSE | W64: FALSE | X64: FALSE
A65: Bedford | B65: - | O65: FALSE | P65: chris | Q65: halligan | R65: 862733958 | S65: Chris.halligan@hotmail.com | T65: Food | U65: FALSE | V65: FALSE | W65: FALSE | X65: FALSE
A66: Deli Truck 07 | B66: - | O66: FALSE | P66: john | Q66: mccarton | R66: 871237228 | T66: Food | U66: FALSE | V66: FALSE | W66: FALSE | X66: FALSE
A67: Jeep | B67: - | O67: FALSE | P67: Micheala | Q67: Wade | T67: Food | U67: FALSE | V67: FALSE | W67: FALSE | X67: FALSE
A68: Dads Van | B68: - | O68: FALSE | P68: Tania | Q68: Griffin | T68: Food | U68: FALSE | V68: FALSE | W68: FALSE | X68: FALSE
A69: Sprinter Fridge | B69: - | O69: FALSE | P69: Aline | T69: Food | U69: FALSE | V69: FALSE | W69: FALSE | X69: FALSE
A70: Friday | O70: FALSE | P70: Aimee | T70: Food | U70: FALSE | V70: FALSE | W70: FALSE | X70: FALSE
O71: FALSE | P71: Aine | T71: Food | U71: FALSE | V71: FALSE | W71: FALSE | X71: FALSE
B72: 12-10pm | F72: 2.30pm-12.30pm | I72: 4pm-2am | O72: FALSE | P72: Zamb 1 | T72: Ice cream | U72: FALSE | V72: FALSE | W72: FALSE | X72: FALSE
A73: Stall/Unit Name | B73: 1 | C73: 2 | D73: 3 | E73: 4 | F73: 5 | G73: 6 | H73: 7 | I73: 8 | J73: 9 | O73: FALSE | P73: Zamb 2 | T73: Food | U73: FALSE | V73: FALSE | W73: FALSE | X73: FALSE
O74: FALSE | P74: Zamb 3 | T74: Food | U74: FALSE | V74: FALSE | W74: FALSE | X74: FALSE
A75: Pitt Bro's | B75: Aoife | C75: Mary Kate | D75: Aziz | F75: Donna | G75: Colin M | O75: FALSE | P75: Zamb 4 | T75: Food | U75: FALSE | V75: FALSE | W75: FALSE | X75: FALSE
A76: Caffe Duomo | B76: Rachel | C76: Sarah | F76: Viv | G76: Karen | H76: Rachel B | O76: FALSE | P76: Zamb 5 | T76: None | U76: FALSE | V76: FALSE | W76: FALSE | X76: FALSE
A77: Camile Thai | B77: Lauren | C77: Moya | D77: Zoe | F77: Suzie | G77: Pete | H77: Nicola | I77: Zara | J77: Cassie | O77: FALSE | P77: Zamb 6 | T77: Food | U77: FALSE | V77: FALSE | W77: FALSE | X77: FALSE
A78: Zambrero | B78: Donna | C78: Fred | D78: Newton | E78: Samuel | F78: Piter | G78: Vanessa | H78: Eder | I78: Aline | J78: Julia | O78: FALSE | P78: Zamb 7 | T78: Food | U78: FALSE | V78: FALSE | W78: FALSE | X78: FALSE
A79: Smash Burger 2 | B79: Triona | C79: Katie | G79: Charleen | H79: Cokey | I79: Bridget | O79: FALSE | P79: Zamb 8 | T79: Coffee | U79: FALSE | V79: FALSE | W79: FALSE | X79: FALSE
A80: Loaded Burger | B80: John Mc | C80: Wacker | F80: Emma T | G80: Killian B | H80: Dylan O'B | O80: FALSE | P80: Karl | Q80: Haide | T80: Ice cream | U80: FALSE | V80: FALSE | W80: FALSE | X80: FALSE
A81: Smash Burger | B81: Chris | C81: Aimee | D81: Aine | F81: Marcella | I81: Rachel M | J81: Daniele | O81: FALSE | P81: Marcela | Q81: McGrane | T81: Food | U81: FALSE | V81: FALSE | W81: FALSE | X81: FALSE
A82: Ice Cream Vans | O82: FALSE | P82: aaron james | Q82: mcentagart | R82: 830742707 | U82: FALSE | V82: FALSE | W82: FALSE | X82: FALSE
A83: Ice Cream Unit 1 | B83: Grainne | F83: Mikayla | G83: Tania | O83: FALSE | P83: emma | Q83: tallon | R83: 851182744 | U83: FALSE | V83: FALSE | W83: FALSE | X83: FALSE
A84: Ice Cream Unit 2 | F84: Katelyn | G84: Jess | O84: FALSE | P84: jennifer | Q84: oneill | R84: 872569570 | T84: Both | U84: FALSE | V84: FALSE | W84: FALSE | X84: FALSE
A85: Ice Cream Unit 3 | B85: - | F85: Mia | G85: Lewis | K85: 53 | O85: FALSE | P85: Cillian | Q85: Bonner | U85: FALSE | V85: FALSE | W85: FALSE | X85: FALSE
A86: Ice Cream Unit 4 | B86: - | F86: AJ | G86: Taylor | O86: FALSE | P86: Preston | Q86: Lam | U86: FALSE | V86: FALSE | W86: FALSE | X86: FALSE
A87: Vintage Van | B87: Molly | F87: Adam H | G87: Preston | O87: FALSE | P87: nickolla | Q87: brady | R87: 858381775 | T87: None | U87: FALSE | V87: FALSE | W87: FALSE | X87: FALSE
O88: FALSE | P88: bridget | Q88: reid | R88: 833967134 | T88: None | U88: FALSE | V88: FALSE | W88: FALSE | X88: FALSE
O89: FALSE | P89: Charleen | T89: None | U89: FALSE | V89: FALSE | W89: FALSE | X89: FALSE
A90: Saturday | O90: FALSE | P90: Courtney | T90: Food | U90: FALSE | V90: FALSE | W90: FALSE | X90: FALSE
O91: FALSE | P91: Sharon | Q91: Osullivan | T91: Food | U91: FALSE | V91: FALSE | W91: FALSE | X91: FALSE
B92: 9am-7pm | D92: 12-10pm | F92: 2.30pm-12.30pm | H92: 4pm-2am | O92: FALSE | P92: carolanne | Q92: osullivan | R92: 858738670 | T92: Food | U92: FALSE | V92: FALSE | W92: FALSE | X92: FALSE
A93: Stall/Unit Name | B93: 1 | C93: 2 | D93: 3 | E93: 4 | F93: 5 | G93: 6 | H93: 7 | I93: 8 | J93: 9 | K93: 10 | O93: FALSE | P93: sharon | Q93: phelan | R93: 896086306 | T93: Food | U93: FALSE | V93: FALSE | W93: FALSE | X93: FALSE
A94: Pizza Pasta | B94: Katie | O94: FALSE | P94: leon | Q94: gannon | R94: 858812360 | T94: Food | U94: FALSE | V94: FALSE | W94: FALSE | X94: FALSE
A95: Pitt Bro's | B95: Aoife | C95: Mary Kate | D95: Cora | E95: Chloe T | F95: Donna | G95: Jen O | H95: Nicola | I95: Aziz | J95: Chloe T | O95: FALSE | P95: ben | Q95: mcdonell | R95: 877081179 | T95: Food | U95: FALSE | V95: FALSE | W95: FALSE | X95: FALSE
A96: Caffe Duomo | B96: Rachel | C96: Sarah | F96: Viv | G96: Karen | H96: Rachel B | O96: FALSE | P96: Jess | T96: Food | U96: FALSE | V96: FALSE | W96: FALSE | X96: FALSE
A97: Camile Thai | B97: Lauren | C97: Zoe | D97: Ciara | E97: Amelie | F97: Moya | G97: Pete | H97: Suzie | I97: Zara | J97: Cassie | K97: Rhiannon | O97: FALSE | T97: Food | U97: FALSE | V97: FALSE | W97: FALSE | X97: FALSE
A98: Zambrero | B98: Donna | C98: Fred | D98: Newton | E98: Samuel | F98: Piter | G98: Vanessa | H98: Eder | I98: Aline | J98: Julia | O98: FALSE | T98: Food | U98: FALSE | V98: FALSE | W98: FALSE | X98: FALSE
A99: Smash Burger 2 | B99: Triona | C99: Katie | D99: Mikey | E99: Cormac | F99: Adam H | G99: Charleen | H99: Cokey | I99: Bridget | O99: FALSE | P99: John | U99: FALSE | V99: FALSE | W99: FALSE | X99: FALSE
A100: Loaded Burger | B100: Eddie | C100: Moya | D100: Dylan | E100: Killian | F100: Marcella | G100: John McC | H100: Sharon P | I100: Rachel M | J100: Daniele | O100: FALSE | P100: Adam | Q100: Halligan | R100: 871497999 | U100: FALSE | V100: FALSE | W100: FALSE | X100: FALSE
A101: Smash Burger | B101: Chris | C101: Aimee | D101: Aine | E101: Colin | F101: Emma T | G101: Wacker | H101: Shannon F | I101: Carolanne O | J101: Courtney | O101: FALSE | U101: FALSE | V101: FALSE | W101: FALSE | X101: FALSE
A102: Ice Cream Vans | O102: FALSE | U102: FALSE | V102: FALSE | W102: FALSE | X102: FALSE
...

Sheet HS25
A1: RDS Horseshow 24 | I1: Stock & Orders
A2: Stall/Unit Name | B2: Location | C2: 🅿️ | D2: 🧽 | E2: ⚡️ | F2: 💻 | G2: 🧯 | H2: 👥 | I2: Sysco | J2: Camile | K2: ReadyChef | L2: BWG | M2: Pitt Bros | N2: Sandwiches | O2: Bretzel
A3: Offbeat Donuts | B3: Family Zone | C3: FALSE | D3: FALSE | E3: FALSE | F3: FALSE | G3: FALSE | H3: FALSE | I3: FALSE | J3: FALSE | K3: FALSE | L3: FALSE | M3: FALSE | N3: FALSE | O3: FALSE
A4: Ice Cream Van | B4: Family Zone | C4: FALSE | D4: FALSE | E4: FALSE | F4: FALSE | G4: FALSE | H4: FALSE | I4: FALSE | J4: FALSE | K4: FALSE | L4: FALSE | M4: FALSE | N4: FALSE | O4: FALSE
A5: Churros | B5: Family Zone | C5: FALSE | D5: FALSE | E5: FALSE | F5: FALSE | G5: FALSE | H5: FALSE | I5: FALSE | J5: FALSE | K5: FALSE | L5: FALSE | M5: FALSE | N5: FALSE | O5: FALSE
A6: Caffè Duomo | B6: RDS Garden | C6: FALSE | D6: FALSE | E6: FALSE | F6: FALSE | G6: FALSE | H6: FALSE | I6: FALSE | J6: FALSE | K6: FALSE | L6: FALSE | M6: FALSE | N6: FALSE | O6: FALSE
A7: Pink Bedford | B7: RDS Garden | C7: FALSE | D7: FALSE | E7: FALSE | F7: FALSE | G7: FALSE | H7: FALSE | I7: FALSE | J7: FALSE | K7: FALSE | L7: FALSE | M7: FALSE | N7: FALSE | O7: FALSE
A8: Camile Thai | B8: RDS Garden | C8: FALSE | D8: FALSE | E8: FALSE | F8: FALSE | G8: FALSE | H8: FALSE | I8: FALSE | J8: FALSE | K8: FALSE | L8: FALSE | M8: FALSE | N8: FALSE | O8: FALSE
A9: Pitt Bros BBQ | B9: Bandlawn | C9: FALSE | D9: FALSE | E9: FALSE | F9: FALSE | G9: FALSE | H9: FALSE | I9: FALSE | J9: FALSE | K9: FALSE | L9: FALSE | M9: FALSE | N9: FALSE | O9: FALSE
A10: Caffè Duomo | B10: Ring 3 | C10: TRUE | D10: FALSE | E10: FALSE | F10: FALSE | G10: FALSE | H10: FALSE | I10: FALSE | J10: FALSE | K10: FALSE | L10: FALSE | M10: FALSE | N10: FALSE | O10: FALSE
A11: Smoothie | B11: Ring 3 | C11: TRUE | D11: FALSE | E11: FALSE | F11: FALSE | G11: FALSE | H11: FALSE | I11: FALSE | J11: FALSE | K11: FALSE | L11: FALSE | M11: FALSE | N11: FALSE | O11: FALSE
A12: Angelo's Pizza | B12: Ring 3 | C12: TRUE | D12: FALSE | E12: FALSE | F12: FALSE | G12: FALSE | H12: FALSE | I12: FALSE | J12: FALSE | K12: FALSE | L12: FALSE | M12: FALSE | N12: FALSE | O12: FALSE
A13: The Village Kiosk | B13: Ring 3 | C13: TRUE | D13: FALSE | E13: FALSE | F13: FALSE | G13: FALSE | H13: FALSE | I13: FALSE | J13: FALSE | K13: FALSE | L13: FALSE | M13: FALSE | N13: FALSE | O13: FALSE
A14: Loaded Fries | B14: Simm. Roadway (left) | C14: TRUE | D14: FALSE | E14: FALSE | F14: FALSE | G14: FALSE | H14: FALSE | I14: FALSE | J14: FALSE | K14: FALSE | L14: FALSE | M14: FALSE | N14: FALSE | O14: FALSE
... A17: Toasty | B17: Sky Bar | C17: FALSE | D17: FALSE | E17: FALSE | F17: FALSE | G17: FALSE | H17: FALSE | I17: FALSE | J17: FALSE | K17: FALSE | L17: FALSE | M17: FALSE | N17: FALSE | O17: FALSE
C18: FALSE | D18: FALSE | E18: FALSE | F18: FALSE | G18: FALSE | H18: FALSE | I18: FALSE | J18: FALSE | K18: FALSE | L18: FALSE | M18: FALSE | N18: FALSE | O18: FALSE
G19: Tuesday
A22: To Do List
A24: Patrick to get vans dropped in the evening
A26: Pitt Bros Roofsign : Tony & Kian
A28: Tony to continue ticking off cleaning list, Robo to show standard.
A30: Kian to continue power
A32: Barry continue counting tills & getting enough.
A34: Barry also on fire extinguishers. Pinned and labelled. If not enough, Johnny fire man.
A36: Robo take in deliveries with Oisin and oversee.
A39: Staff Names | B39: Wednesday | C39: Thursday | D39: Friday | E39: Saturday | F39: Sunday
A40: Samantha | B40: TRUE | C40: TRUE | D40: TRUE | E40: TRUE | F40: TRUE
A41: Lauren | B41: TRUE | C41: TRUE | D41: TRUE | E41: TRUE | F41: TRUE
A42: Dani | B42: TRUE | C42: FALSE | D42: TRUE | E42: TRUE | F42: TRUE
A43: Megan | B43: TRUE | C43: FALSE | D43: TRUE | E43: TRUE | F43: TRUE
A44: Kayleigh | B44: FALSE | C44: FALSE | D44: TRUE | E44: TRUE | F44: TRUE
A45: Ashy | B45: TRUE | C45: TRUE | D45: TRUE | E45: TRUE | F45: TRUE
A46: Nicole | B46: FALSE | C46: FALSE | D46: FALSE | E46: TRUE | F46: TRUE
A47: Jen On | B47: FALSE | C47: FALSE | D47: TRUE | E47: TRUE | F47: TRUE
A48: Estelle | B48: TRUE | C48: TRUE | D48: TRUE | E48: TRUE | F48: TRUE
A49: Emma (estelle) | B49: FALSE | C49: FALSE | D49: TRUE | E49: TRUE | F49: TRUE
A50: Ann maire | B50: TRUE | C50: TRUE | D50: TRUE | E50: TRUE | F50: TRUE
A51: Amanda | B51: TRUE | C51: TRUE | D51: TRUE | E51: TRUE | F51: TRUE
... A115: Cousin | B115: FALSE | C115: TRUE | D115: TRUE | E115: TRUE | F115: TRUE
A118: Trailers | B118: Wednesday Cash | C118: Wednesday Card | D118: Thursday Cash | E118: Thursday Card | F118: Friday Cash | G118: Friday Card | H118: Saturday Cash | I118: Saturday Card | J118: Sunday Cash | K118: Sunday Card
A119: Coffee Ring 3 | B119: 2740 | C119: 4357 | D119: 2420 | E119: 5185 | F119: 2280 | G119: 4200 | H119: 2240 | I119: 4526 | J119: 1960 | K119: 4267
A120: Coffee till 2 | D120: 880 | E120: 464 | F120: 900 | G120: 1890 | H120: 1200 | I120: 3036 | J120: 800 | K120: 1830
A121: Kiosk | B121: 1300 | C121: 1600 | D121: 2090 | E121: 1980 | F121: 1620 | G121: 2622 | H121: 2500 | I121: 4152 | J121: 1830 | K121: 2646
A122: Hot Dog | B122: 1120 | C122: 2187 | D122: 1250 | E122: 2522 | F122: 1720 | G122: 3764 | H122: 2305 | I122: 5705 | J122: 1550 | K122: 4328
A123: Smoothie | B123: 2000 | C123: 2265 | D123: 1670 | E123: 2607 | F123: 1710 | G123: 2812 | H123: 2600 | I123: 3436 | J123: 2240 | K123: 3131
A124: Thindi | B124: 325 | C124: 700 | D124: 430 | E124: 916 | F124: 1000 | G124: 1878 | H124: 450 | I124: 2123 | J124: 380 | K124: 1159
A125: Loaded | B125: 1265 | C125: 3980 | D125: 3290 | E125: 4045 | F125: 2980 | G125: 6816 | H125: 3250 | I125: 6470 | J125: 2160 | K125: 4431
A126: Zambrero | B126: 780 | C126: 1710 | D126: 1010 | E126: 2176 | F126: 1500 | G126: 2567 | H126: 1850 | I126: 6820 | J126: 1110 | K126: 4563
A127: Toasty | B127: 700 | C127: 525 | D127: 670 | E127: 1036 | F127: 400 | G127: 1804 | H127: 820 | I127: 1587 | J127: 820 | K127: 1384
A128: Pitt Bros | B128: 900 | C128: 2537 | D128: 1140 | E128: 2994 | F128: 2030 | G128: 5655 | H128: 2450 | I128: 4526 | J128: 1540 | K128: 4288
A129: Camile | B129: 1400 | C129: 4932 | D129: 2500 | E129: 4964 | F129: 2930 | G129: 8324 | H129: 3120 | I129: 13026 | J129: 1470 | K129: 7505
A130: Coffee Garden | B130: 850 | C130: 1740 | D130: 960 | E130: 2862 | F130: 1670 | G130: 3770 | H130: 1550 | I130: 3915 | J130: 970 | K130: 2816
A131: Churro | B131: 200 | C131: 605 | D131: 550 | E131: 560 | F131: 600 | G131: 1232 | H131: 835 | I131: 1778
A132: Off Beat | B132: 620 | C132: 1237 | D132: 1010 | E132: 1211 | F132: 1250 | G132: 1169 | H132: 1560 | I132: 1969 | J132: 550 | K132: 2139
B133: =SUM(Takens[[Wednesday Cash ]]) -> 14200 | C133: =SUM(C119:C132) -> 28375 | D133: =SUM(D119:D132) -> 19870 | E133: =SUM(E119:E132) -> 33522 | F133: =SUM(F119:F132) -> 22590 | G133: =SUM(G119:G132) -> 48503 | H133: =SUM(H119:H132) -> 26730 | I133: =SUM(I119:I132) -> 63069 | J133: =SUM(J119:J132) -> 17380 | K133: =SUM(K119:K132) -> 44487
I134: Total | J134: =SUM(B133:K133) -> 318726
I135: Cash Total | J135: =SUM(B133,D133,F133,H133,J133) -> 100770
A136: Caffe Duomo Ring 3 | B136: Needs: | C136: Allergen | I136: Card Total | J136: =SUM(C133,E133,G133,I133,K133) -> 217956
A137: Franks | B137: " | C137: Allergen
A138: Smoothie | C138: Allergen
C146: Camile | D146: Needs 2 tills

Sheet ATN
B1: All Together Now
B2: Unit ID | C2: Location | D2: Friday | E2: Saturday | F2: Sunday | G2: Monday | H2: Total | J2: To Do
B3: Caffe Duomo 1 | C3: Main Arena | D3: 2010 | E3: 5663.8 | F3: 6611 | H3: =SUM(D3:G3) -> 14284.8 | J3: Back of house | L3: TRUE
B4: Camile | C4: Main Arena | D4: 9571 | E4: 18789 | F4: 16405.5 | H4: =SUM(D4:G4) -> 44765.5 | J4: Toasty prep area | L4: TRUE
B5: Pitt Bros BBQ | C5: Main Arena | D5: 4319 | E5: 8931 | F5: 8668.5 | H5: =SUM(D5:G5) -> 21918.5 | J5: extra clam grills | L5: TRUE
B6: Toasted | C6: Campsite | D6: 3198 | E6: 6361 | F6: 7056 | G6: 2407 | H6: =SUM(D6:G6) -> 19022 | J6: gazebo | L6: TRUE
B7: Ice Cream Vans | H7: =SUM(D7:G7) -> 0 | J7: extra grinder | L7: TRUE | N7: Staff Names
B8: 22 Sprinter | C8: Guinness | D8: 1054 | E8: 2281 | F8: 1665.13 | H8: =SUM(D8:G8) -> 5000.13 | J8: zambrero chopper | L8: TRUE
B9: 142 | C9: Bandstand | D9: 2082 | E9: 4298 | F9: 3176.5 | H9: =SUM(D9:G9) -> 9556.5 | J9: pallets | L9: TRUE | M9: Group Chat | N9: First Name | O9: Last Name | P9: Phone Number | Q9: Experience | R9: Days Available
H10: =SUM(D10:G10) -> 0 | J10: coffee order **** | L10: FALSE | R10: Thursday | S10: Friday | T10: Saturday | U10: Sunday
C11: Total | D11: =SUM(D3:D9) -> 22234 | E11: =SUM(E3:E9) -> 46323.8 | F11: =SUM(F3:F9) -> 43582.63 | G11: =SUM(G3:G9) -> 2407 | H11: =SUM(D11:G11) -> 114547.43 | J11: Milk | L11: TRUE | N11: Samantha
G12: Commission | H12: =H11*0.2 -> 22909.486 | J12: Ice cream stock | L12: TRUE | N12: Lauren
G13: Gross | H13: =H11-H12 -> 91637.944 | L13: FALSE | N13: Triona
N14: Ava
B15: Unit ID | E15: Opening Hours | L15: Location | N15: Janet
C16: # Staff | D16: Hrs | E16: # Staff | F16: Hrs | G16: # Staff | H16: Hrs | I16: # Staff | J16: Hrs | K16: # Staff | N16: Shannon
C17: Thursday | E17: Friday | G17: Saturday | I17: Sunday | K17: Monday | N17: Lisa
B18: Caffe Duomo 1 | C18: 1 | D18: 2 | E18: 3 | F18: 8 | G18: 4 | H18: 8 | I18: 4 | J18: 8 | L18: Main Arena | N18: Karl
B19: Camile | C19: 2 | D19: 4 | E19: 8 | F19: 8 | G19: 8 | H19: 8 | I19: 8 | J19: 8 | L19: Main Arena | N19: Donna
B20: Pitt Bros BBQ | C20: 1 | D20: 2 | E20: 5 | F20: 8 | G20: 5 | H20: 8 | I20: 5 | J20: 8 | L20: Main Arena | N20: Zoe
B21: Toasted | C21: 2 | D21: 6 | E21: 4 | F21: 8 | G21: 5 | H21: 8 | I21: 5 | J21: 8 | L21: Campsite | N21: Emma t
B22: 22 Sprinter | E22: 2 | F22: 8 | G22: 2 | H22: 8 | I22: 2 | J22: 8 | L22: Main Arena | N22: John mc
B23: 152 | E23: 2 | F23: 8 | G23: 2 | H23: 8 | I23: 2 | J23: 8 | L23: Main Arena | N23: Suzie
N24: Peter
B25: Spares | N25: Sean
B26: Stock Boys | N26: Aiden
N27: Mary Kate
N28: Thiago
B29: Totals Needed | C29: =SUM(C18:C28) -> 6 | D29: =SUM(D18:D28) -> 14 | E29: =SUM(E18:E28) -> 24 | F29: =SUM(F18:F28) -> 48 | G29: =SUM(G18:G28) -> 26 | H29: =SUM(H18:H28) -> 48 | I29: =SUM(I18:I28) -> 26 | J29: =SUM(J18:J28) -> 48 | ... L29: =SUM(L18:L28) -> 0 | N29: Vera
N30: Cora
B31: Total Shifts | C31: =SUM(C18, C19, C20, C21, E18, E19, E20, E21, E23, E22, G18, G19, G20, G21, G22, G23, I18, I19, I20, I21, I22, I23) -> 82 | N31: Kyle
N32: Katie
N33: Paddy
N34: Oisin
N35: Thomas
B36: Forecast | D36: Higher | F36: Sleeping Arrangements | N36: Simon
B37: Camile | C37: €40k | D37: €45k | F37: Dads | G37: 4 | N37: Barry
B38: Caffe Duomo | C38: €14k | D38: €16k | F38: Fiat | G38: 6 | N38: Sam
B39: Pitt Bros | C39: €30k | D39: €35k | F39: Transit | G39: 2 | N39: Gra
B40: Toasted | C40: €18k | D40: €25k | F40: Showers | G40: 4 | N40: Jucilane
B41: Ice cream | C41: €8k | D41: €9k | F41: VW | G41: 2 | N41: Alex
B42: Ice cream | C42: €8k | D42: €9k | F42: Man Van | G42: 2
F43: Box Body | G43: 4 | H43: =SUM(G38, G37, G39, G41, G40, G42, G43) -> 24
B45: Orders
B46: Unit | C46: Sysco | D46: Camile | E46: Readychef | F46: CP | G46: Ice Cream
B47: Camile | C47: TRUE | D47: TRUE | E47: TRUE | F47: FALSE | G47: FALSE | H47: FALSE
B48: Caffe Duomo | C48: TRUE | D48: FALSE | E48: FALSE | F48: FALSE | G48: FALSE | H48: FALSE
B49: Pitt Bros | C49: TRUE | D49: FALSE | E49: TRUE | F49: FALSE | G49: FALSE | H49: FALSE
B50: Toasted | C50: TRUE | D50: FALSE | E50: FALSE | F50: FALSE | G50: FALSE | H50: FALSE
B51: Ice cream | C51: TRUE | D51: FALSE | E51: FALSE | F51: FALSE | G51: FALSE | H51: FALSE
B52: Ice cream | C52: TRUE | D52: FALSE | E52: FALSE | F52: FALSE | G52: FALSE | H52: FALSE
B57: Trailer | C57: Bands | D57: Delivery pass | E57: Static pass
B58: Coffee | C58: 6 | D58: 1 | E58: 1
B59: Camile | C59: 10 | D59: 1 | E59: 1
B60: Ice cream | C60: 3 | D60: 1 | E60: 1
B61: Ice cream | C61: 3 | E61: 1
B62: Toasted | C62: 8 | D62: 1 | E62: 1
B63: Pitt Bros | C63: 8
A66: Camile
A67: 11 | B67: 1 | C67: 2 | D67: 3 | E67: 4 | F67: 5 | G67: 6 | H67: 7 | I67: 8
A68: 12pm

Sheet ATN 2025
B1: All Together Now
B2: Unit ID | C2: Location | D2: Friday | E2: Saturday | F2: Sunday | G2: Monday | H2: Total | J2: To Do
B3: Caffe Duomo 1 | J3: Back of house | L3: FALSE
B4: Camile | J4: Toasty prep area | L4: FALSE
B5: Pitt Bros BBQ | J5: extra clam grills | L5: FALSE
B6: Toasted | J6: gazebo | L6: FALSE
B7: Zambrero | L7: FALSE
B8: Ice Cream Vans | J8: extra grinder | L8: FALSE | N8: Staff Names
B9: 22 Sprinter | J9: zambrero chopper | L9: FALSE
B10: 142 | J10: pallets | L10: FALSE | M10: Group Chat | N10: First Name | O10: Last Name | P10: Phone Number | Q10: Pass Sent | R10: Days Available
J11: coffee order **** | L11: FALSE | Q11: FALSE | R11: Thursday | S11: Friday | T11: Saturday | U11: Sunday
C12: Total | J12: Milk | L12: FALSE | N12: Samantha | O12: OBrien | Q12: TRUE | R12: FALSE | S12: TRUE | T12: TRUE | U12: TRUE
G13: Commission | H13: =H12*0.2 -> 0 | J13: Ice cream stock | L13: FALSE | N13: Lauren | O13: OBrien | Q13: TRUE | R13: TRUE | S13: TRUE | T13: TRUE | U13: TRUE
G14: Gross | H14: =H12-H13 -> 0 | L14: FALSE | N14: Dani | O14: OBrien | Q14: TRUE | R14: FALSE | S14: TRUE | T14: TRUE | U14: TRUE
N15: Ava | O15: DeAlmeida | Q15: TRUE | R15: FALSE | S15: TRUE | T15: TRUE | U15: TRUE
B16: Unit ID | E16: Opening Hours | L16: Location | N16: Janet | O16: Orr | Q16: TRUE | R16: FALSE | S16: TRUE | T16: TRUE | U16: TRUE
C17: # Staff | D17: Hrs | E17: # Staff | F17: Hrs | G17: # Staff | H17: Hrs | I17: # Staff | J17: Hrs | K17: # Staff | N17: Louise | O17: Malone | Q17: TRUE | R17: FALSE | S17: FALSE | T17: TRUE | U17: TRUE
C18: Thursday | E18: Friday | G18: Saturday | I18: Sunday | K18: Monday | N18: Lisa | O18: Gaffney | Q18: TRUE | R18: FALSE | S18: TRUE | T18: TRUE | U18: TRUE
B19: Caffe Duomo 1 | C19: 1 | D19: 2 | E19: 3 | F19: 8 | G19: 4 | H19: 12 | I19: 4 | J19: 12 | N19: Karl | O19: Brennan | Q19: TRUE | R19: TRUE | S19: TRUE | T19: TRUE | U19: TRUE
B20: Camile | C20: 5 | D20: 4 | E20: 8 | F20: 8 | G20: 9 | H20: 12 | I20: 9 | J20: 12 | N20: Stacey | O20: Smith | Q20: TRUE | R20: TRUE | S20: TRUE | T20: TRUE | U20: TRUE
B21: Pitt Bros BBQ | C21: 2 | D21: 4 | E21: 5 | F21: 8 | G21: 6 | H21: 12 | I21: 6 | J21: 12 | N21: Suzie | O21: Sykes | Q21: TRUE | R21: FALSE | S21: TRUE | T21: TRUE | U21: TRUE
B22: Toasted | C22: 3 | D22: 6 | E22: 4 | F22: 17 | G22: 5 | H22: 19 | I22: 5 | J22: 19 | N22: Peter | O22: Murphy | Q22: TRUE | R22: FALSE | S22: TRUE | T22: TRUE | U22: TRUE
B23: 22 Sprinter | C23: - | D23: - | E23: 2 | F23: 12 | G23: 2 | H23: 12 | I23: 2 | J23: 12 | N23: Sean | O23: Murphy | Q23: TRUE | R23: FALSE | S23: TRUE | T23: TRUE | U23: TRUE
B24: 152 | C24: - | D24: - | E24: 2 | F24: 12 | G24: 2 | H24: 12 | I24: 2 | J24: 12 | N24: Aidan | O24: Murphy | Q24: TRUE | R24: FALSE | S24: TRUE | T24: TRUE | U24: TRUE
B25: Zambrero | C25: 3 | D25: 4 | E25: 9 | F25: 8 | G25: 9 | H25: 12 | I25: 9 | J25: 12 | N25: Thomas | O25: OBrien | Q25: TRUE | R25: FALSE | S25: FALSE | T25: FALSE | U25: FALSE
B26: Total | C26: =SUM(C19:C25) -> 14 | D26: =SUM(D19:D25) -> 20 | E26: =SUM(E19:E25) -> 33 | F26: =SUM(F19:F25) -> 73 | G26: =SUM(G19:G25) -> 37 | H26: =SUM(H19:H25) -> 91 | I26: =SUM(I19:I25) -> 37 | J26: =SUM(J19:J25) -> 91 | N26: Simon | O26: OConnor | Q26: TRUE | R26: FALSE | S26: FALSE | T26: FALSE | U26: FALSE
N27: Laura | O27: Murphy | Q27: TRUE | R27: FALSE | S27: TRUE | T27: TRUE | U27: TRUE
B28: Spares | N28: Catriona | O28: Moore | Q28: TRUE | S28: TRUE | T28: TRUE | U28: TRUE
B29: Stock Boys | C29: 2 | E29: 2 | G29: 2 | I29: 2 | N29: Gra | Q29: FALSE | S29: TRUE | T29: TRUE | U29: TRUE
N30: Mary | O30: Kate | Q30: TRUE | S30: TRUE | T30: TRUE | U30: TRUE
N31: Renata | O31: Gomez | Q31: TRUE | S31: TRUE | T31: TRUE | U31: TRUE
B32: Totals Needed | C32: =SUM(C19:C31) -> 30 | D32: =SUM(D19:D31) -> 40 | E32: =SUM(E19:E31) -> 68 | F32: =SUM(F19:F31) -> 146 | G32: =SUM(G19:G31) -> 76 | H32: =SUM(H19:H31) -> 182 | I32: =SUM(I19:I31) -> 76 | J32: =SUM(J19:J31) -> 182 | ... L32: =SUM(L19:L31) -> 0 | N32: Ilze | O32: Bondarenko | Q32: TRUE | S32: TRUE | T32: TRUE | U32: TRUE
N33: Fabio | O33: Marciel | Q33: TRUE | S33: TRUE | T33: TRUE | U33: TRUE
B34: Total Shifts | C34: =SUM(C19, C20, C21, C22, E19, E20, E21, E22, E24, E23, G19, G20, G21, G22, G23, G24, I19, I20, I21, I22, I23, I24) -> 91 | N34: Ryan | O34: Silva | Q34: TRUE | S34: TRUE | T34: TRUE | U34: TRUE
N35: Chloe | O35: Donovan | Q35: TRUE | S35: TRUE | T35: TRUE | U35: TRUE
N36: Maira | O36: Flores | Q36: TRUE | S36: TRUE | T36: TRUE | U36: TRUE
N37: Facundo | O37: Mendez | Q37: TRUE | S37: TRUE | T37: TRUE | U37: TRUE
N38: Karina | O38: Vieria | Q38: TRUE | S38: TRUE | T38: TRUE | U38: TRUE
B39: Forecast | D39: Higher | F39: Sleeping Arrangements | N39: Peadar | O39: Odalaigh | Q39: TRUE | S39: TRUE | T39: TRUE | U39: TRUE
B40: Actual 2024 | C40: 2025 | D40: Actual 2025 | N40: Sam | O40: Sykes | Q40: TRUE | S40: TRUE | T40: TRUE | U40: TRUE
A41: Camile | B41: 44765 | C41: 60000 | D41: 63166 | F41: Dads | G41: 4 | N41: Luciana | O41: Campos | Q41: TRUE | S41: TRUE | T41: TRUE | U41: TRUE
A42: Caffe Duomo | B42: 14284 | C42: 20000 | D42: 12482 | F42: Fiat | G42: 6 | N42: Hsu | O42: Fu yun | Q42: TRUE | S42: TRUE | T42: TRUE | U42: TRUE
A43: Pitt Bros | B43: 21918 | C43: 30000 | D43: 27334 | F43: Transit | G43: 2 | N43: Colm | O43: Dunne | Q43: FALSE | S43: FALSE | T43: FALSE | U43: FALSE
A44: Toasted | B44: 19022 | C44: 30000 | D44: 21988 | F44: Showers | G44: 4 | N44: Samantha | O44: OBrien | Q44: FALSE | S44: FALSE | T44: FALSE | U44: FALSE
A45: Ice cream | B45: 5000 | C45: 8000 | F45: VW | G45: 2 | N45: Jade | O45: Malone | Q45: TRUE | S45: FALSE | T45: TRUE | U45: TRUE
A46: Ice cream | B46: 9556 | C46: 12000 | F46: Man Van | G46: 2 | N46: Barry | O46: Or | Q46: TRUE | S46: TRUE | T46: TRUE | U46: TRUE
A47: Zambrero | B47: - | C47: 50000 | D47: 32726.5 | F47: Box Body | G47: 4 | H47: =SUM(G42, G41, G43, G45, G44, G46, G47) -> 24 | N47: Valquira | O47: Coutinho | Q47: TRUE | S47: TRUE | T47: TRUE | U47: TRUE
A48: Total | B48: =SUM(B41:B47) -> 114545 | C48: =SUM(C41:C47) -> 210000 | D48: =SUM(D41:D47) -> 157696.5 | N48: Ciaran | O48: Dinan | Q48: TRUE | S48: TRUE | T48: TRUE | U48: TRUE
N49: Kayleigh | P49: Megan | Q49: TRUE | S49: TRUE | T49: TRUE | U49: TRUE
B50: Orders | N50: Hamza | P50: Dave | Q50: TRUE | S50: TRUE | T50: TRUE | U50: TRUE
B51: Unit | C51: Sysco | D51: Camile | E51: Readychef | F51: BWG | G51: Ice Cream | T51: FALSE | U51: TRUE
B52: Camile | C52: FALSE | D52: TRUE | E52: FALSE | F52: FALSE | G52: FALSE | H52: FALSE | M52: Accreditation Opening Times
B53: Caffe Duomo | C53: FALSE | D53: TRUE | E53: FALSE | F53: FALSE | G53: FALSE | H53: FALSE | L53: Day | M53: Open | N53: Close
B54: Pitt Bros | C54: FALSE | D54: TRUE | E54: FALSE | F54: FALSE | G54: FALSE | H54: FALSE | L54: Wednesday | M54: 0.3125 | N54: 0.91666667
B55: Toasted | C55: FALSE | D55: TRUE | E55: FALSE | F55: FALSE | G55: FALSE | H55: FALSE | L55: Thursday | M55: 0.3125 | N55: 0.91666667
B56: Ice cream | C56: FALSE | D56: TRUE | E56: FALSE | F56: FALSE | G56: FALSE | H56: FALSE | L56: Friday | M56: 0.3125 | N56: 0.91666667
B57: Ice cream | C57: FALSE | D57: TRUE | E57: FALSE | F57: FALSE | G57: FALSE | H57: FALSE | L57: Saturday | M57: 0.3125 | N57: 0.91666667
B58: Zambrero | C58: FALSE | D58: TRUE | E58: FALSE | F58: FALSE | G58: FALSE | H58: FALSE | L58: Sunday | M58: 0.41666667 | N58: 0.75
B62: Trailer | C62: Bands | D62: Delivery pass | E62: Static pass | K62: Staff Names
B63: Coffee | C63: 4 | D63: 1 | E63: 1
B64: Camile | C64: 8 | D64: 1 | E64: 1 | K64: First Name | L64: Last Name | M64: Phone Number | N64: Paid | O64: Days Available
B65: Ice cream | C65: 3 | N65: FALSE | O65: Thursday | P65: Friday | Q65: Saturday | R65: Sunday
B66: Ice cream | C66: 3 | K66: Samantha | L66: OBrien | N66: FALSE | O66: FALSE | P66: TRUE | Q66: TRUE | R66: TRUE
B67: Toasted | C67: 5 | K67: Lauren | L67: OBrien | N67: FALSE | O67: TRUE | P67: TRUE | Q67: TRUE | R67: TRUE
B68: Pitt Bros | C68: 6 | K68: Dani | L68: OBrien | N68: FALSE | O68: FALSE | P68: TRUE | Q68: TRUE | R68: TRUE
B69: Zambrero | C69: 8 | K69: Ava | L69: DeAlmeida | N69: FALSE | O69: FALSE | P69: TRUE | Q69: TRUE | R69: TRUE
C70: =SUM(C63:C69) -> 37 | K70: Janet | L70: Orr | N70: FALSE | O70: FALSE | P70: TRUE | Q70: TRUE | R70: TRUE
A71: Camile | K71: Louise | L71: Malone | N71: FALSE | O71: FALSE | P71: FALSE | Q71: TRUE | R71: TRUE
A72: 11 | B72: 1 | C72: 2 | D72: 3 | E72: 4 | F72: 5 | G72: 6 | H72: 7 | I72: 8 | K72: Lisa | L72: Gaffney | N72: FALSE | O72: FALSE | P72: TRUE | Q72: TRUE | R72: TRUE
A73: 12pm | K73: Karl | L73: Brennan | N73: FALSE | O73: TRUE | P73: TRUE | Q73: TRUE | R73: TRUE
K74: Stacey | L74: Smith | N74: FALSE | O74: TRUE | P74: TRUE | Q74: TRUE | R74: TRUE
K75: Suzie | L75: Sykes | N75: FALSE | O75: FALSE | P75: TRUE | Q75: TRUE | R75: TRUE
K76: Peter | L76: Murphy | N76: FALSE | O76: FALSE | P76: TRUE | Q76: TRUE | R76: TRUE
K77: Sean | L77: Murphy | N77: FALSE | O77: FALSE | P77: TRUE | Q77: TRUE | R77: TRUE
A78: 2024 | K78: Aidan | L78: Murphy | N78: FALSE | O78: FALSE | P78: TRUE | Q78: TRUE | R78: TRUE
A79: Unit ID | B79: Location | C79: Friday | D79: Saturday | E79: Sunday | F79: Monday | G79: Total | K79: Thomas | L79: OBrien | N79: FALSE | O79: FALSE | P79: FALSE | Q79: FALSE | R79: FALSE
A80: Caffe Duomo 1 | B80: Main Arena | C80: 2010 | D80: 5663.8 | E80: 6611 | G80: =SUM(C80:F80) -> 14284.8 | K80: Simon | L80: OConnor | N80: FALSE | O80: FALSE | P80: FALSE | Q80: FALSE | R80: FALSE
A81: Camile | B81: Main Arena | C81: 9571 | D81: 18789 | E81: 16405.5 | G81: =SUM(C81:F81) -> 44765.5 | K81: Laura | L81: Murphy | N81: FALSE | O81: FALSE | P81: TRUE | Q81: TRUE | R81: TRUE
A82: Pitt Bros BBQ | B82: Main Arena | C82: 4319 | D82: 8931 | E82: 8668.5 | G82: =SUM(C82:F82) -> 21918.5 | K82: Catriona | L82: Moore | N82: FALSE | P82: TRUE | Q82: TRUE | R82: TRUE
A83: Toasted | B83: Campsite | C83: 3198 | D83: 6361 | E83: 7056 | F83: 2407 | G83: =SUM(C83:F83) -> 19022 | K83: Gra | N83: FALSE | P83: TRUE | Q83: TRUE | R83: TRUE
A84: Ice Cream Vans | G84: =SUM(C84:F84) -> 0 | K84: Mary | L84: Kate | N84: FALSE | P84: TRUE | Q84: TRUE | R84: TRUE
A85: 22 Sprinter | B85: Guinness | C85: 1054 | D85: 2281 | E85: 1665.13 | G85: =SUM(C85:F85) -> 5000.13 | K85: Renata | L85: Gomez | N85: FALSE | P85: TRUE | Q85: TRUE | R85: TRUE
A86: 142 | B86: Bandstand | C86: 2082 | D86: 4298 | E86: 3176.5 | G86: =SUM(C86:F86) -> 9556.5 | K86: Ilze | L86: Bondarenko | N86: FALSE | P86: TRUE | Q86: TRUE | R86: TRUE
G87: =SUM(C87:F87) -> 0 | K87: Fabio | L87: Marciel | N87: FALSE | P87: TRUE | Q87: TRUE | R87: TRUE
B88: Total | C88: =SUM(C80:C86) -> 22234 | D88: =SUM(D80:D86) -> 46323.8 | E88: =SUM(E80:E86) -> 43582.63 | F88: =SUM(F80:F86) -> 2407 | G88: =SUM(C88:F88) -> 114547.43 | K88: Ryan | L88: Silva | N88: FALSE | P88: TRUE | Q88: TRUE | R88: TRUE
F89: Commission | G89: =G88*0.2 -> 22909.486 | K89: Chloe | L89: Donovan | N89: FALSE | P89: TRUE | Q89: TRUE | R89: TRUE
F90: Gross | G90: =G88-G89 -> 91637.944 | K90: Maira | L90: Flores | N90: FALSE | P90: TRUE | Q90: TRUE | R90: TRUE
K91: Facundo | L91: Mendez | N91: FALSE | P91: TRUE | Q91: TRUE | R91: TRUE
K92: Karina | L92: Vieria | N92: FALSE | P92: TRUE | Q92: TRUE | R92: TRUE
A93: Shifts | K93: Peadar | L93: Odalaigh | N93: FALSE | P93: TRUE | Q93: TRUE | R93: TRUE
A94: Trailers | B94: Times | D94: Names | E94: Names | F94: Names | G94: Names | K94: Sam | L94: Sykes | N94: FALSE | P94: TRUE | Q94: TRUE | R94: TRUE
A95: Caffe Duomo | B95: 45972 | D95: laura | E95: suzie | K95: Luciana | L95: Campos | N95: FALSE | P95: TRUE | Q95: TRUE | R95: TRUE
B96: 45701 | D96: megan | E96: renata | K96: Hsu | L96: Fu yun | N96: FALSE | P96: TRUE | Q96: TRUE | R96: TRUE
A97: Camile | B97: 45972 | D97: sam | E97: pete | F97: dave | K97: Colm | L97: Dunne | N97: FALSE | P97: FALSE | Q97: FALSE | R97: FALSE
B98: 45701 | D98: triona | E98: stacey | F98: valquira | G98: Ciaran & Jade | K98: Samantha | L98: OBrien | N98: FALSE | P98: FALSE | Q98: FALSE | R98: FALSE
A99: Pitt Bros | B99: 45972 | D99: lauren | E99: ava | F99: Sean | K99: Jade | L99: Malone | N99: FALSE | P99: FALSE | Q99: TRUE | R99: TRUE
B100: 45701 | D100: dani | E100: Louise | F100: medikate | K100: Barry | L100: Or | N100: FALSE | P100: TRUE | Q100: TRUE | R100: TRUE
A101: Zambrero | K101: Valquira | L101: Coutinho | N101: FALSE | P101: TRUE | Q101: TRUE | R101: TRUE
A103: Van | B103: karl | C103: aidan
A104: Van | B104: barry | C104: sean
...

Sheet Fire Extinguishers
E5: Single Phase
E6: Three Phase
B11: Unit ID | C11: Fire Extinguishers | H11: Unit ID | I11: Fire Extinguishers
C12: CO2 | D12: Powder | E12: Wet Chemical | F12: Fire Blanket | G12: Ansul | I12: CO2 | J12: Powder | K12: Wet Chemical | L12: Fire Blanket
B13: Burger/Chipper Units | H13: Confectionery
B14: O'Briens Chipper 1 | F14: 6/25 | H14: Donuts & Coffee 1 | I14: 6/20
B15: O'Briens Chipper 2 small | C15: 6/25 | D15: 6/25 | E15: 6/25 | H15: Off Beat Donuts | I15: 7/26 | L15: 4/25
B16: Loaded burger 2 | C16: 5/25 | D16: 6/25 | E16: 6/25 | F16: 6/25 | H16: Chocolate Fountain
B17: FGF Burger Co. 1 electric | C17: 4/26 | D17: 4/26 | E17: 1/27+ 8/26 | F17: No date | H17: Pick'n'Mix
B18: FGF Burger Co. 2 gas | C18: 8/26 | D18: 4/26 | E18: 1/27 | F18: 6/18 | H18: The Village Kiosk 1 van | I18: 8/25
B19: Loaded Burger | C19: 8/26, 7/26, | D19: 5/25 | E19: 1/27, | F19: 4/26 | H19: The Village Kiosk 2
B20: Misc. Food Units | H20: Sprinkles Churros | I20: 4/26 | J20: 4/26 | K20: 4/26 | L20: 7/26
B21: Angelo's Pizza | C21: 4/26 | D21: 4/26 | H21: Sprinkles Desserts
B22: Angelo's Pizza & Pasta | F22: 4/25 | H22: Ice Cream Vans
H23: Lauren new van | I23: 6/24
B24: Pizza Horsebox | H24: 152-D
B25: Thindi | C25: 6/25 | D25: 6/25 | E25: 6/25 | F25: 4/25 | H25: 142-D | I25: 6/24
B26: Toasted | C26: 1/27 | D26: 4/26 | F26: 6/25 | H26: 09-D
B27: Rollover Hot Dog 1 | F27: 4/26 | H27: 07-D
B28: Zambrero | C28: 3/25 | D28: 3/25 | F28: 5/24 | H28: 07-RN
B29: Pitt Bros BBQ | C29: 7/26 | D29: 8/26 | E29: 8/26 | H29: 05-D
B30: Camile Thai 2.0 | C30: 8/26 | D30: 7/26 | E30: 4/26 | H30: 05-WH
B31: Caffe Duomo Baguettes | H31: 04-D
B32: Camile Thai | C32: 1/27, | D32: 7/26 | E32: 8/25,1/27 | H32: 03-D
B33: Coffee/Beverages | H33: 02-WW
B34: Caffe Duomo 1 | C34: 12/26 | H34: 02-C
B35: Caffe Duomo 2 b&c | C35: 6/25 | F35: 6/25 | H35: 01-D
B36: Caffe Duomo 3 | H36: BMC
B37: Caffe Duomo Van | C37: 5/15 | H37: LD
B38: Caffe Duomo/Torelli | C38: 3/25 | F38: 4/25 | H38: Pink Bedford
B39: Caffe duomo/new | H39: Yellow Transit
B40: Freshly Ground Coffee 1 | C40: 7/26 | D40: 8/26 | H40: 88-WX
B41: Freshly ground coffee 2
B42: Smoothies & Shakes 1 | C42: 8/26+ 4/26 | E42: 8/26 | H42: Carts & Trikes
B43: Nobo/Citroen | H43: Camile Cart
B44: Spares | C44: 4/26+7/26 | D44: 4/26 | H44: Zambrero Cart
H45: Vespa Cart #1
H46: Vespa Cart #2
H47: Sweet Cart

Sheet Calendar
A1: 2024 | B1: January | AG1: February | BJ1: March | CO1: April | DS1: May | EX1: June | GB1: July | HG1: August | IL1: September | JP1: October | KU1: November | LY1: December | ND1: January
B2: 45292 | C2: 45293 | D2: 45294 | E2: 45295 | F2: 45296 | G2: 45297 | H2: 45298 | I2: 45299 | J2: 45300 | K2: 45301 | L2: 45302 | M2: 45303 | N2: 45304 | O2: 45305 | P2: 45306 | Q2: 45307 | R2: 45308 | S2: 45309 | T2: 45310 | U2: 45311 | V2: 45312 | W2: 45313 | X2: 45314 | Y2: 45315 | Z2: 45316 | AA2: 45317 | AB2: 45318 | AC2: 45319 | AD2: 45320 | AE2: 45321 | AF2: 45322 | AG2: 45323 | AH2: 45324 | AI2: 45325 | AJ2: 45326 | AK2: 45327 | AL2: 45328 | AM2: 45329 | AN2: 45330 | AO2: 45331 | AP2: 45332 | AQ2: 45333 | AR2: 45334 | AS2: 45335 | AT2: 45336 | AU2: 45337 | AV2: 45338 | AW2: 45339 | AX2: 45340 | AY2: 45341 | AZ2: 45342 | BA2: 45343 | BB2: 45344 | BC2: 45345 | BD2: 45346 | BE2: 45347 | BF2: 45348 | BG2: 45349 | BH2: 45350 | BI2: 45351 | BJ2: 45352 | BK2: 45353 | BL2: 45354 | BM2: 45355 | BN2: 45356 | BO2: 45357 | BP2: 45358 | BQ2: 45359 | BR2: 45360 | BS2: 45361 | BT2: 45362 | BU2: 45363 | BV2: 45364 | BW2: 45365 | BX2: 45366 | BY2: 45367 | BZ2: 45368 | CA2: 45369 | CB2: 45370 | CC2: 45371 | CD2: 45372 | CE2: 45373 | CF2: 45374 | CG2: 45375 | CH2: 45376 | CI2: 45377 | CJ2: 45378 | CK2: 45379 | CL2: 45380 | CM2: 45381 | CN2: 45382 | CO2: 45383 | CP2: 45384 | CQ2: 45385 | CR2: 45386 | CS2: 45387 | CT2: 45388 | CU2: 45389 | CV2: 45390 | CW2: 45391 | CX2: 45392 | CY2: 45393 | CZ2: 45394 | DA2: 45395 | DB2: 45396 | DC2: 45397 | DD2: 45398 | DE2: 45399 | DF2: 45400 | DG2: 45401 | DH2: 45402 | DI2: 45403 | DJ2: 45404 | DK2: 45405 | DL2: 45406 | DM2: 45407 | DN2: 45408 | DO2: 45409 | DP2: 45410 | DQ2: 45411 | DR2: 45412 | DS2: 45413 | DT2: 45414 | DU2: 45415 | DV2: 45416 | DW2: 45417 | DX2: 45418 | DY2: 45419 | DZ2: 45420 | EA2: 45421 | EB2: 45422 | EC2: 45423 | ED2: 45424 | EE2: 45425 | EF2: 45426 | EG2: 45427 | EH2: 45428 | EI2: 45429 | EJ2: 45430 | EK2: 45431 | EL2: 45432 | EM2: 45433 | EN2: 45434 | EO2: 45435 | EP2: 45436 | EQ2: 45437 | ER2: 45438 | ES2: 45439 | ET2: 45440 | EU2: 45441 | EV2: 45442 | EW2: 45443 | EX2: 45444 | EY2: 45445 | EZ2: 45446 | FA2: 45447 | FB2: 45448 | FC2: 45449 | FD2: 45450 | FE2: 45451 | FF2: 45452 | FG2: 45453 | FH2: 45454 | FI2: 45455 | FJ2: 45456 | FK2: 45457 | FL2: 45458 | FM2: 45459 | FN2: 45460 | FO2: 45461 | FP2: 45462 | FQ2: 45463 | FR2: 45464 | FS2: 45465 | FT2: 45466 | FU2: 45467 | FV2: 45468 | FW2: 45469 | FX2: 45470 | FY2: 45471 | FZ2: 45472 | GA2: 45473 | GB2: 45474 | GC2: 45475 | GD2: 45476 | GE2: 45477 | GF2: 45478 | GG2: 45479 | GH2: 45480 | GI2: 45481 | GJ2: 45482 | GK2: 45483 | GL2: 45484 | GM2: 45485 | GN2: 45486 | GO2: 45487 | GP2: 45488 | GQ2: 45489 | GR2: 45490 | GS2: 45491 | GT2: 45492 | GU2: 45493 | GV2: 45494 | GW2: 45495 | GX2: 45496 | GY2: 45497 | GZ2: 45498 | HA2: 45499 | HB2: 45500 | HC2: 45501 | HD2: 45502 | HE2: 45503 | HF2: 45504 | HG2: 45505 | HH2: 45506 | HI2: 45507 | HJ2: 45508 | HK2: 45509 | HL2: 45510 | HM2: 45511 | HN2: 45512 | HO2: 45513 | HP2: 45514 | HQ2: 45515 | HR2: 45516 | HS2: 45517 | HT2: 45518 | HU2: 45519 | HV2: 45520 | HW2: 45521 | HX2: 45522 | HY2: 45523 | HZ2: 45524 | IA2: 45525 | IB2: 45526 | IC2: 45527 | ID2: 45528 | IE2: 45529 | IF2: 45530 | IG2: 45531 | IH2: 45532 | II2: 45533 | IJ2: 45534 | IK2: 45535 | IL2: 45536 | IM2: 45537 | IN2: 45538 | IO2: 45539 | IP2: 45540 | IQ2: 45541 | IR2: 45542 | IS2: 45543 | IT2: 45544 | IU2: 45545 | IV2: 45546 | IW2: 45547 | IX2: 45548 | IY2: 45549 | IZ2: 45550 | JA2: 45551 | JB2: 45552 | JC2: 45553 | JD2: 45554 | JE2: 45555 | JF2: 45556 | JG2: 45557 | JH2: 45558 | JI2: 45559 | JJ2: 45560 | JK2: 45561 | JL2: 45562 | JM2: 45563 | JN2: 45564 | JO2: 45565 | JP2: 45566 | JQ2: 45567 | JR2: 45568 | JS2: 45569 | JT2: 45570 | JU2: 45571 | JV2: 45572 | JW2: 45573 | JX2: 45574 | JY2: 45575 | JZ2: 45576 | KA2: 45577 | KB2: 45578 | KC2: 45579 | KD2: 45580 | KE2: 45581 | KF2: 45582 | KG2: 45583 | KH2: 45584 | KI2: 45585 | KJ2: 45586 | KK2: 45587 | KL2: 45588 | KM2: 45589 | KN2: 45590 | KO2: 45591 | KP2: 45592 | KQ2: 45593 | KR2: 45594 | KS2: 45595 | KT2: 45596 | KU2: 45597 | KV2: 45598 | KW2: 45599 | KX2: 45600 | KY2: 45601 | KZ2: 45602 | LA2: 45603 | LB2: 45604 | LC2: 45605 | LD2: 45606 | LE2: 45607 | LF2: 45608 | LG2: 45609 | LH2: 45610 | LI2: 45611 | LJ2: 45612 | LK2: 45613 | LL2: 45614 | LM2: 45615 | LN2: 45616 | LO2: 45617 | LP2: 45618 | LQ2: 45619 | LR2: 45620 | LS2: 45621 | LT2: 45622 | LU2: 45623 | LV2: 45624 | LW2: 45625 | LX2: 45626 | LY2: 45627 | LZ2: 45628 | MA2: 45629 | MB2: 45630 | MC2: 45631 | MD2: 45632 | ME2: 45633 | MF2: 45634 | MG2: 45635 | MH2: 45636 | MI2: 45637 | MJ2: 45638 | MK2: 45639 | ML2: 45640 | MM2: 45641 | MN2: 45642 | MO2: 45643 | MP2: 45644 | MQ2: 45645 | MR2: 45646 | MS2: 45647 | MT2: 45648 | MU2: 45649 | MV2: 45650 | MW2: 45651 | MX2: 45652 | MY2: 45653 | MZ2: 45654 | NA2: 45655 | NB2: 45656 | NC2: 45657 | ND2: 45658 | NE2: 45659 | NF2: 45660 | NG2: 45661 | NH2: 45662 | NI2: 45663 | NJ2: 45664 | NK2: 45665 | NL2: 45666 | NM2: 45667 | NN2: 45668 | NO2: 45669
A3: Unit Availability 2024 | B3: M | C3: T | D3: W | E3: T | F3: F | G3: S | H3: S | I3: M | J3: T | K3: W | L3: T | M3: F | N3: S | O3: S | P3: M | Q3: T | R3: W | S3: T | T3: F | U3: S | V3: S | W3: M | X3: T | Y3: W | Z3: T | AA3: F | AB3: S | AC3: S | AD3: M | AE3: T | AF3: W | AG3: T | AH3: F | AI3: S | AJ3: S | AK3: M | AL3: T | AM3: W | AN3: T | AO3: F | AP3: S | AQ3: S | AR3: M | AS3: T | AT3: W | AU3: T | AV3: F | AW3: S | AX3: S | AY3: M | AZ3: T | BA3: W | BB3: T | BC3: F | BD3: S | BE3: S | BF3: M | BG3: T | BH3: W | BI3: T | BJ3: F | BK3: S | BL3: S | BM3: M | BN3: T | BO3: W | BP3: T | BQ3: F | BR3: S | BS3: S | BT3: M | BU3: T | BV3: W | BW3: T | BX3: F | BY3: S | BZ3: S | CA3: M | CB3: T | CC3: W | CD3: T | CE3: F | CF3: S | CG3: S | CH3: M | CI3: T | CJ3: W | CK3: T | CL3: F | CM3: S | CN3: S | CO3: M | CP3: T | CQ3: W | CR3: T | CS3: F | CT3: S | CU3: S | CV3: M | CW3: T | CX3: W | CY3: T | CZ3: F | DA3: S | DB3: S | DC3: M | DD3: T | DE3: W | DF3: T | DG3: F | DH3: S | DI3: S | DJ3: M | DK3: T | DL3: W | DM3: T | DN3: F | DO3: S | DP3: S | DQ3: M | DR3: T | DS3: W | DT3: T | DU3: F | DV3: S | DW3: S | DX3: M | DY3: T | DZ3: W | EA3: T | EB3: F | EC3: S | ED3: S | EE3: M | EF3: T | EG3: W | EH3: T | EI3: F | EJ3: S | EK3: S | EL3: M | EM3: T | EN3: W | EO3: T | EP3: F | EQ3: S | ER3: S | ES3: M | ET3: T | EU3: W | EV3: T | EW3: F | EX3: S | EY3: S | EZ3: M | FA3: T | FB3: W | FC3: T | FD3: F | FE3: S | FF3: S | FG3: M | FH3: T | FI3: W | FJ3: T | FK3: F | FL3: S | FM3: S | FN3: M | FO3: T | FP3: W | FQ3: T | FR3: F | FS3: S | FT3: S | FU3: M | FV3: T | FW3: W | FX3: T | FY3: F | FZ3: S | GA3: S | GB3: M | GC3: T | GD3: W | GE3: T | GF3: F | GG3: S | GH3: S | GI3: M | GJ3: T | GK3: W | GL3: T | GM3: F | GN3: S | GO3: S | GP3: M | GQ3: T | GR3: W | GS3: T | GT3: F | GU3: S | GV3: S | GW3: M | GX3: T | GY3: W | GZ3: T | HA3: F | HB3: S | HC3: S | HD3: M | HE3: T | HF3: W | HG3: T | HH3: F | HI3: S | HJ3: S | HK3: M | HL3: T | HM3: W | HN3: T | HO3: F | HP3: S | HQ3: S | HR3: M | HS3: T | HT3: W | HU3: T | HV3: F | HW3: S | HX3: S | HY3: M | HZ3: T | IA3: W | IB3: T | IC3: F | ID3: S | IE3: S | IF3: M | IG3: T | IH3: W | II3: T | IJ3: F | IK3: S | IL3: S | IM3: M | IN3: T | IO3: W | IP3: T | IQ3: F | IR3: S | IS3: S | IT3: M | IU3: T | IV3: W | IW3: T | IX3: F | IY3: S | IZ3: S | JA3: M | JB3: T | JC3: W | JD3: T | JE3: F | JF3: S | JG3: S | JH3: M | JI3: T | JJ3: W | JK3: T | JL3: F | JM3: S | JN3: S | JO3: M | JP3: T | JQ3: W | JR3: T | JS3: F | JT3: S | JU3: S | JV3: M | JW3: T | JX3: W | JY3: T | JZ3: F | KA3: S | KB3: S | KC3: M | KD3: T | KE3: W | KF3: T | KG3: F | KH3: S | KI3: S | KJ3: M | KK3: T | KL3: W | KM3: T | KN3: F | KO3: S | KP3: S | KQ3: M | KR3: T | KS3: W | KT3: T | KU3: F | KV3: S | KW3: S | KX3: M | KY3: T | KZ3: W | LA3: T | LB3: F | LC3: S | LD3: S | LE3: M | LF3: T | LG3: W | LH3: T | LI3: F | LJ3: S | LK3: S | LL3: M | LM3: T | LN3: W | LO3: T | LP3: F | LQ3: S | LR3: S | LS3: M | LT3: T | LU3: W | LV3: T | LW3: F | LX3: S | LY3: S | LZ3: M | MA3: T | MB3: W | MC3: T | MD3: F | ME3: S | MF3: S | MG3: M | MH3: T | MI3: W | MJ3: T | MK3: F | ML3: S | MM3: S | MN3: M | MO3: T | MP3: W | MQ3: T | MR3: F | MS3: S | MT3: S | MU3: M | MV3: T | MW3: W | MX3: T | MY3: F | MZ3: S | NA3: S | NB3: M | NC3: T | ND3: W | NE3: T | NF3: F | NG3: S | NH3: S | NI3: M | NJ3: T | NK3: W | NL3: T | NM3: F | NN3: S | NO3: S
A4: {=Table!B13:B41} -> Burger/Chipper Units | B4: FALSE | C4: FALSE | D4: FALSE | E4: FALSE | F4: FALSE | G4: FALSE | H4: FALSE | I4: FALSE | J4: FALSE | K4: FALSE | L4: FALSE | M4: FALSE | N4: FALSE | O4: FALSE | P4: FALSE | Q4: FALSE | R4: FALSE | S4: FALSE | T4: FALSE | U4: FALSE | V4: FALSE | W4: FALSE | X4: FALSE | Y4: FALSE | Z4: FALSE | AA4: FALSE | AB4: FALSE | AC4: FALSE | AD4: FALSE | AE4: FALSE | AF4: FALSE | AG4: FALSE | AH4: FALSE | AI4: FALSE | AJ4: FALSE | AK4: FALSE | AL4: FALSE | AM4: FALSE | AN4: FALSE | AO4: FALSE | AP4: FALSE | AQ4: FALSE | AR4: FALSE | AS4: FALSE | AT4: FALSE | AU4: FALSE | AV4: FALSE | AW4: FALSE | AX4: FALSE | AY4: FALSE | AZ4: FALSE | BA4: FALSE | BB4: FALSE | BC4: FALSE | BD4: FALSE | BE4: FALSE | BF4: FALSE | BG4: FALSE | BH4: FALSE | BI4: FALSE | BJ4: FALSE | BK4: FALSE | BL4: FALSE | BM4: FALSE | BN4: FALSE | BO4: FALSE | BP4: FALSE | BQ4: FALSE | BR4: FALSE | BS4: FALSE | BT4: FALSE | BU4: FALSE | BV4: FALSE | BW4: FALSE | BX4: FALSE | BY4: FALSE | BZ4: FALSE | CA4: FALSE | CB4: FALSE | CC4: FALSE | CD4: FALSE | CE4: FALSE | CF4: FALSE | CG4: FALSE | CH4: FALSE | CI4: FALSE | CJ4: FALSE | CK4: FALSE | CL4: FALSE | CM4: FALSE | CN4: FALSE | CO4: FALSE | CP4: FALSE | CQ4: FALSE | CR4: FALSE | CS4: FALSE | CT4: FALSE | CU4: FALSE | CV4: FALSE | CW4: FALSE | CX4: FALSE | CY4: FALSE | CZ4: FALSE | DA4: FALSE | DB4: FALSE | DC4: FALSE | DD4: FALSE | DE4: FALSE | DF4: FALSE | DG4: FALSE | DH4: FALSE | DI4: FALSE | DJ4: FALSE | DK4: FALSE | DL4: FALSE | DM4: FALSE | DN4: FALSE | DO4: FALSE | DP4: FALSE | DQ4: FALSE | DR4: FALSE | DS4: FALSE | DT4: FALSE | DU4: FALSE | DV4: FALSE | DW4: FALSE | DX4: FALSE | DY4: FALSE | DZ4: FALSE | EA4: FALSE | EB4: FALSE | EC4: FALSE | ED4: FALSE | EE4: FALSE | EF4: FALSE | EG4: FALSE | EH4: FALSE | EI4: FALSE | EJ4: FALSE | EK4: FALSE | EL4: FALSE | EM4: FALSE | EN4: FALSE | EO4: FALSE | EP4: FALSE | EQ4: FALSE | ER4: FALSE | ES4: FALSE | ET4: FALSE | EU4: FALSE | EV4: FALSE | EW4: FALSE | EX4: FALSE | EY4: FALSE | EZ4: FALSE | FA4: FALSE | FB4: FALSE | FC4: FALSE | FD4: FALSE | FE4: FALSE | FF4: FALSE | FG4: FALSE | FH4: FALSE | FI4: FALSE | FJ4: FALSE | FK4: FALSE | FL4: FALSE | FM4: FALSE | FN4: FALSE | FO4: FALSE | FP4: FALSE | FQ4: FALSE | FR4: FALSE | FS4: FALSE | FT4: FALSE | FU4: FALSE | FV4: FALSE | FW4: FALSE | FX4: FALSE | FY4: FALSE | FZ4: FALSE | GA4: FALSE | GB4: FALSE | GC4: FALSE | GD4: FALSE | GE4: FALSE | GF4: FALSE | GG4: FALSE | GH4: FALSE | GI4: FALSE | GJ4: FALSE | GK4: FALSE | GL4: FALSE | GM4: FALSE | GN4: FALSE | GO4: FALSE | GP4: FALSE | GQ4: FALSE | GR4: FALSE | GS4: FALSE | GT4: FALSE | GU4: FALSE | GV4: FALSE | GW4: FALSE | GX4: FALSE | GY4: FALSE | GZ4: FALSE | HA4: FALSE | HB4: FALSE | HC4: FALSE | HD4: FALSE | HE4: FALSE | HF4: FALSE | HG4: FALSE | HH4: FALSE | HI4: FALSE | HJ4: FALSE | HK4: FALSE | HL4: FALSE | HM4: FALSE | HN4: FALSE | HO4: FALSE | HP4: FALSE | HQ4: FALSE | HR4: FALSE | HS4: FALSE | HT4: FALSE | HU4: FALSE | HV4: FALSE | HW4: FALSE | HX4: FALSE | HY4: FALSE | HZ4: FALSE | IA4: FALSE | IB4: FALSE | IC4: FALSE | ID4: FALSE | IE4: FALSE | IF4: FALSE | IG4: FALSE | IH4: FALSE | II4: FALSE | IJ4: FALSE | IK4: FALSE | IL4: FALSE | IM4: FALSE | IN4: FALSE | IO4: FALSE | IP4: FALSE | IQ4: FALSE | IR4: FALSE | IS4: FALSE | IT4: FALSE | IU4: FALSE | IV4: FALSE | IW4: FALSE | IX4: FALSE | IY4: FALSE | IZ4: FALSE | JA4: FALSE | JB4: FALSE | JC4: FALSE | JD4: FALSE | JE4: FALSE | JF4: FALSE | JG4: FALSE | JH4: FALSE | JI4: FALSE | JJ4: FALSE | JK4: FALSE | JL4: FALSE | JM4: FALSE | JN4: FALSE | JO4: FALSE | JP4: FALSE | JQ4: FALSE | JR4: FALSE | JS4: FALSE | JT4: FALSE | JU4: FALSE | JV4: FALSE | JW4: FALSE | JX4: FALSE | JY4: FALSE | JZ4: FALSE | KA4: FALSE | KB4: FALSE | KC4: FALSE | KD4: FALSE | KE4: FALSE | KF4: FALSE | KG4: FALSE | KH4: FALSE | KI4: FALSE | KJ4: FALSE | KK4: FALSE | KL4: FALSE | KM4: FALSE | KN4: FALSE | KO4: FALSE | KP4: FALSE | KQ4: FALSE | KR4: FALSE | KS4: FALSE | KT4: FALSE | KU4: FALSE | KV4: FALSE | KW4: FALSE | KX4: FALSE | KY4: FALSE | KZ4: FALSE | LA4: FALSE | LB4: FALSE | LC4: FALSE | LD4: FALSE | LE4: FALSE | LF4: FALSE | LG4: FALSE | LH4: FALSE | LI4: FALSE | LJ4: FALSE | LK4: FALSE | LL4: FALSE | LM4: FALSE | LN4: FALSE | LO4: FALSE | LP4: FALSE | LQ4: FALSE | LR4: FALSE | LS4: FALSE | LT4: FALSE | LU4: FALSE | LV4: FALSE | LW4: FALSE | LX4: FALSE | LY4: FALSE | LZ4: FALSE | MA4: FALSE | MB4: FALSE | MC4: FALSE | MD4: FALSE | ME4: FALSE | MF4: FALSE | MG4: FALSE | MH4: FALSE | MI4: FALSE | MJ4: FALSE | MK4: FALSE | ML4: FALSE | MM4: FALSE | MN4: FALSE | MO4: FALSE | MP4: FALSE | MQ4: FALSE | MR4: FALSE | MS4: FALSE | MT4: FALSE | MU4: FALSE | MV4: FALSE | MW4: FALSE | MX4: FALSE | MY4: FALSE | MZ4: FALSE | NA4: FALSE | NB4: FALSE | NC4: FALSE | ND4: FALSE | NE4: FALSE | NF4: FALSE | NG4: FALSE | NH4: FALSE | NI4: FALSE | NJ4: FALSE | NK4: FALSE | NL4: FALSE | NM4: FALSE | NN4: FALSE | NO4: FALSE
A5: O'Briens Chipper 1 | B5: FALSE | C5: FALSE | D5: FALSE | E5: FALSE | F5: FALSE | G5: FALSE | H5: FALSE | I5: FALSE | J5: FALSE | K5: FALSE | L5: FALSE | M5: FALSE | N5: FALSE | O5: FALSE | P5: FALSE | Q5: FALSE | R5: FALSE | S5: FALSE | T5: FALSE | U5: FALSE | V5: FALSE | W5: FALSE | X5: FALSE | Y5: FALSE | Z5: FALSE | AA5: FALSE | AB5: FALSE | AC5: FALSE | AD5: FALSE | AE5: FALSE | AF5: FALSE | AG5: FALSE | AH5: FALSE | AI5: FALSE | AJ5: FALSE | AK5: FALSE | AL5: FALSE | AM5: FALSE | AN5: FALSE | AO5: FALSE | AP5: FALSE | AQ5: FALSE | AR5: FALSE | AS5: FALSE | AT5: FALSE | AU5: FALSE | AV5: FALSE | AW5: FALSE | AX5: FALSE | AY5: FALSE | AZ5: FALSE | BA5: FALSE | BB5: FALSE | BC5: FALSE | BD5: FALSE | BE5: FALSE | BF5: FALSE | BG5: FALSE | BH5: FALSE | BI5: FALSE | BJ5: FALSE | BK5: FALSE | BL5: FALSE | BM5: FALSE | BN5: FALSE | BO5: FALSE | BP5: FALSE | BQ5: FALSE | BR5: FALSE | BS5: FALSE | BT5: FALSE | BU5: FALSE | BV5: FALSE | BW5: FALSE | BX5: FALSE | BY5: FALSE | BZ5: TRUE | CA5: FALSE | CB5: FALSE | CC5: FALSE | CD5: FALSE | CE5: FALSE | CF5: FALSE | CG5: FALSE | CH5: FALSE | CI5: FALSE | CJ5: FALSE | CK5: FALSE | CL5: FALSE | CM5: FALSE | CN5: FALSE | CO5: FALSE | CP5: FALSE | CQ5: FALSE | CR5: FALSE | CS5: FALSE | CT5: FALSE | CU5: FALSE | CV5: FALSE | CW5: FALSE | CX5: FALSE | CY5: FALSE | CZ5: FALSE | DA5: FALSE | DB5: FALSE | DC5: FALSE | DD5: FALSE | DE5: FALSE | DF5: FALSE | DG5: FALSE | DH5: FALSE | DI5: FALSE | DJ5: FALSE | DK5: FALSE | DL5: FALSE | DM5: FALSE | DN5: FALSE | DO5: FALSE | DP5: FALSE | DQ5: FALSE | DR5: TRUE | DS5: TRUE | DT5: TRUE | DU5: TRUE | DV5: TRUE | DW5: FALSE | DX5: FALSE | DY5: FALSE | DZ5: FALSE | EA5: FALSE | EB5: FALSE | EC5: TRUE | ED5: FALSE | EE5: FALSE | EF5: FALSE | EG5: FALSE | EH5: FALSE | EI5: FALSE | EJ5: FALSE | EK5: FALSE | EL5: FALSE | EM5: FALSE | EN5: FALSE | EO5: FALSE | EP5: FALSE | EQ5: FALSE | ER5: FALSE | ES5: FALSE | ET5: FALSE | EU5: FALSE | EV5: FALSE | EW5: TRUE | EX5: FALSE | EY5: FALSE | EZ5: FALSE | FA5: FALSE | FB5: FALSE | FC5: FALSE | FD5: FALSE | FE5: FALSE | FF5: FALSE | FG5: FALSE | FH5: FALSE | FI5: FALSE | FJ5: FALSE | FK5: FALSE | FL5: FALSE | FM5: FALSE | FN5: FALSE | FO5: FALSE | FP5: FALSE | FQ5: FALSE | FR5: FALSE | FS5: FALSE | FT5: TRUE | FU5: FALSE | FV5: FALSE | FW5: FALSE | FX5: FALSE | FY5: FALSE | FZ5: FALSE | GA5: FALSE | GB5: FALSE | GC5: FALSE | GD5: FALSE | GE5: FALSE | GF5: FALSE | GG5: FALSE | GH5: FALSE | GI5: FALSE | GJ5: FALSE | GK5: FALSE | GL5: FALSE | GM5: FALSE | GN5: FALSE | GO5: FALSE | GP5: FALSE | GQ5: FALSE | GR5: FALSE | GS5: FALSE | GT5: FALSE | GU5: FALSE | GV5: FALSE | GW5: FALSE | GX5: FALSE | GY5: FALSE | GZ5: FALSE | HA5: FALSE | HB5: FALSE | HC5: FALSE | HD5: FALSE | HE5: FALSE | HF5: FALSE | HG5: FALSE | HH5: FALSE | HI5: FALSE | HJ5: FALSE | HK5: FALSE | HL5: FALSE | HM5: FALSE | HN5: FALSE | HO5: FALSE | HP5: FALSE | HQ5: FALSE | HR5: FALSE | HS5: FALSE | HT5: TRUE | HU5: TRUE | HV5: TRUE | HW5: TRUE | HX5: TRUE | HY5: FALSE | HZ5: FALSE | IA5: FALSE | IB5: FALSE | IC5: FALSE | ID5: FALSE | IE5: FALSE | IF5: FALSE | IG5: FALSE | IH5: FALSE | II5: FALSE | IJ5: FALSE | IK5: FALSE | IL5: FALSE | IM5: FALSE | IN5: FALSE | IO5: FALSE | IP5: FALSE | IQ5: FALSE | IR5: FALSE | IS5: FALSE | IT5: FALSE | IU5: FALSE | IV5: FALSE | IW5: FALSE | IX5: FALSE | IY5: FALSE | IZ5: FALSE | JA5: FALSE | JB5: FALSE | JC5: FALSE | JD5: FALSE | JE5: FALSE | JF5: FALSE | JG5: FALSE | JH5: FALSE | JI5: FALSE | JJ5: FALSE | JK5: FALSE | JL5: FALSE | JM5: FALSE | JN5: FALSE | JO5: FALSE | JP5: FALSE | JQ5: FALSE | JR5: FALSE | JS5: FALSE | JT5: FALSE | JU5: FALSE | JV5: FALSE | JW5: FALSE | JX5: FALSE | JY5: FALSE | JZ5: FALSE | KA5: FALSE | KB5: FALSE | KC5: FALSE | KD5: FALSE | KE5: FALSE | KF5: FALSE | KG5: FALSE | KH5: FALSE | KI5: FALSE | KJ5: FALSE | KK5: FALSE | KL5: FALSE | KM5: FALSE | KN5: FALSE | KO5: FALSE | KP5: FALSE | KQ5: FALSE | KR5: FALSE | KS5: FALSE | KT5: FALSE | KU5: FALSE | KV5: FALSE | KW5: FALSE | KX5: FALSE | KY5: FALSE | KZ5: FALSE | LA5: FALSE | LB5: FALSE | LC5: FALSE | LD5: FALSE | LE5: FALSE | LF5: FALSE | LG5: FALSE | LH5: FALSE | LI5: FALSE | LJ5: FALSE | LK5: FALSE | LL5: FALSE | LM5: FALSE | LN5: FALSE | LO5: FALSE | LP5: FALSE | LQ5: FALSE | LR5: FALSE | LS5: FALSE | LT5: FALSE | LU5: FALSE | LV5: FALSE | LW5: FALSE | LX5: FALSE | LY5: FALSE | LZ5: FALSE | MA5: FALSE | MB5: FALSE | MC5: FALSE | MD5: FALSE | ME5: FALSE | MF5: FALSE | MG5: FALSE | MH5: FALSE | MI5: FALSE | MJ5: FALSE | MK5: FALSE | ML5: FALSE | MM5: FALSE | MN5: FALSE | MO5: FALSE | MP5: FALSE | MQ5: FALSE | MR5: FALSE | MS5: FALSE | MT5: FALSE | MU5: FALSE | MV5: FALSE | MW5: FALSE | MX5: FALSE | MY5: FALSE | MZ5: FALSE | NA5: FALSE | NB5: FALSE | NC5: FALSE | ND5: FALSE | NE5: FALSE | NF5: FALSE | NG5: FALSE | NH5: FALSE | NI5: FALSE | NJ5: FALSE | NK5: FALSE | NL5: FALSE | NM5: FALSE | NN5: FALSE | NO5: FALSE
A6: O'Briens Chipper 2 | B6: FALSE | C6: FALSE | D6: FALSE | E6: FALSE | F6: FALSE | G6: FALSE | H6: FALSE | I6: FALSE | J6: FALSE | K6: FALSE | L6: FALSE | M6: FALSE | N6: FALSE | O6: FALSE | P6: FALSE | Q6: FALSE | R6: FALSE | S6: FALSE | T6: FALSE | U6: FALSE | V6: FALSE | W6: FALSE | X6: FALSE | Y6: FALSE | Z6: FALSE | AA6: FALSE | AB6: FALSE | AC6: FALSE | AD6: FALSE | AE6: FALSE | AF6: FALSE | AG6: FALSE | AH6: FALSE | AI6: FALSE | AJ6: FALSE | AK6: FALSE | AL6: FALSE | AM6: FALSE | AN6: FALSE | AO6: FALSE | AP6: FALSE | AQ6: FALSE | AR6: FALSE | AS6: FALSE | AT6: FALSE | AU6: FALSE | AV6: FALSE | AW6: FALSE | AX6: FALSE | AY6: FALSE | AZ6: FALSE | BA6: FALSE | BB6: FALSE | BC6: FALSE | BD6: FALSE | BE6: FALSE | BF6: FALSE | BG6: FALSE | BH6: FALSE | BI6: FALSE | BJ6: FALSE | BK6: FALSE | BL6: FALSE | BM6: FALSE | BN6: FALSE | BO6: FALSE | BP6: FALSE | BQ6: FALSE | BR6: FALSE | BS6: FALSE | BT6: FALSE | BU6: FALSE | BV6: FALSE | BW6: FALSE | BX6: FALSE | BY6: FALSE | BZ6: FALSE | CA6: FALSE | CB6: FALSE | CC6: FALSE | CD6: FALSE | CE6: FALSE | CF6: FALSE | CG6: FALSE | CH6: FALSE | CI6: FALSE | CJ6: FALSE | CK6: FALSE | CL6: FALSE | CM6: FALSE | CN6: FALSE | CO6: FALSE | CP6: FALSE | CQ6: FALSE | CR6: FALSE | CS6: FALSE | CT6: FALSE | CU6: FALSE | CV6: FALSE | CW6: FALSE | CX6: FALSE | CY6: FALSE | CZ6: FALSE | DA6: FALSE | DB6: FALSE | DC6: FALSE | DD6: FALSE | DE6: FALSE | DF6: FALSE | DG6: FALSE | DH6: FALSE | DI6: FALSE | DJ6: FALSE | DK6: FALSE | DL6: FALSE | DM6: FALSE | DN6: FALSE | DO6: FALSE | DP6: FALSE | DQ6: FALSE | DR6: FALSE | DS6: FALSE | DT6: FALSE | DU6: FALSE | DV6: FALSE | DW6: FALSE | DX6: FALSE | DY6: FALSE | DZ6: FALSE | EA6: FALSE | EB6: FALSE | EC6: FALSE | ED6: FALSE | EE6: FALSE | EF6: FALSE | EG6: FALSE | EH6: FALSE | EI6: FALSE | EJ6: FALSE | EK6: FALSE | EL6: FALSE | EM6: FALSE | EN6: FALSE | EO6: FALSE | EP6: FALSE | EQ6: FALSE | ER6: FALSE | ES6: FALSE | ET6: FALSE | EU6: FALSE | EV6: FALSE | EW6: FALSE | EX6: FALSE | EY6: FALSE | EZ6: FALSE | FA6: FALSE | FB6: FALSE | FC6: FALSE | FD6: FALSE | FE6: FALSE | FF6: FALSE | FG6: FALSE | FH6: FALSE | FI6: FALSE | FJ6: FALSE | FK6: FALSE | FL6: FALSE | FM6: FALSE | FN6: FALSE | FO6: FALSE | FP6: FALSE | FQ6: FALSE | FR6: FALSE | FS6: FALSE | FT6: FALSE | FU6: FALSE | FV6: FALSE | FW6: FALSE | FX6: FALSE | FY6: FALSE | FZ6: FALSE | GA6: FALSE | GB6: FALSE | GC6: FALSE | GD6: FALSE | GE6: FALSE | GF6: FALSE | GG6: FALSE | GH6: FALSE | GI6: FALSE | GJ6: FALSE | GK6: FALSE | GL6: FALSE | GM6: FALSE | GN6: FALSE | GO6: FALSE | GP6: FALSE | GQ6: FALSE | GR6: FALSE | GS6: FALSE | GT6: FALSE | GU6: FALSE | GV6: FALSE | GW6: FALSE | GX6: FALSE | GY6: FALSE | GZ6: FALSE | HA6: FALSE | HB6: FALSE | HC6: FALSE | HD6: FALSE | HE6: FALSE | HF6: FALSE | HG6: FALSE | HH6: FALSE | HI6: FALSE | HJ6: FALSE | HK6: FALSE | HL6: FALSE | HM6: FALSE | HN6: FALSE | HO6: FALSE | HP6: FALSE | HQ6: FALSE | HR6: FALSE | HS6: FALSE | HT6: FALSE | HU6: FALSE | HV6: FALSE | HW6: FALSE | HX6: FALSE | HY6: FALSE | HZ6: FALSE | IA6: FALSE | IB6: FALSE | IC6: FALSE | ID6: FALSE | IE6: FALSE | IF6: FALSE | IG6: FALSE | IH6: FALSE | II6: FALSE | IJ6: FALSE | IK6: FALSE | IL6: FALSE | IM6: FALSE | IN6: FALSE | IO6: FALSE | IP6: FALSE | IQ6: FALSE | IR6: FALSE | IS6: FALSE | IT6: FALSE | IU6: FALSE | IV6: FALSE | IW6: FALSE | IX6: FALSE | IY6: FALSE | IZ6: FALSE | JA6: FALSE | JB6: FALSE | JC6: FALSE | JD6: FALSE | JE6: FALSE | JF6: FALSE | JG6: FALSE | JH6: FALSE | JI6: FALSE | JJ6: FALSE | JK6: FALSE | JL6: FALSE | JM6: FALSE | JN6: FALSE | JO6: FALSE | JP6: FALSE | JQ6: FALSE | JR6: FALSE | JS6: FALSE | JT6: FALSE | JU6: FALSE | JV6: FALSE | JW6: FALSE | JX6: FALSE | JY6: FALSE | JZ6: FALSE | KA6: FALSE | KB6: FALSE | KC6: FALSE | KD6: FALSE | KE6: FALSE | KF6: FALSE | KG6: FALSE | KH6: FALSE | KI6: FALSE | KJ6: FALSE | KK6: FALSE | KL6: FALSE | KM6: FALSE | KN6: FALSE | KO6: FALSE | KP6: FALSE | KQ6: FALSE | KR6: FALSE | KS6: FALSE | KT6: FALSE | KU6: FALSE | KV6: FALSE | KW6: FALSE | KX6: FALSE | KY6: FALSE | KZ6: FALSE | LA6: FALSE | LB6: FALSE | LC6: FALSE | LD6: FALSE | LE6: FALSE | LF6: FALSE | LG6: FALSE | LH6: FALSE | LI6: FALSE | LJ6: FALSE | LK6: FALSE | LL6: FALSE | LM6: FALSE | LN6: FALSE | LO6: FALSE | LP6: FALSE | LQ6: FALSE | LR6: FALSE | LS6: FALSE | LT6: FALSE | LU6: FALSE | LV6: FALSE | LW6: FALSE | LX6: FALSE | LY6: FALSE | LZ6: FALSE | MA6: FALSE | MB6: FALSE | MC6: FALSE | MD6: FALSE | ME6: FALSE | MF6: FALSE | MG6: FALSE | MH6: FALSE | MI6: FALSE | MJ6: FALSE | MK6: FALSE | ML6: FALSE | MM6: FALSE | MN6: FALSE | MO6: FALSE | MP6: FALSE | MQ6: FALSE | MR6: FALSE | MS6: FALSE | MT6: FALSE | MU6: FALSE | MV6: FALSE | MW6: FALSE | MX6: FALSE | MY6: FALSE | MZ6: FALSE | NA6: FALSE | NB6: FALSE | NC6: FALSE | ND6: FALSE | NE6: FALSE | NF6: FALSE | NG6: FALSE | NH6: FALSE | NI6: FALSE | NJ6: FALSE | NK6: FALSE | NL6: FALSE | NM6: FALSE | NN6: FALSE | NO6: FALSE
A7: Smash Burger 1 | B7: FALSE | C7: FALSE | D7: FALSE | E7: FALSE | F7: FALSE | G7: FALSE | H7: FALSE | I7: FALSE | J7: FALSE | K7: FALSE | L7: FALSE | M7: FALSE | N7: FALSE | O7: FALSE | P7: FALSE | Q7: FALSE | R7: FALSE | S7: FALSE | T7: FALSE | U7: FALSE | V7: FALSE | W7: FALSE | X7: FALSE | Y7: FALSE | Z7: FALSE | AA7: FALSE | AB7: FALSE | AC7: FALSE | AD7: FALSE | AE7: FALSE | AF7: FALSE | AG7: FALSE | AH7: FALSE | AI7: FALSE | AJ7: FALSE | AK7: FALSE | AL7: FALSE | AM7: FALSE | AN7: FALSE | AO7: FALSE | AP7: FALSE | AQ7: FALSE | AR7: FALSE | AS7: FALSE | AT7: FALSE | AU7: FALSE | AV7: FALSE | AW7: FALSE | AX7: FALSE | AY7: FALSE | AZ7: FALSE | BA7: FALSE | BB7: FALSE | BC7: FALSE | BD7: FALSE | BE7: FALSE | BF7: FALSE | BG7: FALSE | BH7: FALSE | BI7: FALSE | BJ7: FALSE | BK7: FALSE | BL7: FALSE | BM7: FALSE | BN7: FALSE | BO7: FALSE | BP7: FALSE | BQ7: FALSE | BR7: FALSE | BS7: FALSE | BT7: FALSE | BU7: FALSE | BV7: FALSE | BW7: FALSE | BX7: FALSE | BY7: FALSE | BZ7: FALSE | CA7: FALSE | CB7: FALSE | CC7: FALSE | CD7: FALSE | CE7: FALSE | CF7: FALSE | CG7: FALSE | CH7: FALSE | CI7: FALSE | CJ7: FALSE | CK7: FALSE | CL7: FALSE | CM7: FALSE | CN7: FALSE | CO7: FALSE | CP7: FALSE | CQ7: FALSE | CR7: FALSE | CS7: FALSE | CT7: FALSE | CU7: FALSE | CV7: FALSE | CW7: FALSE | CX7: FALSE | CY7: FALSE | CZ7: FALSE | DA7: FALSE | DB7: FALSE | DC7: FALSE | DD7: FALSE | DE7: FALSE | DF7: FALSE | DG7: FALSE | DH7: FALSE | DI7: FALSE | DJ7: FALSE | DK7: FALSE | DL7: FALSE | DM7: FALSE | DN7: FALSE | DO7: FALSE | DP7: FALSE | DQ7: FALSE | DR7: FALSE | DS7: FALSE | DT7: FALSE | DU7: FALSE | DV7: FALSE | DW7: FALSE | DX7: FALSE | DY7: FALSE | DZ7: FALSE | EA7: FALSE | EB7: FALSE | EC7: FALSE | ED7: FALSE | EE7: FALSE | EF7: FALSE | EG7: FALSE | EH7: FALSE | EI7: FALSE | EJ7: FALSE | EK7: FALSE | EL7: FALSE | EM7: FALSE | EN7: FALSE | EO7: FALSE | EP7: FALSE | EQ7: FALSE | ER7: FALSE | ES7: FALSE | ET7: FALSE | EU7: FALSE | EV7: FALSE | EW7: FALSE | EX7: FALSE | EY7: FALSE | EZ7: FALSE | FA7: FALSE | FB7: FALSE | FC7: FALSE | FD7: FALSE | FE7: FALSE | FF7: FALSE | FG7: FALSE | FH7: FALSE | FI7: FALSE | FJ7: FALSE | FK7: FALSE | FL7: FALSE | FM7: FALSE | FN7: FALSE | FO7: FALSE | FP7: FALSE | FQ7: FALSE | FR7: FALSE | FS7: FALSE | FT7: FALSE | FU7: FALSE | FV7: FALSE | FW7: FALSE | FX7: FALSE | FY7: FALSE | FZ7: FALSE | GA7: FALSE | GB7: FALSE | GC7: FALSE | GD7: FALSE | GE7: FALSE | GF7: FALSE | GG7: FALSE | GH7: FALSE | GI7: FALSE | GJ7: FALSE | GK7: FALSE | GL7: FALSE | GM7: FALSE | GN7: FALSE | GO7: FALSE | GP7: FALSE | GQ7: FALSE | GR7: FALSE | GS7: FALSE | GT7: FALSE | GU7: FALSE | GV7: FALSE | GW7: FALSE | GX7: FALSE | GY7: FALSE | GZ7: FALSE | HA7: FALSE | HB7: FALSE | HC7: FALSE | HD7: FALSE | HE7: FALSE | HF7: FALSE | HG7: FALSE | HH7: FALSE | HI7: FALSE | HJ7: FALSE | HK7: FALSE | HL7: FALSE | HM7: FALSE | HN7: FALSE | HO7: FALSE | HP7: FALSE | HQ7: FALSE | HR7: FALSE | HS7: FALSE | HT7: FALSE | HU7: FALSE | HV7: FALSE | HW7: FALSE | HX7: FALSE | HY7: FALSE | HZ7: FALSE | IA7: FALSE | IB7: FALSE | IC7: FALSE | ID7: FALSE | IE7: FALSE | IF7: FALSE | IG7: FALSE | IH7: FALSE | II7: FALSE | IJ7: FALSE | IK7: FALSE | IL7: FALSE | IM7: FALSE | IN7: FALSE | IO7: FALSE | IP7: FALSE | IQ7: FALSE | IR7: FALSE | IS7: FALSE | IT7: FALSE | IU7: FALSE | IV7: FALSE | IW7: FALSE | IX7: FALSE | IY7: FALSE | IZ7: FALSE | JA7: FALSE | JB7: FALSE | JC7: FALSE | JD7: FALSE | JE7: FALSE | JF7: FALSE | JG7: FALSE | JH7: FALSE | JI7: FALSE | JJ7: FALSE | JK7: FALSE | JL7: FALSE | JM7: FALSE | JN7: FALSE | JO7: FALSE | JP7: FALSE | JQ7: FALSE | JR7: FALSE | JS7: FALSE | JT7: FALSE | JU7: FALSE | JV7: FALSE | JW7: FALSE | JX7: FALSE | JY7: FALSE | JZ7: FALSE | KA7: FALSE | KB7: FALSE | KC7: FALSE | KD7: FALSE | KE7: FALSE | KF7: FALSE | KG7: FALSE | KH7: FALSE | KI7: FALSE | KJ7: FALSE | KK7: FALSE | KL7: FALSE | KM7: FALSE | KN7: FALSE | KO7: FALSE | KP7: FALSE | KQ7: FALSE | KR7: FALSE | KS7: FALSE | KT7: FALSE | KU7: FALSE | KV7: FALSE | KW7: FALSE | KX7: FALSE | KY7: FALSE | KZ7: FALSE | LA7: FALSE | LB7: FALSE | LC7: FALSE | LD7: FALSE | LE7: FALSE | LF7: FALSE | LG7: FALSE | LH7: FALSE | LI7: FALSE | LJ7: FALSE | LK7: FALSE | LL7: FALSE | LM7: FALSE | LN7: FALSE | LO7: FALSE | LP7: FALSE | LQ7: FALSE | LR7: FALSE | LS7: FALSE | LT7: FALSE | LU7: FALSE | LV7: FALSE | LW7: FALSE | LX7: FALSE | LY7: FALSE | LZ7: FALSE | MA7: FALSE | MB7: FALSE | MC7: FALSE | MD7: FALSE | ME7: FALSE | MF7: FALSE | MG7: FALSE | MH7: FALSE | MI7: FALSE | MJ7: FALSE | MK7: FALSE | ML7: FALSE | MM7: FALSE | MN7: FALSE | MO7: FALSE | MP7: FALSE | MQ7: FALSE | MR7: FALSE | MS7: FALSE | MT7: FALSE | MU7: FALSE | MV7: FALSE | MW7: FALSE | MX7: FALSE | MY7: FALSE | MZ7: FALSE | NA7: FALSE | NB7: FALSE | NC7: FALSE | ND7: FALSE | NE7: FALSE | NF7: FALSE | NG7: FALSE | NH7: FALSE | NI7: FALSE | NJ7: FALSE | NK7: FALSE | NL7: FALSE | NM7: FALSE | NN7: FALSE | NO7: FALSE
A8: Smash Burger 2 | B8: FALSE | C8: FALSE | D8: FALSE | E8: FALSE | F8: FALSE | G8: FALSE | H8: FALSE | I8: FALSE | J8: FALSE | K8: FALSE | L8: FALSE | M8: FALSE | N8: FALSE | O8: FALSE | P8: FALSE | Q8: FALSE | R8: FALSE | S8: FALSE | T8: FALSE | U8: FALSE | V8: FALSE | W8: FALSE | X8: FALSE | Y8: FALSE | Z8: FALSE | AA8: FALSE | AB8: FALSE | AC8: FALSE | AD8: FALSE | AE8: FALSE | AF8: FALSE | AG8: FALSE | AH8: FALSE | AI8: FALSE | AJ8: FALSE | AK8: FALSE | AL8: FALSE | AM8: FALSE | AN8: FALSE | AO8: FALSE | AP8: FALSE | AQ8: FALSE | AR8: FALSE | AS8: FALSE | AT8: FALSE | AU8: FALSE | AV8: FALSE | AW8: FALSE | AX8: FALSE | AY8: FALSE | AZ8: FALSE | BA8: FALSE | BB8: FALSE | BC8: FALSE | BD8: FALSE | BE8: FALSE | BF8: FALSE | BG8: FALSE | BH8: FALSE | BI8: FALSE | BJ8: FALSE | BK8: FALSE | BL8: FALSE | BM8: FALSE | BN8: FALSE | BO8: FALSE | BP8: FALSE | BQ8: FALSE | BR8: FALSE | BS8: FALSE | BT8: FALSE | BU8: FALSE | BV8: FALSE | BW8: FALSE | BX8: FALSE | BY8: FALSE | BZ8: TRUE | CA8: FALSE | CB8: FALSE | CC8: FALSE | CD8: FALSE | CE8: FALSE | CF8: FALSE | CG8: FALSE | CH8: FALSE | CI8: FALSE | CJ8: FALSE | CK8: FALSE | CL8: FALSE | CM8: FALSE | CN8: FALSE | CO8: FALSE | CP8: FALSE | CQ8: FALSE | CR8: FALSE | CS8: FALSE | CT8: FALSE | CU8: FALSE | CV8: FALSE | CW8: FALSE | CX8: FALSE | CY8: FALSE | CZ8: FALSE | DA8: FALSE | DB8: FALSE | DC8: FALSE | DD8: FALSE | DE8: FALSE | DF8: FALSE | DG8: FALSE | DH8: FALSE | DI8: FALSE | DJ8: FALSE | DK8: FALSE | DL8: FALSE | DM8: FALSE | DN8: FALSE | DO8: FALSE | DP8: FALSE | DQ8: FALSE | DR8: TRUE | DS8: TRUE | DT8: TRUE | DU8: TRUE | DV8: TRUE | DW8: FALSE | DX8: FALSE | DY8: FALSE | DZ8: FALSE | EA8: FALSE | EB8: FALSE | EC8: TRUE | ED8: FALSE | EE8: FALSE | EF8: FALSE | EG8: FALSE | EH8: FALSE | EI8: FALSE | EJ8: FALSE | EK8: FALSE | EL8: FALSE | EM8: FALSE | EN8: FALSE | EO8: FALSE | EP8: FALSE | EQ8: FALSE | ER8: FALSE | ES8: FALSE | ET8: FALSE | EU8: FALSE | EV8: FALSE | EW8: TRUE | EX8: FALSE | EY8: FALSE | EZ8: FALSE | FA8: FALSE | FB8: FALSE | FC8: FALSE | FD8: FALSE | FE8: FALSE | FF8: FALSE | FG8: FALSE | FH8: FALSE | FI8: FALSE | FJ8: FALSE | FK8: FALSE | FL8: FALSE | FM8: FALSE | FN8: FALSE | FO8: FALSE | FP8: FALSE | FQ8: FALSE | FR8: FALSE | FS8: FALSE | FT8: TRUE | FU8: FALSE | FV8: FALSE | FW8: FALSE | FX8: FALSE | FY8: FALSE | FZ8: FALSE | GA8: FALSE | GB8: FALSE | GC8: FALSE | GD8: FALSE | GE8: FALSE | GF8: FALSE | GG8: FALSE | GH8: FALSE | GI8: FALSE | GJ8: FALSE | GK8: FALSE | GL8: FALSE | GM8: FALSE | GN8: FALSE | GO8: FALSE | GP8: FALSE | GQ8: FALSE | GR8: FALSE | GS8: FALSE | GT8: FALSE | GU8: FALSE | GV8: FALSE | GW8: FALSE | GX8: FALSE | GY8: FALSE | GZ8: FALSE | HA8: FALSE | HB8: FALSE | HC8: FALSE | HD8: FALSE | HE8: FALSE | HF8: FALSE | HG8: FALSE | HH8: TRUE | HI8: TRUE | HJ8: TRUE | HK8: FALSE | HL8: FALSE | HM8: FALSE | HN8: FALSE | HO8: TRUE | HP8: FALSE | HQ8: TRUE | HR8: FALSE | HS8: FALSE | HT8: FALSE | HU8: FALSE | HV8: FALSE | HW8: FALSE | HX8: FALSE | HY8: FALSE | HZ8: FALSE | IA8: FALSE | IB8: FALSE | IC8: FALSE | ID8: FALSE | IE8: FALSE | IF8: FALSE | IG8: FALSE | IH8: FALSE | II8: FALSE | IJ8: FALSE | IK8: FALSE | IL8: FALSE | IM8: FALSE | IN8: FALSE | IO8: FALSE | IP8: FALSE | IQ8: FALSE | IR8: FALSE | IS8: FALSE | IT8: FALSE | IU8: FALSE | IV8: FALSE | IW8: FALSE | IX8: FALSE | IY8: FALSE | IZ8: FALSE | JA8: FALSE | JB8: FALSE | JC8: FALSE | JD8: FALSE | JE8: FALSE | JF8: FALSE | JG8: FALSE | JH8: FALSE | JI8: FALSE | JJ8: FALSE | JK8: FALSE | JL8: FALSE | JM8: FALSE | JN8: FALSE | JO8: FALSE | JP8: FALSE | JQ8: FALSE | JR8: FALSE | JS8: FALSE | JT8: FALSE | JU8: FALSE | JV8: FALSE | JW8: FALSE | JX8: FALSE | JY8: FALSE | JZ8: FALSE | KA8: FALSE | KB8: FALSE | KC8: FALSE | KD8: FALSE | KE8: FALSE | KF8: FALSE | KG8: FALSE | KH8: FALSE | KI8: FALSE | KJ8: FALSE | KK8: FALSE | KL8: FALSE | KM8: FALSE | KN8: FALSE | KO8: FALSE | KP8: FALSE | KQ8: FALSE | KR8: FALSE | KS8: FALSE | KT8: FALSE | KU8: FALSE | KV8: FALSE | KW8: FALSE | KX8: FALSE | KY8: FALSE | KZ8: FALSE | LA8: FALSE | LB8: FALSE | LC8: FALSE | LD8: FALSE | LE8: FALSE | LF8: FALSE | LG8: FALSE | LH8: FALSE | LI8: FALSE | LJ8: FALSE | LK8: FALSE | LL8: FALSE | LM8: FALSE | LN8: FALSE | LO8: FALSE | LP8: FALSE | LQ8: FALSE | LR8: FALSE | LS8: FALSE | LT8: FALSE | LU8: FALSE | LV8: FALSE | LW8: FALSE | LX8: FALSE | LY8: FALSE | LZ8: FALSE | MA8: FALSE | MB8: FALSE | MC8: FALSE | MD8: FALSE | ME8: FALSE | MF8: FALSE | MG8: FALSE | MH8: FALSE | MI8: FALSE | MJ8: FALSE | MK8: FALSE | ML8: FALSE | MM8: FALSE | MN8: FALSE | MO8: FALSE | MP8: FALSE | MQ8: FALSE | MR8: FALSE | MS8: FALSE | MT8: FALSE | MU8: FALSE | MV8: FALSE | MW8: FALSE | MX8: FALSE | MY8: FALSE | MZ8: FALSE | NA8: FALSE | NB8: FALSE | NC8: FALSE | ND8: FALSE | NE8: FALSE | NF8: FALSE | NG8: FALSE | NH8: FALSE | NI8: FALSE | NJ8: FALSE | NK8: FALSE | NL8: FALSE | NM8: FALSE | NN8: FALSE | NO8: FALSE
A9: Loaded Burger | B9: FALSE | C9: FALSE | D9: FALSE | E9: FALSE | F9: FALSE | G9: FALSE | H9: FALSE | I9: FALSE | J9: FALSE | K9: FALSE | L9: FALSE | M9: FALSE | N9: FALSE | O9: FALSE | P9: FALSE | Q9: FALSE | R9: FALSE | S9: FALSE | T9: FALSE | U9: FALSE | V9: FALSE | W9: FALSE | X9: FALSE | Y9: FALSE | Z9: FALSE | AA9: FALSE | AB9: FALSE | AC9: FALSE | AD9: FALSE | AE9: FALSE | AF9: FALSE | AG9: FALSE | AH9: FALSE | AI9: FALSE | AJ9: FALSE | AK9: FALSE | AL9: FALSE | AM9: FALSE | AN9: FALSE | AO9: FALSE | AP9: FALSE | AQ9: FALSE | AR9: FALSE | AS9: FALSE | AT9: FALSE | AU9: FALSE | AV9: FALSE | AW9: FALSE | AX9: FALSE | AY9: FALSE | AZ9: FALSE | BA9: FALSE | BB9: FALSE | BC9: FALSE | BD9: FALSE | BE9: FALSE | BF9: FALSE | BG9: FALSE | BH9: FALSE | BI9: FALSE | BJ9: FALSE | BK9: FALSE | BL9: FALSE | BM9: FALSE | BN9: FALSE | BO9: FALSE | BP9: FALSE | BQ9: FALSE | BR9: FALSE | BS9: FALSE | BT9: FALSE | BU9: FALSE | BV9: FALSE | BW9: FALSE | BX9: FALSE | BY9: FALSE | BZ9: TRUE | CA9: FALSE | CB9: FALSE | CC9: FALSE | CD9: FALSE | CE9: FALSE | CF9: FALSE | CG9: FALSE | CH9: FALSE | CI9: FALSE | CJ9: FALSE | CK9: FALSE | CL9: FALSE | CM9: FALSE | CN9: FALSE | CO9: FALSE | CP9: FALSE | CQ9: FALSE | CR9: FALSE | CS9: FALSE | CT9: FALSE | CU9: FALSE | CV9: FALSE | CW9: FALSE | CX9: FALSE | CY9: FALSE | CZ9: FALSE | DA9: FALSE | DB9: FALSE | DC9: FALSE | DD9: FALSE | DE9: FALSE | DF9: FALSE | DG9: FALSE | DH9: FALSE | DI9: FALSE | DJ9: FALSE | DK9: FALSE | DL9: FALSE | DM9: FALSE | DN9: FALSE | DO9: FALSE | DP9: FALSE | DQ9: FALSE | DR9: FALSE | DS9: FALSE | DT9: FALSE | DU9: FALSE | DV9: FALSE | DW9: FALSE | DX9: FALSE | DY9: FALSE | DZ9: FALSE | EA9: FALSE | EB9: FALSE | EC9: FALSE | ED9: FALSE | EE9: FALSE | EF9: FALSE | EG9: FALSE | EH9: FALSE | EI9: FALSE | EJ9: FALSE | EK9: FALSE | EL9: FALSE | EM9: FALSE | EN9: FALSE | EO9: FALSE | EP9: FALSE | EQ9: FALSE | ER9: FALSE | ES9: FALSE | ET9: FALSE | EU9: FALSE | EV9: FALSE | EW9: FALSE | EX9: FALSE | EY9: FALSE | EZ9: FALSE | FA9: FALSE | FB9: FALSE | FC9: FALSE | FD9: FALSE | FE9: FALSE | FF9: FALSE | FG9: FALSE | FH9: FALSE | FI9: FALSE | FJ9: FALSE | FK9: FALSE | FL9: FALSE | FM9: FALSE | FN9: FALSE | FO9: FALSE | FP9: FALSE | FQ9: FALSE | FR9: FALSE | FS9: FALSE | FT9: FALSE | FU9: FALSE | FV9: FALSE | FW9: FALSE | FX9: FALSE | FY9: FALSE | FZ9: FALSE | GA9: FALSE | GB9: FALSE | GC9: FALSE | GD9: FALSE | GE9: FALSE | GF9: FALSE | GG9: FALSE | GH9: FALSE | GI9: FALSE | GJ9: FALSE | GK9: FALSE | GL9: FALSE | GM9: FALSE | GN9: FALSE | GO9: FALSE | GP9: FALSE | GQ9: FALSE | GR9: FALSE | GS9: FALSE | GT9: FALSE | GU9: FALSE | GV9: FALSE | GW9: FALSE | GX9: FALSE | GY9: FALSE | GZ9: FALSE | HA9: FALSE | HB9: FALSE | HC9: FALSE | HD9: FALSE | HE9: FALSE | HF9: FALSE | HG9: FALSE | HH9: FALSE | HI9: FALSE | HJ9: FALSE | HK9: FALSE | HL9: FALSE | HM9: FALSE | HN9: FALSE | HO9: FALSE | HP9: FALSE | HQ9: FALSE | HR9: FALSE | HS9: FALSE | HT9: FALSE | HU9: FALSE | HV9: FALSE | HW9: FALSE | HX9: FALSE | HY9: FALSE | HZ9: FALSE | IA9: FALSE | IB9: FALSE | IC9: FALSE | ID9: FALSE | IE9: FALSE | IF9: FALSE | IG9: FALSE | IH9: FALSE | II9: FALSE | IJ9: FALSE | IK9: FALSE | IL9: FALSE | IM9: FALSE | IN9: FALSE | IO9: FALSE | IP9: FALSE | IQ9: FALSE | IR9: FALSE | IS9: FALSE | IT9: FALSE | IU9: FALSE | IV9: FALSE | IW9: FALSE | IX9: FALSE | IY9: FALSE | IZ9: FALSE | JA9: FALSE | JB9: FALSE | JC9: FALSE | JD9: FALSE | JE9: FALSE | JF9: FALSE | JG9: FALSE | JH9: FALSE | JI9: FALSE | JJ9: FALSE | JK9: FALSE | JL9: FALSE | JM9: FALSE | JN9: FALSE | JO9: FALSE | JP9: FALSE | JQ9: FALSE | JR9: FALSE | JS9: FALSE | JT9: FALSE | JU9: FALSE | JV9: FALSE | JW9: FALSE | JX9: FALSE | JY9: FALSE | JZ9: FALSE | KA9: FALSE | KB9: FALSE | KC9: FALSE | KD9: FALSE | KE9: FALSE | KF9: FALSE | KG9: FALSE | KH9: FALSE | KI9: FALSE | KJ9: FALSE | KK9: FALSE | KL9: FALSE | KM9: FALSE | KN9: FALSE | KO9: FALSE | KP9: FALSE | KQ9: FALSE | KR9: FALSE | KS9: FALSE | KT9: FALSE | KU9: FALSE | KV9: FALSE | KW9: FALSE | KX9: FALSE | KY9: FALSE | KZ9: FALSE | LA9: FALSE | LB9: FALSE | LC9: FALSE | LD9: FALSE | LE9: FALSE | LF9: FALSE | LG9: FALSE | LH9: FALSE | LI9: FALSE | LJ9: FALSE | LK9: FALSE | LL9: FALSE | LM9: FALSE | LN9: FALSE | LO9: FALSE | LP9: FALSE | LQ9: FALSE | LR9: FALSE | LS9: FALSE | LT9: FALSE | LU9: FALSE | LV9: FALSE | LW9: FALSE | LX9: FALSE | LY9: FALSE | LZ9: FALSE | MA9: FALSE | MB9: FALSE | MC9: FALSE | MD9: FALSE | ME9: FALSE | MF9: FALSE | MG9: FALSE | MH9: FALSE | MI9: FALSE | MJ9: FALSE | MK9: FALSE | ML9: FALSE | MM9: FALSE | MN9: FALSE | MO9: FALSE | MP9: FALSE | MQ9: FALSE | MR9: FALSE | MS9: FALSE | MT9: FALSE | MU9: FALSE | MV9: FALSE | MW9: FALSE | MX9: FALSE | MY9: FALSE | MZ9: FALSE | NA9: FALSE | NB9: FALSE | NC9: FALSE | ND9: FALSE | NE9: FALSE | NF9: FALSE | NG9: FALSE | NH9: FALSE | NI9: FALSE | NJ9: FALSE | NK9: FALSE | NL9: FALSE | NM9: FALSE | NN9: FALSE | NO9: FALSE
